Workbook

Sheet CONTROL DE RAZAGOS
B1: CONTROL DE REZAGOS | E1: DEL | H1: al | K1: OBSERVACIONES
A3: CODIGO | B3: NOMBRE Y APELLIDO | C3: CODIGO | D3: LUNES | E3: MARTES | F3: MIERCOLES | G3: JUEVES | H3: VIERNES | I3: SABADO | J3: TOTAL
A4: 1 | B4: =+'SEMANA DEL 2 AL 7-3-26'!A5 -> ALCIDES CORREA | C4: AC
A5: =+A4+1 -> 2 | B5: =+'SEMANA DEL 2 AL 7-3-26'!A7 -> BLANCA ALVARADO | C5: BNA
A6: =+A5+1 -> 3 | B6: =+'SEMANA DEL 2 AL 7-3-26'!A8 -> ESPERANZA REY | C6: E.R
A7: =+A6+1 -> 4 | B7: =+'SEMANA DEL 2 AL 7-3-26'!A9 -> ELIZABETH REYES SERRANO | C7: E.R.S
A8: =+A7+1 -> 5 | B8: =+'SEMANA DEL 2 AL 7-3-26'!A10 -> ELVIRA LOPEZ | C8: E.L
A9: =+A8+1 -> 6 | B9: =+'SEMANA DEL 2 AL 7-3-26'!A11 -> ERNESTO REYES | C9: E.REYES
A10: =+A9+1 -> 7 | B10: =+'SEMANA DEL 2 AL 7-3-26'!A12 -> GUILLERMO ZAMBRANO | C10: G.Z
A11: =+A10+1 -> 8 | B11: =+'SEMANA DEL 2 AL 7-3-26'!#REF! -> #REF! | C11: G.R
A12: =+A11+1 -> 9 | B12: =+'SEMANA DEL 2 AL 7-3-26'!A13 -> HUGO ALMEIDA | C12: H.A
A13: =+A12+1 -> 10 | B13: =+'SEMANA DEL 2 AL 7-3-26'!A14 -> HILDA SERRANO | C13: H.S
A14: =+A13+1 -> 11 | B14: =+'SEMANA DEL 2 AL 7-3-26'!A15 -> HUMBERTO LUNA | C14: H.L
A15: =+A14+1 -> 12 | B15: =+'SEMANA DEL 2 AL 7-3-26'!A16 -> JOSE EBLAN GIRON | C15: J.E.G
A16: =+A15+1 -> 13 | B16: =+'SEMANA DEL 2 AL 7-3-26'!A17 -> JOSE JURADO | C16: J,J
A17: =+A16+1 -> 14 | B17: =+'SEMANA DEL 2 AL 7-3-26'!A18 -> KARINA SILVA | C17: K.S
A18: =+A17+1 -> 15 | B18: =+'SEMANA DEL 2 AL 7-3-26'!A19 -> LUZ MERY ABAUNZA | C18: L.M.A
A19: =+A18+1 -> 16 | B19: =+'SEMANA DEL 2 AL 7-3-26'!A20 -> LUIS ROJAS | C19: L,R
A20: =+A19+1 -> 17 | B20: =+'SEMANA DEL 2 AL 7-3-26'!A21 -> LUIS VALDERRAMA | C20: L.V.C
A21: =+A20+1 -> 18 | B21: =+'SEMANA DEL 2 AL 7-3-26'!A22 -> LILIANA VEGA | C21: L,V
A22: =+A21+1 -> 19 | B22: =+'SEMANA DEL 2 AL 7-3-26'!A23 -> LUIS ERNESTO ALMEIDA | C22: L.E.A
A23: =+A22+1 -> 20 | B23: =+'SEMANA DEL 2 AL 7-3-26'!A24 -> LEIDY SERRANO | C23: L.S.S
... A25: =+A24+1 -> 22 | B25: =+'SEMANA DEL 2 AL 7-3-26'!A26 -> MARTHA SILVA | C25: M.S.
A26: =+A25+1 -> 23 | B26: =+'SEMANA DEL 2 AL 7-3-26'!A29 -> MARIA MEDINA | C26: M.M.
A27: =+A26+1 -> 24 | B27: =+'SEMANA DEL 2 AL 7-3-26'!#REF! -> #REF! | C27: M.E.C
A28: =+A27+1 -> 25 | B28: =+'SEMANA DEL 2 AL 7-3-26'!#REF! -> #REF! | C28: P.A
A29: =+A28+1 -> 26 | B29: =+'SEMANA DEL 2 AL 7-3-26'!A30 -> PETTER BENAVIDES | C29: P.B
A30: =+A29+1 -> 27 | B30: =+'SEMANA DEL 2 AL 7-3-26'!A31 -> RAMON PARRA | C30: R.P
A31: =+A30+1 -> 28 | B31: =+'SEMANA DEL 2 AL 7-3-26'!A32 -> SULAY ALMEIDA | C31: S.A
A32: =+A31+1 -> 29 | B32: =+'SEMANA DEL 2 AL 7-3-26'!#REF! -> #REF! | C32: R.A
A33: =+A32+1 -> 30 | B33: =+'SEMANA DEL 2 AL 7-3-26'!A33 -> RENE ALMEIDA | C33: H.R.A
A34: =+A33+1 -> 31 | B34: =+'SEMANA DEL 2 AL 7-3-26'!A34 -> RUBIELA MARTINEZ | C34: R.M.D
A35: =+A34+1 -> 32 | B35: =+'SEMANA DEL 2 AL 7-3-26'!A35 -> ROSMIRA DURAN | C35: R.D.
A36: =+A35+1 -> 33 | B36: =+'SEMANA DEL 2 AL 7-3-26'!#REF! -> #REF! | C36: R.R.
A37: =+A36+1 -> 34 | B37: =+'SEMANA DEL 2 AL 7-3-26'!A36 -> ROSALBA MATAGIRA | C37: R.M.
A38: =+A37+1 -> 35 | B38: =+'SEMANA DEL 2 AL 7-3-26'!#REF! -> #REF! | C38: R.C
A39: =+A38+1 -> 36 | B39: =+'SEMANA DEL 2 AL 7-3-26'!A37 -> STELLA SILVA | C39: S.SILVA
A40: =+A39+1 -> 37 | B40: =+'SEMANA DEL 2 AL 7-3-26'!#REF! -> #REF! | C40: A.S
A41: =+A40+1 -> 38 | B41: =+'SEMANA DEL 2 AL 7-3-26'!#REF! -> #REF! | C41: T.R
A42: =+A41+1 -> 39 | B42: =+'SEMANA DEL 2 AL 7-3-26'!A40 -> YENDER PADILLA | C42: Y.P
A43: =+A42+1 -> 40 | B43: =+'SEMANA DEL 2 AL 7-3-26'!A42 -> YARIRETH ROA | C43: Y.R.
A44: =+A43+1 -> 41 | B44: =+'SEMANA DEL 2 AL 7-3-26'!A43 -> YOLI BECERRA | C44: Y.B
A45: =+A44+1 -> 42 | B45: =+'SEMANA DEL 2 AL 7-3-26'!A44 -> MUESTRAS SRA MARIA
A46: =+A45+1 -> 43 | B46: =+'SEMANA DEL 2 AL 7-3-26'!A45 -> 0
B47: =+'SEMANA DEL 2 AL 7-3-26'!A47 -> 0

Sheet CONTROL DE CALIDAD 
A1: CONTROL DE REZAGOS
A3: ENCINTADOS
A4: CORTOS LA MEDIDA
A5: ROTOS
A6: DESCONADOS
A7: PERILLAS MALAS
A8: TABACO TRIPUDO

Sheet ENTREGA CESTAS 
E1: DEL | H1: al
A3: CODIGO | B3: NOMBRE Y APELLIDO | C3: CODIGO | D3: LUNES | E3: MARTES | F3: MIERCOLES | G3: JUEVES | H3: VIERNES | I3: SABADO | J3: TOTAL
A4: 1 | B4: =+'SEMANA DEL 2 AL 7-3-26'!A5 -> ALCIDES CORREA
A5: =+A4+1 -> 2 | B5: =+'SEMANA DEL 2 AL 7-3-26'!A6 -> ALBA SANABRIA
A6: =+A5+1 -> 3 | B6: =+'SEMANA DEL 2 AL 7-3-26'!A7 -> BLANCA ALVARADO
A7: =+A6+1 -> 4 | B7: =+'SEMANA DEL 2 AL 7-3-26'!A8 -> ESPERANZA REY
A8: =+A7+1 -> 5 | B8: =+'SEMANA DEL 2 AL 7-3-26'!A9 -> ELIZABETH REYES SERRANO
A9: =+A8+1 -> 6 | B9: =+'SEMANA DEL 2 AL 7-3-26'!A10 -> ELVIRA LOPEZ
A10: =+A9+1 -> 7 | B10: =+'SEMANA DEL 2 AL 7-3-26'!A11 -> ERNESTO REYES
A11: =+A10+1 -> 8 | B11: =+'SEMANA DEL 2 AL 7-3-26'!A12 -> GUILLERMO ZAMBRANO
A12: =+A11+1 -> 9 | B12: =+'SEMANA DEL 2 AL 7-3-26'!A13 -> HUGO ALMEIDA
A13: =+A12+1 -> 10 | B13: =+'SEMANA DEL 2 AL 7-3-26'!A14 -> HILDA SERRANO
A14: =+A13+1 -> 11 | B14: =+'SEMANA DEL 2 AL 7-3-26'!A15 -> HUMBERTO LUNA
A15: =+A14+1 -> 12 | B15: =+'SEMANA DEL 2 AL 7-3-26'!A16 -> JOSE EBLAN GIRON
A16: =+A15+1 -> 13 | B16: =+'SEMANA DEL 2 AL 7-3-26'!A17 -> JOSE JURADO
... A49: =+A48+1 -> 46 | B49: =+'SEMANA DEL 2 AL 7-3-26'!A50 -> 0
A50: =+A49+1 -> 47 | B50: =+'SEMANA DEL 2 AL 7-3-26'!A54 -> 0

Sheet ENTREGA MATERIAL 
D1: FECHA
A2: No | B2: NOMBRE | C2: CAPA | D2: CAPOTE | E2: PICADURA | F2: CESTAS
A3: 1 | B3: =+'SEMANA DEL 2 AL 7-3-26'!A5 -> ALCIDES CORREA
A4: =+A3+1 -> 2 | B4: =+'SEMANA DEL 2 AL 7-3-26'!A6 -> ALBA SANABRIA
A5: =+A4+1 -> 3 | B5: =+'SEMANA DEL 2 AL 7-3-26'!A7 -> BLANCA ALVARADO
A6: =+A5+1 -> 4 | B6: =+'SEMANA DEL 2 AL 7-3-26'!A8 -> ESPERANZA REY
A7: =+A6+1 -> 5 | B7: =+'SEMANA DEL 2 AL 7-3-26'!A9 -> ELIZABETH REYES SERRANO
A8: =+A7+1 -> 6 | B8: =+'SEMANA DEL 2 AL 7-3-26'!A10 -> ELVIRA LOPEZ
A9: =+A8+1 -> 7 | B9: =+'SEMANA DEL 2 AL 7-3-26'!A11 -> ERNESTO REYES
A10: =+A9+1 -> 8 | B10: =+'SEMANA DEL 2 AL 7-3-26'!A12 -> GUILLERMO ZAMBRANO
A11: =+A10+1 -> 9 | B11: =+'SEMANA DEL 2 AL 7-3-26'!A13 -> HUGO ALMEIDA
A12: =+A11+1 -> 10 | B12: =+'SEMANA DEL 2 AL 7-3-26'!A14 -> HILDA SERRANO
A13: =+A12+1 -> 11 | B13: =+'SEMANA DEL 2 AL 7-3-26'!A15 -> HUMBERTO LUNA
A14: =+A13+1 -> 12 | B14: =+'SEMANA DEL 2 AL 7-3-26'!A16 -> JOSE EBLAN GIRON
A15: =+A14+1 -> 13 | B15: =+'SEMANA DEL 2 AL 7-3-26'!A17 -> JOSE JURADO
... A45: =+A44+1 -> 43 | B45: =+'SEMANA DEL 2 AL 7-3-26'!A47 -> 0
A46: =+A45+1 -> 44 | B46: =+'SEMANA DEL 2 AL 7-3-26'!A51 -> 0
A47: =+A46+1 -> 45 | B47: =+'SEMANA DEL 2 AL 7-3-26'!A52 -> 0
A48: =+A47+1 -> 46 | B48: =+'SEMANA DEL 2 AL 7-3-26'!A53 -> 0
A49: =+A48+1 -> 47 | B49: =+'SEMANA DEL 2 AL 7-3-26'!A54 -> 0
B50: =+'SEMANA DEL 2 AL 7-3-26'!A55 -> 0

Sheet RECP-TAB-FAB
A1: RECEPCION DE CESTAS DE TABACOS FABRIQUINES | H1: al | J1: 2023
E2: LLEVAN | J2: TRAEN
A3: CODIGO | B3: NOMBRE Y APELLIDO | C3: CODIGO | D3: AMARILLAS | E3: AZULES | F3: ROJAS | G3: NEGRAS | H3: TOTAL | I3: AMARILLAS | J3: AZULES | K3: ROJAS | L3: NEGRAS | M3: TOTAL
A4: 1 | B4: =+'SEMANA DEL 2 AL 7-3-26'!A5 -> ALCIDES CORREA
A5: =+A4+1 -> 2 | B5: =+'SEMANA DEL 2 AL 7-3-26'!A7 -> BLANCA ALVARADO
A6: =+A5+1 -> 3 | B6: =+'SEMANA DEL 2 AL 7-3-26'!#REF! -> #REF!
A7: =+A6+1 -> 4 | B7: =+'SEMANA DEL 2 AL 7-3-26'!#REF! -> #REF!
A8: =+A7+1 -> 5 | B8: =+'SEMANA DEL 2 AL 7-3-26'!#REF! -> #REF!
A9: =+A8+1 -> 6 | B9: =+'SEMANA DEL 2 AL 7-3-26'!A9 -> ELIZABETH REYES SERRANO
A10: =+A9+1 -> 7 | B10: =+'SEMANA DEL 2 AL 7-3-26'!A10 -> ELVIRA LOPEZ
A11: =+A10+1 -> 8 | B11: =+'SEMANA DEL 2 AL 7-3-26'!A11 -> ERNESTO REYES
A12: =+A11+1 -> 9 | B12: =+'SEMANA DEL 2 AL 7-3-26'!A12 -> GUILLERMO ZAMBRANO
A13: =+A12+1 -> 10 | B13: =+'SEMANA DEL 2 AL 7-3-26'!#REF! -> #REF!
A14: =+A13+1 -> 11 | B14: =+'SEMANA DEL 2 AL 7-3-26'!A13 -> HUGO ALMEIDA
A15: =+A14+1 -> 12 | B15: =+'SEMANA DEL 2 AL 7-3-26'!A14 -> HILDA SERRANO
A16: =+A15+1 -> 13 | B16: =+'SEMANA DEL 2 AL 7-3-26'!A15 -> HUMBERTO LUNA
A17: =+A16+1 -> 14 | B17: =+'SEMANA DEL 2 AL 7-3-26'!A16 -> JOSE EBLAN GIRON
A18: =+A17+1 -> 15 | B18: =+'SEMANA DEL 2 AL 7-3-26'!A17 -> JOSE JURADO
A19: =+A18+1 -> 16 | B19: =+'SEMANA DEL 2 AL 7-3-26'!A18 -> KARINA SILVA
A20: =+A19+1 -> 17 | B20: =+'SEMANA DEL 2 AL 7-3-26'!A19 -> LUZ MERY ABAUNZA
A21: =+A20+1 -> 18 | B21: =+'SEMANA DEL 2 AL 7-3-26'!A20 -> LUIS ROJAS
A22: =+A21+1 -> 19 | B22: =+'SEMANA DEL 2 AL 7-3-26'!A21 -> LUIS VALDERRAMA
A23: =+A22+1 -> 20 | B23: =+'SEMANA DEL 2 AL 7-3-26'!A22 -> LILIANA VEGA
A24: =+A23+1 -> 21 | B24: =+'SEMANA DEL 2 AL 7-3-26'!A23 -> LUIS ERNESTO ALMEIDA
A25: =+A24+1 -> 22 | B25: =+'SEMANA DEL 2 AL 7-3-26'!A25 -> MAYERLIN BOLIVAR
A26: =+A25+1 -> 23 | B26: =+'SEMANA DEL 2 AL 7-3-26'!A26 -> MARTHA SILVA
A27: =+A26+1 -> 24 | B27: =+'SEMANA DEL 2 AL 7-3-26'!#REF! -> #REF!
A28: =+A27+1 -> 25 | B28: =+'SEMANA DEL 2 AL 7-3-26'!#REF! -> #REF!
A29: =+A28+1 -> 26 | B29: =+'SEMANA DEL 2 AL 7-3-26'!A29 -> MARIA MEDINA
A30: =+A29+1 -> 27 | B30: =+'SEMANA DEL 2 AL 7-3-26'!#REF! -> #REF!
A31: =+A30+1 -> 28 | B31: =+'SEMANA DEL 2 AL 7-3-26'!A31 -> RAMON PARRA
A32: =+A31+1 -> 29 | B32: =+'SEMANA DEL 2 AL 7-3-26'!A32 -> SULAY ALMEIDA
A33: =+A32+1 -> 30 | B33: =+'SEMANA DEL 2 AL 7-3-26'!A33 -> RENE ALMEIDA
A34: =+A33+1 -> 31 | B34: =+'SEMANA DEL 2 AL 7-3-26'!A34 -> RUBIELA MARTINEZ
A35: =+A34+1 -> 32 | B35: =+'SEMANA DEL 2 AL 7-3-26'!A35 -> ROSMIRA DURAN
A36: =+A35+1 -> 33 | B36: =+'SEMANA DEL 2 AL 7-3-26'!#REF! -> #REF!
A37: =+A36+1 -> 34 | B37: =+'SEMANA DEL 2 AL 7-3-26'!A36 -> ROSALBA MATAGIRA
A38: =+A37+1 -> 35 | B38: =+'SEMANA DEL 2 AL 7-3-26'!#REF! -> #REF!
A39: =+A38+1 -> 36 | B39: =+'SEMANA DEL 2 AL 7-3-26'!A37 -> STELLA SILVA
A40: =+A39+1 -> 37 | B40: =+'SEMANA DEL 2 AL 7-3-26'!#REF! -> #REF!
A41: =+A40+1 -> 38 | B41: =+'SEMANA DEL 2 AL 7-3-26'!#REF! -> #REF!
A42: =+A41+1 -> 39 | B42: =+'SEMANA DEL 2 AL 7-3-26'!A42 -> YARIRETH ROA
A43: =+A42+1 -> 40 | B43: =+'SEMANA DEL 2 AL 7-3-26'!A43 -> YOLI BECERRA
A44: =+A43+1 -> 41 | B44: =+'SEMANA DEL 2 AL 7-3-26'!A45 -> 0
A45: =+A44+1 -> 42 | B45: =+'SEMANA DEL 2 AL 7-3-26'!A46 -> 0
A46: =+A45+1 -> 43 | B46: =+'SEMANA DEL 2 AL 7-3-26'!A47 -> 0
A47: =+A46+1 -> 44 | B47: =+'SEMANA DEL 2 AL 7-3-26'!A48 -> 0
A48: =+A47+1 -> 45 | B48: =+'SEMANA DEL 2 AL 7-3-26'!A49 -> 0

Sheet ACUM-RES
C1: MES ENERO 2025
D2: =+'ACUM-DET'!BN30 -> #REF!
B4: MATERIALES | C4: SALDO INI | D4: LLEVAN | E4: TOTAL | F4: PAGA | G4: SALDO
B5: CAPA | C5: =+'ACUM-DET'!B39 -> 0 | D5: =+'ACUM-DET'!R39 -> #REF! | E5: =+C5+D5 -> #REF! | F5: =+'ACUM-DET'!AH30 -> #REF! | G5: =E5-F5 -> #REF!
B6: CAPOTE | C6: =+'ACUM-DET'!C39 -> 0 | D6: =+'ACUM-DET'!S39 -> #REF! | E6: =+C6+D6 -> #REF! | F6: =+'ACUM-DET'!AI30 -> #REF! | G6: =E6-F6 -> #REF!
B8: PICADURA FC | C8: =+'ACUM-DET'!D39 -> 0 | D8: =+'ACUM-DET'!T39 -> #REF! | E8: =+C8+D8 -> #REF! | F8: =+'ACUM-DET'!AJ30 -> #REF! | G8: =E8-F8 -> #REF!
E9: =+C9+D9 -> 0 | G9: =E9-F9 -> 0
E10: =+C10+D10 -> 0 | G10: =E10-F10 -> 0
B11: CESTAS | C11: =+'ACUM-DET'!E39 -> 0 | D11: =+'ACUM-DET'!U39 -> #REF! | E11: =+C11+D11 -> #REF! | F11: =+'ACUM-DET'!AK30 -> #REF! | G11: =E11-F11 -> #REF!
B12: SUMINISTROS | E12: =+C12+D12 -> 0 | G12: =E12-F12 -> 0
B13: SACAS | C13: =+'ACUM-DET'!F39 -> 0 | D13: =+'ACUM-DET'!V39 -> #REF! | E13: =+C13+D13 -> #REF! | F13: =+'ACUM-DET'!AL30 -> #REF! | G13: =E13-F13 -> #REF!
B14: GOMA | C14: =+'ACUM-DET'!G39 -> 0 | D14: =+'ACUM-DET'!W39 -> #REF! | E14: =+C14+D14 -> #REF! | F14: =+'ACUM-DET'!AN30 -> #REF! | G14: =E14-F14 -> #REF!
B15: MARCADOR | C15: =+'ACUM-DET'!H39 -> 0 | D15: =+'ACUM-DET'!X30 -> #REF! | E15: =+C15+D15 -> #REF! | F15: =+'ACUM-DET'!AN30 -> #REF! | G15: =E15-F15 -> #REF!
B16: PAPEL | C16: =+'ACUM-DET'!I39 -> 0 | D16: =+'ACUM-DET'!Y30 -> #REF! | E16: =+C16+D16 -> #REF! | F16: =+'ACUM-DET'!AO30 -> #REF! | G16: =E16-F16 -> #REF!
B17: RESORTES | C17: =+'ACUM-DET'!J39 -> 0 | D17: =+'ACUM-DET'!Z30 -> #REF! | E17: =+C17+D17 -> #REF! | F17: =+'ACUM-DET'!AP30 -> #REF! | G17: =E17-F17 -> #REF!
B18: PACORAS | C18: =+'ACUM-DET'!K39 -> 0 | D18: =+'ACUM-DET'!AA30 -> #REF! | E18: =+C18+D18 -> #REF! | F18: =+'ACUM-DET'!AQ30 -> #REF! | G18: =E18-F18 -> #REF!
B19: MAQUINAS | C19: =+'ACUM-DET'!L39 -> 0 | D19: =+'ACUM-DET'!AB30 -> #REF! | E19: =+C19+D19 -> #REF! | F19: =+'ACUM-DET'!AR30 -> #REF! | G19: =E19-F19 -> #REF!
B20: TRAPOS | C20: =+'ACUM-DET'!M39 -> 0 | D20: =+'ACUM-DET'!AC30 -> #REF! | E20: =+C20+D20 -> #REF! | F20: =+'ACUM-DET'!AS30 -> #REF! | G20: =E20-F20 -> #REF!
B21: SILLAS | C21: =+'ACUM-DET'!N39 -> 0 | D21: =+'ACUM-DET'!AD30 -> #REF! | E21: =+C21+D21 -> #REF! | F21: =+'ACUM-DET'!AT30 -> #REF! | G21: =E21-F21 -> #REF!
B22: PRENSA | C22: =+'ACUM-DET'!O39 -> 0 | D22: =+'ACUM-DET'!AE30 -> #REF! | E22: =+C22+D22 -> #REF! | F22: =+'ACUM-DET'!AU30 -> #REF! | G22: =E22-F22 -> #REF!
B23: CORTADORES | C23: =+'ACUM-DET'!P39 -> 0 | D23: =+'ACUM-DET'!AG30 -> #REF! | E23: =+C23+D23 -> #REF! | F23: =+'ACUM-DET'!AW30 -> #REF! | G23: =E23-F23 -> #REF!
C24: =+'ACUM-DET'!Q31 -> 0 | D24: =+'ACUM-DET'!AG31 -> #REF! | E24: =+C24+D24 -> #REF! | F24: =+'ACUM-DET'!AW31 -> #REF! | G24: =E24-F24 -> #REF!
C25: =+'ACUM-DET'!Q32 -> 0 | D25: =+'ACUM-DET'!AG32 -> #REF! | E25: =+C25+D25 -> #REF! | F25: =+'ACUM-DET'!AW32 -> #REF! | G25: =E25-F25 -> #REF!
C26: =+'ACUM-DET'!Q33 -> 0 | D26: =+'ACUM-DET'!AG33 -> #REF! | E26: =+C26+D26 -> #REF! | F26: =+'ACUM-DET'!AW33 -> #REF! | G26: =E26-F26 -> #REF!
C27: =+'ACUM-DET'!Q34 -> 0 | D27: =+'ACUM-DET'!AG34 -> #REF! | E27: =+C27+D27 -> #REF! | F27: =+'ACUM-DET'!AW34 -> #REF! | G27: =E27-F27 -> #REF!
C28: =+'ACUM-DET'!Q35 -> 0 | D28: =+'ACUM-DET'!AG35 -> #REF! | E28: =+C28+D28 -> #REF! | F28: =+'ACUM-DET'!AW35 -> #REF! | G28: =E28-F28 -> #REF!

Sheet ACUM-DET
A1: MES DE ENERO 2025
B2: S A L D O S I N I C I A L E S | R2: L L E V A N | AH2: P A G A N | AX2: SALDOS | BV2: SUMINISTROS | CH2: OTRAS
A3: NOMBRE | B3: CAPA | C3: CAPOTE | D3: PICADURA | E3: CESTA | F3: SACAS | G3: GOMA | H3: MAR | I3: PAPEL | J3: REST | K3: PACORA | L3: MAQ | M3: TRAP | N3: SILLA | O3: PRENS | P3: CORT | Q3: REZAGOS | R3: CAPA | S3: CAPOTE | T3: PICADURA | U3: CESTA | V3: SACAS | W3: GOMA | X3: MAR | Y3: PAPEL | Z3: REST | AA3: PACORA | AB3: MAQ | AC3: TRAP | AD3: SILLA | AE3: PRENS | AF3: CORT | AG3: REZAGOS | AH3: CAPA | AI3: CAPOTE | AJ3: PICADURA | AK3: CESTA | AL3: SACAS | AM3: GOMA | AN3: MAR | AO3: PAPEL | AP3: REST | AQ3: PACORA | AR3: MAQ | AS3: TRAP | AT3: SILLA | AU3: PRENS | AV3: CORT | AW3: REZAGOS | AX3: CAPA | AY3: CAPOTE | AZ3: PICADURA | BA3: CESTA | BB3: SACAS | BC3: GOMA | BD3: MAR | BE3: PAPEL | BF3: REST | BG3: TABL | BH3: MAQ | BI3: TRAP | BJ3: SILLA | BK3: PRENS | BL3: CORT | BM3: REZAGOS | BN3: Tabacos | BO3: SACAS | BP3: GOMA | BQ3: MAR | BR3: PAPEL | BS3: REST | BT3: TABL | BU3: MAQ | BV3: TRAP | BW3: SILLA | BX3: PRENS | BY3: CORT | BZ3: REZAGOS | CA3: PRESTAMO | CB3: AHORROS | CC3: PRECIO CAPA | CD3: PRECIO CAPOTE | CE3: PRECIO PICADURA | CF3: TOTAL MATERIAL | CG3: PRECIO TAB. | CH3: DEDUCCIONES | CI3: TOTAL A PAGAR
A4: =+'SEMANA DEL 2 AL 7-3-26'!A5 -> ALCIDES CORREA | B4: =+'SEMANA DEL 2 AL 7-3-26'!B5 -> 0 | C4: =+'SEMANA DEL 2 AL 7-3-26'!C5 -> 0 | D4: =+'SEMANA DEL 2 AL 7-3-26'!D5 -> 0 | E4: =+'SEMANA DEL 2 AL 7-3-26'!E5 -> 0 | F4: =+'SEMANA DEL 2 AL 7-3-26'!F5 -> 0 | G4: =+'SEMANA DEL 2 AL 7-3-26'!G5 -> 0 | H4: =+'SEMANA DEL 2 AL 7-3-26'!H5 -> 0 | ... Q4: =+'SEMANA DEL 2 AL 7-3-26'!Q5 -> 0 | R4: =+'SEMANA DEL 2 AL 7-3-26'!R5+'SEMANA DEL 7 AL 14'!R5+'SEMANA DEL 14 AL 21 '!R5+'SEMANA DEL 21AL 28-3'!R5+#REF! -> #REF! | S4: =+'SEMANA DEL 2 AL 7-3-26'!S5+'SEMANA DEL 7 AL 14'!S5+'SEMANA DEL 14 AL 21 '!S5+'SEMANA DEL 21AL 28-3'!S5+#REF! -> #REF! | T4: =+'SEMANA DEL 2 AL 7-3-26'!T5+'SEMANA DEL 7 AL 14'!T5+'SEMANA DEL 14 AL 21 '!T5+'SEMANA DEL 21AL 28-3'!T5+#REF! -> #REF! | U4: =+'SEMANA DEL 2 AL 7-3-26'!U5+'SEMANA DEL 7 AL 14'!U5+'SEMANA DEL 14 AL 21 '!U5+'SEMANA DEL 21AL 28-3'!U5+#REF! -> #REF! | V4: =+'SEMANA DEL 2 AL 7-3-26'!V5+'SEMANA DEL 7 AL 14'!V5+'SEMANA DEL 14 AL 21 '!V5+'SEMANA DEL 21AL 28-3'!V5+#REF! -> #REF! | W4: =+'SEMANA DEL 2 AL 7-3-26'!W5+'SEMANA DEL 7 AL 14'!W5+'SEMANA DEL 14 AL 21 '!W5+'SEMANA DEL 21AL 28-3'!W5+#REF! -> #REF! | X4: =+'SEMANA DEL 2 AL 7-3-26'!X5+'SEMANA DEL 7 AL 14'!X5+'SEMANA DEL 14 AL 21 '!X5+'SEMANA DEL 21AL 28-3'!X5+#REF! -> #REF! | Y4: =+'SEMANA DEL 2 AL 7-3-26'!Y5+'SEMANA DEL 7 AL 14'!Y5+'SEMANA DEL 14 AL 21 '!Y5+'SEMANA DEL 21AL 28-3'!Y5+#REF! -> #REF! | ... AW4: =+'SEMANA DEL 2 AL 7-3-26'!AW5+'SEMANA DEL 7 AL 14'!AW5+'SEMANA DEL 14 AL 21 '!AW5+'SEMANA DEL 21AL 28-3'!AW5+#REF! -> #REF! | AX4: =+B4+R4-AH4 -> #REF! | AY4: =+C4+S4-AI4 -> #REF! | AZ4: =+D4+T4-AJ4 -> #REF! | BA4: =+E4+U4-AK4 -> #REF! | BB4: =+F4+V4-AL4 -> #REF! | BC4: =+G4+W4-AM4 -> #REF! | BD4: =+H4+X4-AN4 -> #REF! | BE4: =+I4+Y4-AO4 -> #REF! | ... BM4: =+Q4+AG4-AW4 -> #REF! | BN4: =+'SEMANA DEL 2 AL 7-3-26'!BN5+'SEMANA DEL 7 AL 14'!BN5+'SEMANA DEL 14 AL 21 '!BN5+'SEMANA DEL 21AL 28-3'!BN5+#REF! -> #REF! | BO4: =+'SEMANA DEL 2 AL 7-3-26'!BO5+'SEMANA DEL 7 AL 14'!BO5+'SEMANA DEL 14 AL 21 '!BO5+'SEMANA DEL 21AL 28-3'!BO5+#REF! -> #REF! | BP4: =+'SEMANA DEL 2 AL 7-3-26'!BP5+'SEMANA DEL 7 AL 14'!BP5+'SEMANA DEL 14 AL 21 '!BP5+'SEMANA DEL 21AL 28-3'!BP5+#REF! -> #REF! | BQ4: =+'SEMANA DEL 2 AL 7-3-26'!BQ5+'SEMANA DEL 7 AL 14'!BQ5+'SEMANA DEL 14 AL 21 '!BQ5+'SEMANA DEL 21AL 28-3'!BQ5+#REF! -> #REF! | BR4: =+'SEMANA DEL 2 AL 7-3-26'!BR5+'SEMANA DEL 7 AL 14'!BR5+'SEMANA DEL 14 AL 21 '!BR5+'SEMANA DEL 21AL 28-3'!BR5+#REF! -> #REF! | BS4: =+'SEMANA DEL 2 AL 7-3-26'!BS5+'SEMANA DEL 7 AL 14'!BS5+'SEMANA DEL 14 AL 21 '!BS5+'SEMANA DEL 21AL 28-3'!BS5+#REF! -> #REF! | BT4: =+'SEMANA DEL 2 AL 7-3-26'!BT5+'SEMANA DEL 7 AL 14'!BT5+'SEMANA DEL 14 AL 21 '!BT5+'SEMANA DEL 21AL 28-3'!BT5+#REF! -> #REF! | BU4: =+'SEMANA DEL 2 AL 7-3-26'!BU5+'SEMANA DEL 7 AL 14'!BU5+'SEMANA DEL 14 AL 21 '!BU5+'SEMANA DEL 21AL 28-3'!BU5+#REF! -> #REF! | ... CI4: =+'SEMANA DEL 2 AL 7-3-26'!CI5+'SEMANA DEL 7 AL 14'!CI5+'SEMANA DEL 14 AL 21 '!CI5+'SEMANA DEL 21AL 28-3'!CI5+#REF! -> #REF!
A5: =+'SEMANA DEL 2 AL 7-3-26'!A7 -> BLANCA ALVARADO | B5: =+'SEMANA DEL 2 AL 7-3-26'!B7 -> 0 | C5: =+'SEMANA DEL 2 AL 7-3-26'!C7 -> 0 | D5: =+'SEMANA DEL 2 AL 7-3-26'!D7 -> 0 | E5: =+'SEMANA DEL 2 AL 7-3-26'!E7 -> 0 | F5: =+'SEMANA DEL 2 AL 7-3-26'!F7 -> 0 | G5: =+'SEMANA DEL 2 AL 7-3-26'!G7 -> 0 | H5: =+'SEMANA DEL 2 AL 7-3-26'!H7 -> 0 | ... Q5: =+'SEMANA DEL 2 AL 7-3-26'!Q7 -> 0 | R5: =+'SEMANA DEL 2 AL 7-3-26'!#REF!+'SEMANA DEL 7 AL 14'!R6+'SEMANA DEL 14 AL 21 '!R6+'SEMANA DEL 21AL 28-3'!R7+#REF! -> #REF! | S5: =+'SEMANA DEL 2 AL 7-3-26'!#REF!+'SEMANA DEL 7 AL 14'!S6+'SEMANA DEL 14 AL 21 '!S6+'SEMANA DEL 21AL 28-3'!S7+#REF! -> #REF! | T5: =+'SEMANA DEL 2 AL 7-3-26'!#REF!+'SEMANA DEL 7 AL 14'!T6+'SEMANA DEL 14 AL 21 '!T6+'SEMANA DEL 21AL 28-3'!T7+#REF! -> #REF! | U5: =+'SEMANA DEL 2 AL 7-3-26'!#REF!+'SEMANA DEL 7 AL 14'!U6+'SEMANA DEL 14 AL 21 '!U6+'SEMANA DEL 21AL 28-3'!U7+#REF! -> #REF! | V5: =+'SEMANA DEL 2 AL 7-3-26'!#REF!+'SEMANA DEL 7 AL 14'!V6+'SEMANA DEL 14 AL 21 '!V6+'SEMANA DEL 21AL 28-3'!V7+#REF! -> #REF! | W5: =+'SEMANA DEL 2 AL 7-3-26'!#REF!+'SEMANA DEL 7 AL 14'!W6+'SEMANA DEL 14 AL 21 '!W6+'SEMANA DEL 21AL 28-3'!W7+#REF! -> #REF! | X5: =+'SEMANA DEL 2 AL 7-3-26'!#REF!+'SEMANA DEL 7 AL 14'!X6+'SEMANA DEL 14 AL 21 '!X6+'SEMANA DEL 21AL 28-3'!X7+#REF! -> #REF! | Y5: =+'SEMANA DEL 2 AL 7-3-26'!#REF!+'SEMANA DEL 7 AL 14'!Y6+'SEMANA DEL 14 AL 21 '!Y6+'SEMANA DEL 21AL 28-3'!Y7+#REF! -> #REF! | ... AW5: =+'SEMANA DEL 2 AL 7-3-26'!#REF!+'SEMANA DEL 7 AL 14'!AW6+'SEMANA DEL 14 AL 21 '!AW6+'SEMANA DEL 21AL 28-3'!AW7+#REF! -> #REF! | AX5: =+B5+R5-AH5 -> #REF! | AY5: =+C5+S5-AI5 -> #REF! | AZ5: =+D5+T5-AJ5 -> #REF! | BA5: =+E5+U5-AK5 -> #REF! | BB5: =+F5+V5-AL5 -> #REF! | BC5: =+G5+W5-AM5 -> #REF! | BD5: =+H5+X5-AN5 -> #REF! | BE5: =+I5+Y5-AO5 -> #REF! | ... BM5: =+Q5+AG5-AW5 -> #REF! | BN5: =+'SEMANA DEL 2 AL 7-3-26'!#REF!+'SEMANA DEL 7 AL 14'!BN6+'SEMANA DEL 14 AL 21 '!BN6+'SEMANA DEL 21AL 28-3'!BN7+#REF! -> #REF! | BO5: =+'SEMANA DEL 2 AL 7-3-26'!#REF!+'SEMANA DEL 7 AL 14'!BO6+'SEMANA DEL 14 AL 21 '!BO6+'SEMANA DEL 21AL 28-3'!BO7+#REF! -> #REF! | BP5: =+'SEMANA DEL 2 AL 7-3-26'!#REF!+'SEMANA DEL 7 AL 14'!BP6+'SEMANA DEL 14 AL 21 '!BP6+'SEMANA DEL 21AL 28-3'!BP7+#REF! -> #REF! | BQ5: =+'SEMANA DEL 2 AL 7-3-26'!#REF!+'SEMANA DEL 7 AL 14'!BQ6+'SEMANA DEL 14 AL 21 '!BQ6+'SEMANA DEL 21AL 28-3'!BQ7+#REF! -> #REF! | BR5: =+'SEMANA DEL 2 AL 7-3-26'!#REF!+'SEMANA DEL 7 AL 14'!BR6+'SEMANA DEL 14 AL 21 '!BR6+'SEMANA DEL 21AL 28-3'!BR7+#REF! -> #REF! | BS5: =+'SEMANA DEL 2 AL 7-3-26'!#REF!+'SEMANA DEL 7 AL 14'!BS6+'SEMANA DEL 14 AL 21 '!BS6+'SEMANA DEL 21AL 28-3'!BS7+#REF! -> #REF! | BT5: =+'SEMANA DEL 2 AL 7-3-26'!#REF!+'SEMANA DEL 7 AL 14'!BT6+'SEMANA DEL 14 AL 21 '!BT6+'SEMANA DEL 21AL 28-3'!BT7+#REF! -> #REF! | BU5: =+'SEMANA DEL 2 AL 7-3-26'!#REF!+'SEMANA DEL 7 AL 14'!BU6+'SEMANA DEL 14 AL 21 '!BU6+'SEMANA DEL 21AL 28-3'!BU7+#REF! -> #REF! | ... CI5: =+'SEMANA DEL 2 AL 7-3-26'!#REF!+'SEMANA DEL 7 AL 14'!CI6+'SEMANA DEL 14 AL 21 '!CI6+'SEMANA DEL 21AL 28-3'!CI7+#REF! -> #REF!
A6: =+'SEMANA DEL 2 AL 7-3-26'!#REF! -> #REF! | B6: =+'SEMANA DEL 2 AL 7-3-26'!#REF! -> #REF! | C6: =+'SEMANA DEL 2 AL 7-3-26'!#REF! -> #REF! | D6: =+'SEMANA DEL 2 AL 7-3-26'!#REF! -> #REF! | E6: =+'SEMANA DEL 2 AL 7-3-26'!#REF! -> #REF! | F6: =+'SEMANA DEL 2 AL 7-3-26'!#REF! -> #REF! | G6: =+'SEMANA DEL 2 AL 7-3-26'!#REF! -> #REF! | H6: =+'SEMANA DEL 2 AL 7-3-26'!#REF! -> #REF! | ... Q6: =+'SEMANA DEL 2 AL 7-3-26'!#REF! -> #REF! | R6: =+'SEMANA DEL 2 AL 7-3-26'!R7+'SEMANA DEL 7 AL 14'!#REF!+'SEMANA DEL 14 AL 21 '!#REF!+'SEMANA DEL 21AL 28-3'!#REF!+#REF! -> #REF! | S6: =+'SEMANA DEL 2 AL 7-3-26'!S7+'SEMANA DEL 7 AL 14'!#REF!+'SEMANA DEL 14 AL 21 '!#REF!+'SEMANA DEL 21AL 28-3'!#REF!+#REF! -> #REF! | T6: =+'SEMANA DEL 2 AL 7-3-26'!T7+'SEMANA DEL 7 AL 14'!#REF!+'SEMANA DEL 14 AL 21 '!#REF!+'SEMANA DEL 21AL 28-3'!#REF!+#REF! -> #REF! | U6: =+'SEMANA DEL 2 AL 7-3-26'!U7+'SEMANA DEL 7 AL 14'!#REF!+'SEMANA DEL 14 AL 21 '!#REF!+'SEMANA DEL 21AL 28-3'!#REF!+#REF! -> #REF! | V6: =+'SEMANA DEL 2 AL 7-3-26'!V7+'SEMANA DEL 7 AL 14'!#REF!+'SEMANA DEL 14 AL 21 '!#REF!+'SEMANA DEL 21AL 28-3'!#REF!+#REF! -> #REF! | W6: =+'SEMANA DEL 2 AL 7-3-26'!W7+'SEMANA DEL 7 AL 14'!#REF!+'SEMANA DEL 14 AL 21 '!#REF!+'SEMANA DEL 21AL 28-3'!#REF!+#REF! -> #REF! | X6: =+'SEMANA DEL 2 AL 7-3-26'!X7+'SEMANA DEL 7 AL 14'!#REF!+'SEMANA DEL 14 AL 21 '!#REF!+'SEMANA DEL 21AL 28-3'!#REF!+#REF! -> #REF! | Y6: =+'SEMANA DEL 2 AL 7-3-26'!Y7+'SEMANA DEL 7 AL 14'!#REF!+'SEMANA DEL 14 AL 21 '!#REF!+'SEMANA DEL 21AL 28-3'!#REF!+#REF! -> #REF! | ... AW6: =+'SEMANA DEL 2 AL 7-3-26'!AW7+'SEMANA DEL 7 AL 14'!#REF!+'SEMANA DEL 14 AL 21 '!#REF!+'SEMANA DEL 21AL 28-3'!#REF!+#REF! -> #REF! | AX6: =+B6+R6-AH6 -> #REF! | AY6: =+C6+S6-AI6 -> #REF! | AZ6: =+D6+T6-AJ6 -> #REF! | BA6: =+E6+U6-AK6 -> #REF! | BB6: =+F6+V6-AL6 -> #REF! | BC6: =+G6+W6-AM6 -> #REF! | BD6: =+H6+X6-AN6 -> #REF! | BE6: =+I6+Y6-AO6 -> #REF! | ... BM6: =+Q6+AG6-AW6 -> #REF! | BN6: =+'SEMANA DEL 2 AL 7-3-26'!BN7+'SEMANA DEL 7 AL 14'!#REF!+'SEMANA DEL 14 AL 21 '!#REF!+'SEMANA DEL 21AL 28-3'!#REF!+#REF! -> #REF! | BO6: =+'SEMANA DEL 2 AL 7-3-26'!BO7+'SEMANA DEL 7 AL 14'!#REF!+'SEMANA DEL 14 AL 21 '!#REF!+'SEMANA DEL 21AL 28-3'!#REF!+#REF! -> #REF! | BP6: =+'SEMANA DEL 2 AL 7-3-26'!BP7+'SEMANA DEL 7 AL 14'!#REF!+'SEMANA DEL 14 AL 21 '!#REF!+'SEMANA DEL 21AL 28-3'!#REF!+#REF! -> #REF! | BQ6: =+'SEMANA DEL 2 AL 7-3-26'!BQ7+'SEMANA DEL 7 AL 14'!#REF!+'SEMANA DEL 14 AL 21 '!#REF!+'SEMANA DEL 21AL 28-3'!#REF!+#REF! -> #REF! | BR6: =+'SEMANA DEL 2 AL 7-3-26'!BR7+'SEMANA DEL 7 AL 14'!#REF!+'SEMANA DEL 14 AL 21 '!#REF!+'SEMANA DEL 21AL 28-3'!#REF!+#REF! -> #REF! | BS6: =+'SEMANA DEL 2 AL 7-3-26'!BS7+'SEMANA DEL 7 AL 14'!#REF!+'SEMANA DEL 14 AL 21 '!#REF!+'SEMANA DEL 21AL 28-3'!#REF!+#REF! -> #REF! | BT6: =+'SEMANA DEL 2 AL 7-3-26'!BT7+'SEMANA DEL 7 AL 14'!#REF!+'SEMANA DEL 14 AL 21 '!#REF!+'SEMANA DEL 21AL 28-3'!#REF!+#REF! -> #REF! | BU6: =+'SEMANA DEL 2 AL 7-3-26'!BU7+'SEMANA DEL 7 AL 14'!#REF!+'SEMANA DEL 14 AL 21 '!#REF!+'SEMANA DEL 21AL 28-3'!#REF!+#REF! -> #REF! | ... CI6: =+'SEMANA DEL 2 AL 7-3-26'!CI7+'SEMANA DEL 7 AL 14'!#REF!+'SEMANA DEL 14 AL 21 '!#REF!+'SEMANA DEL 21AL 28-3'!#REF!+#REF! -> #REF!
A7: =+'SEMANA DEL 2 AL 7-3-26'!#REF! -> #REF! | B7: =+'SEMANA DEL 2 AL 7-3-26'!#REF! -> #REF! | C7: =+'SEMANA DEL 2 AL 7-3-26'!#REF! -> #REF! | D7: =+'SEMANA DEL 2 AL 7-3-26'!#REF! -> #REF! | E7: =+'SEMANA DEL 2 AL 7-3-26'!#REF! -> #REF! | F7: =+'SEMANA DEL 2 AL 7-3-26'!#REF! -> #REF! | G7: =+'SEMANA DEL 2 AL 7-3-26'!#REF! -> #REF! | H7: =+'SEMANA DEL 2 AL 7-3-26'!#REF! -> #REF! | ... Q7: =+'SEMANA DEL 2 AL 7-3-26'!#REF! -> #REF! | R7: =+'SEMANA DEL 2 AL 7-3-26'!#REF!+'SEMANA DEL 7 AL 14'!R9+'SEMANA DEL 14 AL 21 '!R9+'SEMANA DEL 21AL 28-3'!R11+#REF! -> #REF! | S7: =+'SEMANA DEL 2 AL 7-3-26'!#REF!+'SEMANA DEL 7 AL 14'!S9+'SEMANA DEL 14 AL 21 '!S9+'SEMANA DEL 21AL 28-3'!S11+#REF! -> #REF! | T7: =+'SEMANA DEL 2 AL 7-3-26'!#REF!+'SEMANA DEL 7 AL 14'!T9+'SEMANA DEL 14 AL 21 '!T9+'SEMANA DEL 21AL 28-3'!T11+#REF! -> #REF! | U7: =+'SEMANA DEL 2 AL 7-3-26'!#REF!+'SEMANA DEL 7 AL 14'!U9+'SEMANA DEL 14 AL 21 '!U9+'SEMANA DEL 21AL 28-3'!U11+#REF! -> #REF! | V7: =+'SEMANA DEL 2 AL 7-3-26'!#REF!+'SEMANA DEL 7 AL 14'!V9+'SEMANA DEL 14 AL 21 '!V9+'SEMANA DEL 21AL 28-3'!V11+#REF! -> #REF! | W7: =+'SEMANA DEL 2 AL 7-3-26'!#REF!+'SEMANA DEL 7 AL 14'!W9+'SEMANA DEL 14 AL 21 '!W9+'SEMANA DEL 21AL 28-3'!W11+#REF! -> #REF! | X7: =+'SEMANA DEL 2 AL 7-3-26'!#REF!+'SEMANA DEL 7 AL 14'!X9+'SEMANA DEL 14 AL 21 '!X9+'SEMANA DEL 21AL 28-3'!X11+#REF! -> #REF! | Y7: =+'SEMANA DEL 2 AL 7-3-26'!#REF!+'SEMANA DEL 7 AL 14'!Y9+'SEMANA DEL 14 AL 21 '!Y9+'SEMANA DEL 21AL 28-3'!Y11+#REF! -> #REF! | ... AW7: =+'SEMANA DEL 2 AL 7-3-26'!#REF!+'SEMANA DEL 7 AL 14'!AW9+'SEMANA DEL 14 AL 21 '!AW9+'SEMANA DEL 21AL 28-3'!AW11+#REF! -> #REF! | AX7: =+B7+R7-AH7 -> #REF! | AY7: =+C7+S7-AI7 -> #REF! | AZ7: =+D7+T7-AJ7 -> #REF! | BA7: =+E7+U7-AK7 -> #REF! | BB7: =+F7+V7-AL7 -> #REF! | BC7: =+G7+W7-AM7 -> #REF! | BD7: =+H7+X7-AN7 -> #REF! | BE7: =+I7+Y7-AO7 -> #REF! | ... BM7: =+Q7+AG7-AW7 -> #REF! | BN7: =+'SEMANA DEL 2 AL 7-3-26'!#REF!+'SEMANA DEL 7 AL 14'!BN9+'SEMANA DEL 14 AL 21 '!BN9+'SEMANA DEL 21AL 28-3'!BN11+#REF! -> #REF! | BO7: =+'SEMANA DEL 2 AL 7-3-26'!#REF!+'SEMANA DEL 7 AL 14'!BO9+'SEMANA DEL 14 AL 21 '!BO9+'SEMANA DEL 21AL 28-3'!BO11+#REF! -> #REF! | BP7: =+'SEMANA DEL 2 AL 7-3-26'!#REF!+'SEMANA DEL 7 AL 14'!BP9+'SEMANA DEL 14 AL 21 '!BP9+'SEMANA DEL 21AL 28-3'!BP11+#REF! -> #REF! | BQ7: =+'SEMANA DEL 2 AL 7-3-26'!#REF!+'SEMANA DEL 7 AL 14'!BQ9+'SEMANA DEL 14 AL 21 '!BQ9+'SEMANA DEL 21AL 28-3'!BQ11+#REF! -> #REF! | BR7: =+'SEMANA DEL 2 AL 7-3-26'!#REF!+'SEMANA DEL 7 AL 14'!BR9+'SEMANA DEL 14 AL 21 '!BR9+'SEMANA DEL 21AL 28-3'!BR11+#REF! -> #REF! | BS7: =+'SEMANA DEL 2 AL 7-3-26'!#REF!+'SEMANA DEL 7 AL 14'!BS9+'SEMANA DEL 14 AL 21 '!BS9+'SEMANA DEL 21AL 28-3'!BS11+#REF! -> #REF! | BT7: =+'SEMANA DEL 2 AL 7-3-26'!#REF!+'SEMANA DEL 7 AL 14'!BT9+'SEMANA DEL 14 AL 21 '!BT9+'SEMANA DEL 21AL 28-3'!BT11+#REF! -> #REF! | BU7: =+'SEMANA DEL 2 AL 7-3-26'!#REF!+'SEMANA DEL 7 AL 14'!BU9+'SEMANA DEL 14 AL 21 '!BU9+'SEMANA DEL 21AL 28-3'!BU11+#REF! -> #REF! | ... CI7: =+'SEMANA DEL 2 AL 7-3-26'!#REF!+'SEMANA DEL 7 AL 14'!CI9+'SEMANA DEL 14 AL 21 '!CI9+'SEMANA DEL 21AL 28-3'!CI11+#REF! -> #REF!
A8: =+'SEMANA DEL 2 AL 7-3-26'!#REF! -> #REF! | B8: =+'SEMANA DEL 2 AL 7-3-26'!#REF! -> #REF! | C8: =+'SEMANA DEL 2 AL 7-3-26'!#REF! -> #REF! | D8: =+'SEMANA DEL 2 AL 7-3-26'!#REF! -> #REF! | E8: =+'SEMANA DEL 2 AL 7-3-26'!#REF! -> #REF! | F8: =+'SEMANA DEL 2 AL 7-3-26'!#REF! -> #REF! | G8: =+'SEMANA DEL 2 AL 7-3-26'!#REF! -> #REF! | H8: =+'SEMANA DEL 2 AL 7-3-26'!#REF! -> #REF! | ... Q8: =+'SEMANA DEL 2 AL 7-3-26'!#REF! -> #REF! | R8: =+'SEMANA DEL 2 AL 7-3-26'!#REF!+'SEMANA DEL 7 AL 14'!R10+'SEMANA DEL 14 AL 21 '!R10+'SEMANA DEL 21AL 28-3'!R12+#REF! -> #REF! | S8: =+'SEMANA DEL 2 AL 7-3-26'!#REF!+'SEMANA DEL 7 AL 14'!S10+'SEMANA DEL 14 AL 21 '!S10+'SEMANA DEL 21AL 28-3'!S12+#REF! -> #REF! | T8: =+'SEMANA DEL 2 AL 7-3-26'!#REF!+'SEMANA DEL 7 AL 14'!T10+'SEMANA DEL 14 AL 21 '!T10+'SEMANA DEL 21AL 28-3'!T12+#REF! -> #REF! | U8: =+'SEMANA DEL 2 AL 7-3-26'!#REF!+'SEMANA DEL 7 AL 14'!U10+'SEMANA DEL 14 AL 21 '!U10+'SEMANA DEL 21AL 28-3'!U12+#REF! -> #REF! | V8: =+'SEMANA DEL 2 AL 7-3-26'!#REF!+'SEMANA DEL 7 AL 14'!V10+'SEMANA DEL 14 AL 21 '!V10+'SEMANA DEL 21AL 28-3'!V12+#REF! -> #REF! | W8: =+'SEMANA DEL 2 AL 7-3-26'!#REF!+'SEMANA DEL 7 AL 14'!W10+'SEMANA DEL 14 AL 21 '!W10+'SEMANA DEL 21AL 28-3'!W12+#REF! -> #REF! | X8: =+'SEMANA DEL 2 AL 7-3-26'!#REF!+'SEMANA DEL 7 AL 14'!X10+'SEMANA DEL 14 AL 21 '!X10+'SEMANA DEL 21AL 28-3'!X12+#REF! -> #REF! | Y8: =+'SEMANA DEL 2 AL 7-3-26'!#REF!+'SEMANA DEL 7 AL 14'!Y10+'SEMANA DEL 14 AL 21 '!Y10+'SEMANA DEL 21AL 28-3'!Y12+#REF! -> #REF! | ... AW8: =+'SEMANA DEL 2 AL 7-3-26'!#REF!+'SEMANA DEL 7 AL 14'!AW10+'SEMANA DEL 14 AL 21 '!AW10+'SEMANA DEL 21AL 28-3'!AW12+#REF! -> #REF! | AX8: =+B8+R8-AH8 -> #REF! | AY8: =+C8+S8-AI8 -> #REF! | AZ8: =+D8+T8-AJ8 -> #REF! | BA8: =+E8+U8-AK8 -> #REF! | BB8: =+F8+V8-AL8 -> #REF! | BC8: =+G8+W8-AM8 -> #REF! | BD8: =+H8+X8-AN8 -> #REF! | BE8: =+I8+Y8-AO8 -> #REF! | ... BM8: =+Q8+AG8-AW8 -> #REF! | BN8: =+'SEMANA DEL 2 AL 7-3-26'!#REF!+'SEMANA DEL 7 AL 14'!BN10+'SEMANA DEL 14 AL 21 '!BN10+'SEMANA DEL 21AL 28-3'!BN12+#REF! -> #REF! | BO8: =+'SEMANA DEL 2 AL 7-3-26'!#REF!+'SEMANA DEL 7 AL 14'!BO10+'SEMANA DEL 14 AL 21 '!BO10+'SEMANA DEL 21AL 28-3'!BO12+#REF! -> #REF! | BP8: =+'SEMANA DEL 2 AL 7-3-26'!#REF!+'SEMANA DEL 7 AL 14'!BP10+'SEMANA DEL 14 AL 21 '!BP10+'SEMANA DEL 21AL 28-3'!BP12+#REF! -> #REF! | BQ8: =+'SEMANA DEL 2 AL 7-3-26'!#REF!+'SEMANA DEL 7 AL 14'!BQ10+'SEMANA DEL 14 AL 21 '!BQ10+'SEMANA DEL 21AL 28-3'!BQ12+#REF! -> #REF! | BR8: =+'SEMANA DEL 2 AL 7-3-26'!#REF!+'SEMANA DEL 7 AL 14'!BR10+'SEMANA DEL 14 AL 21 '!BR10+'SEMANA DEL 21AL 28-3'!BR12+#REF! -> #REF! | BS8: =+'SEMANA DEL 2 AL 7-3-26'!#REF!+'SEMANA DEL 7 AL 14'!BS10+'SEMANA DEL 14 AL 21 '!BS10+'SEMANA DEL 21AL 28-3'!BS12+#REF! -> #REF! | BT8: =+'SEMANA DEL 2 AL 7-3-26'!#REF!+'SEMANA DEL 7 AL 14'!BT10+'SEMANA DEL 14 AL 21 '!BT10+'SEMANA DEL 21AL 28-3'!BT12+#REF! -> #REF! | BU8: =+'SEMANA DEL 2 AL 7-3-26'!#REF!+'SEMANA DEL 7 AL 14'!BU10+'SEMANA DEL 14 AL 21 '!BU10+'SEMANA DEL 21AL 28-3'!BU12+#REF! -> #REF! | ... CI8: =+'SEMANA DEL 2 AL 7-3-26'!#REF!+'SEMANA DEL 7 AL 14'!CI10+'SEMANA DEL 14 AL 21 '!CI10+'SEMANA DEL 21AL 28-3'!CI12+#REF! -> #REF!
A9: =+'SEMANA DEL 2 AL 7-3-26'!A9 -> ELIZABETH REYES SERRANO | B9: =+'SEMANA DEL 2 AL 7-3-26'!B9 -> 0 | C9: =+'SEMANA DEL 2 AL 7-3-26'!C9 -> 0 | D9: =+'SEMANA DEL 2 AL 7-3-26'!D9 -> 0 | E9: =+'SEMANA DEL 2 AL 7-3-26'!E9 -> 0 | F9: =+'SEMANA DEL 2 AL 7-3-26'!F9 -> 0 | G9: =+'SEMANA DEL 2 AL 7-3-26'!G9 -> 0 | H9: =+'SEMANA DEL 2 AL 7-3-26'!H9 -> 0 | ... Q9: =+'SEMANA DEL 2 AL 7-3-26'!Q9 -> 0 | R9: =+'SEMANA DEL 2 AL 7-3-26'!#REF!+'SEMANA DEL 7 AL 14'!R11+'SEMANA DEL 14 AL 21 '!R11+'SEMANA DEL 21AL 28-3'!#REF!+#REF! -> #REF! | S9: =+'SEMANA DEL 2 AL 7-3-26'!#REF!+'SEMANA DEL 7 AL 14'!S11+'SEMANA DEL 14 AL 21 '!S11+'SEMANA DEL 21AL 28-3'!#REF!+#REF! -> #REF! | T9: =+'SEMANA DEL 2 AL 7-3-26'!#REF!+'SEMANA DEL 7 AL 14'!T11+'SEMANA DEL 14 AL 21 '!T11+'SEMANA DEL 21AL 28-3'!#REF!+#REF! -> #REF! | U9: =+'SEMANA DEL 2 AL 7-3-26'!#REF!+'SEMANA DEL 7 AL 14'!U11+'SEMANA DEL 14 AL 21 '!U11+'SEMANA DEL 21AL 28-3'!#REF!+#REF! -> #REF! | V9: =+'SEMANA DEL 2 AL 7-3-26'!#REF!+'SEMANA DEL 7 AL 14'!V11+'SEMANA DEL 14 AL 21 '!V11+'SEMANA DEL 21AL 28-3'!#REF!+#REF! -> #REF! | W9: =+'SEMANA DEL 2 AL 7-3-26'!#REF!+'SEMANA DEL 7 AL 14'!W11+'SEMANA DEL 14 AL 21 '!W11+'SEMANA DEL 21AL 28-3'!#REF!+#REF! -> #REF! | X9: =+'SEMANA DEL 2 AL 7-3-26'!#REF!+'SEMANA DEL 7 AL 14'!X11+'SEMANA DEL 14 AL 21 '!X11+'SEMANA DEL 21AL 28-3'!#REF!+#REF! -> #REF! | Y9: =+'SEMANA DEL 2 AL 7-3-26'!#REF!+'SEMANA DEL 7 AL 14'!Y11+'SEMANA DEL 14 AL 21 '!Y11+'SEMANA DEL 21AL 28-3'!#REF!+#REF! -> #REF! | ... AW9: =+'SEMANA DEL 2 AL 7-3-26'!#REF!+'SEMANA DEL 7 AL 14'!AW11+'SEMANA DEL 14 AL 21 '!AW11+'SEMANA DEL 21AL 28-3'!#REF!+#REF! -> #REF! | AX9: =+B9+R9-AH9 -> #REF! | AY9: =+C9+S9-AI9 -> #REF! | AZ9: =+D9+T9-AJ9 -> #REF! | BA9: =+E9+U9-AK9 -> #REF! | BB9: =+F9+V9-AL9 -> #REF! | BC9: =+G9+W9-AM9 -> #REF! | BD9: =+H9+X9-AN9 -> #REF! | BE9: =+I9+Y9-AO9 -> #REF! | ... BM9: =+Q9+AG9-AW9 -> #REF! | BN9: =+'SEMANA DEL 2 AL 7-3-26'!#REF!+'SEMANA DEL 7 AL 14'!BN11+'SEMANA DEL 14 AL 21 '!BN11+'SEMANA DEL 21AL 28-3'!#REF!+#REF! -> #REF! | BO9: =+'SEMANA DEL 2 AL 7-3-26'!#REF!+'SEMANA DEL 7 AL 14'!BO11+'SEMANA DEL 14 AL 21 '!BO11+'SEMANA DEL 21AL 28-3'!#REF!+#REF! -> #REF! | BP9: =+'SEMANA DEL 2 AL 7-3-26'!#REF!+'SEMANA DEL 7 AL 14'!BP11+'SEMANA DEL 14 AL 21 '!BP11+'SEMANA DEL 21AL 28-3'!#REF!+#REF! -> #REF! | BQ9: =+'SEMANA DEL 2 AL 7-3-26'!#REF!+'SEMANA DEL 7 AL 14'!BQ11+'SEMANA DEL 14 AL 21 '!BQ11+'SEMANA DEL 21AL 28-3'!#REF!+#REF! -> #REF! | BR9: =+'SEMANA DEL 2 AL 7-3-26'!#REF!+'SEMANA DEL 7 AL 14'!BR11+'SEMANA DEL 14 AL 21 '!BR11+'SEMANA DEL 21AL 28-3'!#REF!+#REF! -> #REF! | BS9: =+'SEMANA DEL 2 AL 7-3-26'!#REF!+'SEMANA DEL 7 AL 14'!BS11+'SEMANA DEL 14 AL 21 '!BS11+'SEMANA DEL 21AL 28-3'!#REF!+#REF! -> #REF! | BT9: =+'SEMANA DEL 2 AL 7-3-26'!#REF!+'SEMANA DEL 7 AL 14'!BT11+'SEMANA DEL 14 AL 21 '!BT11+'SEMANA DEL 21AL 28-3'!#REF!+#REF! -> #REF! | BU9: =+'SEMANA DEL 2 AL 7-3-26'!#REF!+'SEMANA DEL 7 AL 14'!BU11+'SEMANA DEL 14 AL 21 '!BU11+'SEMANA DEL 21AL 28-3'!#REF!+#REF! -> #REF! | ... CI9: =+'SEMANA DEL 2 AL 7-3-26'!#REF!+'SEMANA DEL 7 AL 14'!CI11+'SEMANA DEL 14 AL 21 '!CI11+'SEMANA DEL 21AL 28-3'!#REF!+#REF! -> #REF!
A10: =+'SEMANA DEL 2 AL 7-3-26'!A10 -> ELVIRA LOPEZ | B10: =+'SEMANA DEL 2 AL 7-3-26'!B10 -> 0 | C10: =+'SEMANA DEL 2 AL 7-3-26'!C10 -> 0 | D10: =+'SEMANA DEL 2 AL 7-3-26'!D10 -> 0 | E10: =+'SEMANA DEL 2 AL 7-3-26'!E10 -> 0 | F10: =+'SEMANA DEL 2 AL 7-3-26'!F10 -> 0 | G10: =+'SEMANA DEL 2 AL 7-3-26'!G10 -> 0 | H10: =+'SEMANA DEL 2 AL 7-3-26'!H10 -> 0 | ... Q10: =+'SEMANA DEL 2 AL 7-3-26'!Q10 -> 0 | R10: =+'SEMANA DEL 2 AL 7-3-26'!R10+'SEMANA DEL 7 AL 14'!R12+'SEMANA DEL 14 AL 21 '!R12+'SEMANA DEL 21AL 28-3'!R13+#REF! -> #REF! | S10: =+'SEMANA DEL 2 AL 7-3-26'!S10+'SEMANA DEL 7 AL 14'!S12+'SEMANA DEL 14 AL 21 '!S12+'SEMANA DEL 21AL 28-3'!S13+#REF! -> #REF! | T10: =+'SEMANA DEL 2 AL 7-3-26'!T10+'SEMANA DEL 7 AL 14'!T12+'SEMANA DEL 14 AL 21 '!T12+'SEMANA DEL 21AL 28-3'!T13+#REF! -> #REF! | U10: =+'SEMANA DEL 2 AL 7-3-26'!U10+'SEMANA DEL 7 AL 14'!U12+'SEMANA DEL 14 AL 21 '!U12+'SEMANA DEL 21AL 28-3'!U13+#REF! -> #REF! | V10: =+'SEMANA DEL 2 AL 7-3-26'!V10+'SEMANA DEL 7 AL 14'!V12+'SEMANA DEL 14 AL 21 '!V12+'SEMANA DEL 21AL 28-3'!V13+#REF! -> #REF! | W10: =+'SEMANA DEL 2 AL 7-3-26'!W10+'SEMANA DEL 7 AL 14'!W12+'SEMANA DEL 14 AL 21 '!W12+'SEMANA DEL 21AL 28-3'!W13+#REF! -> #REF! | X10: =+'SEMANA DEL 2 AL 7-3-26'!X10+'SEMANA DEL 7 AL 14'!X12+'SEMANA DEL 14 AL 21 '!X12+'SEMANA DEL 21AL 28-3'!X13+#REF! -> #REF! | Y10: =+'SEMANA DEL 2 AL 7-3-26'!Y10+'SEMANA DEL 7 AL 14'!Y12+'SEMANA DEL 14 AL 21 '!Y12+'SEMANA DEL 21AL 28-3'!Y13+#REF! -> #REF! | ... AW10: =+'SEMANA DEL 2 AL 7-3-26'!AW10+'SEMANA DEL 7 AL 14'!AW12+'SEMANA DEL 14 AL 21 '!AW12+'SEMANA DEL 21AL 28-3'!AW13+#REF! -> #REF! | AX10: =+B10+R10-AH10 -> #REF! | AY10: =+C10+S10-AI10 -> #REF! | AZ10: =+D10+T10-AJ10 -> #REF! | BA10: =+E10+U10-AK10 -> #REF! | BB10: =+F10+V10-AL10 -> #REF! | BC10: =+G10+W10-AM10 -> #REF! | BD10: =+H10+X10-AN10 -> #REF! | BE10: =+I10+Y10-AO10 -> #REF! | ... BM10: =+Q10+AG10-AW10 -> #REF! | BN10: =+'SEMANA DEL 2 AL 7-3-26'!BN10+'SEMANA DEL 7 AL 14'!BN12+'SEMANA DEL 14 AL 21 '!BN12+'SEMANA DEL 21AL 28-3'!BN13+#REF! -> #REF! | BO10: =+'SEMANA DEL 2 AL 7-3-26'!BO10+'SEMANA DEL 7 AL 14'!BO12+'SEMANA DEL 14 AL 21 '!BO12+'SEMANA DEL 21AL 28-3'!BO13+#REF! -> #REF! | BP10: =+'SEMANA DEL 2 AL 7-3-26'!BP10+'SEMANA DEL 7 AL 14'!BP12+'SEMANA DEL 14 AL 21 '!BP12+'SEMANA DEL 21AL 28-3'!BP13+#REF! -> #REF! | BQ10: =+'SEMANA DEL 2 AL 7-3-26'!BQ10+'SEMANA DEL 7 AL 14'!BQ12+'SEMANA DEL 14 AL 21 '!BQ12+'SEMANA DEL 21AL 28-3'!BQ13+#REF! -> #REF! | BR10: =+'SEMANA DEL 2 AL 7-3-26'!BR10+'SEMANA DEL 7 AL 14'!BR12+'SEMANA DEL 14 AL 21 '!BR12+'SEMANA DEL 21AL 28-3'!BR13+#REF! -> #REF! | BS10: =+'SEMANA DEL 2 AL 7-3-26'!BS10+'SEMANA DEL 7 AL 14'!BS12+'SEMANA DEL 14 AL 21 '!BS12+'SEMANA DEL 21AL 28-3'!BS13+#REF! -> #REF! | BT10: =+'SEMANA DEL 2 AL 7-3-26'!BT10+'SEMANA DEL 7 AL 14'!BT12+'SEMANA DEL 14 AL 21 '!BT12+'SEMANA DEL 21AL 28-3'!BT13+#REF! -> #REF! | BU10: =+'SEMANA DEL 2 AL 7-3-26'!BU10+'SEMANA DEL 7 AL 14'!BU12+'SEMANA DEL 14 AL 21 '!BU12+'SEMANA DEL 21AL 28-3'!BU13+#REF! -> #REF! | ... CI10: =+'SEMANA DEL 2 AL 7-3-26'!CI10+'SEMANA DEL 7 AL 14'!CI12+'SEMANA DEL 14 AL 21 '!CI12+'SEMANA DEL 21AL 28-3'!CI13+#REF! -> #REF!
A11: =+'SEMANA DEL 2 AL 7-3-26'!A11 -> ERNESTO REYES | B11: =+'SEMANA DEL 2 AL 7-3-26'!B11 -> 0.2 | C11: =+'SEMANA DEL 2 AL 7-3-26'!C11 -> 0.36 | D11: =+'SEMANA DEL 2 AL 7-3-26'!D11 -> 1.4 | E11: =+'SEMANA DEL 2 AL 7-3-26'!E11 -> 0 | F11: =+'SEMANA DEL 2 AL 7-3-26'!F11 -> 0 | G11: =+'SEMANA DEL 2 AL 7-3-26'!G11 -> 0 | H11: =+'SEMANA DEL 2 AL 7-3-26'!H11 -> 0 | ... Q11: =+'SEMANA DEL 2 AL 7-3-26'!Q11 -> 0 | R11: =+'SEMANA DEL 2 AL 7-3-26'!R11+'SEMANA DEL 7 AL 14'!R13+'SEMANA DEL 14 AL 21 '!R13+'SEMANA DEL 21AL 28-3'!R14+#REF! -> #REF! | S11: =+'SEMANA DEL 2 AL 7-3-26'!S11+'SEMANA DEL 7 AL 14'!S13+'SEMANA DEL 14 AL 21 '!S13+'SEMANA DEL 21AL 28-3'!S14+#REF! -> #REF! | T11: =+'SEMANA DEL 2 AL 7-3-26'!T11+'SEMANA DEL 7 AL 14'!T13+'SEMANA DEL 14 AL 21 '!T13+'SEMANA DEL 21AL 28-3'!T14+#REF! -> #REF! | U11: =+'SEMANA DEL 2 AL 7-3-26'!U11+'SEMANA DEL 7 AL 14'!U13+'SEMANA DEL 14 AL 21 '!U13+'SEMANA DEL 21AL 28-3'!U14+#REF! -> #REF! | V11: =+'SEMANA DEL 2 AL 7-3-26'!V11+'SEMANA DEL 7 AL 14'!V13+'SEMANA DEL 14 AL 21 '!V13+'SEMANA DEL 21AL 28-3'!V14+#REF! -> #REF! | W11: =+'SEMANA DEL 2 AL 7-3-26'!W11+'SEMANA DEL 7 AL 14'!W13+'SEMANA DEL 14 AL 21 '!W13+'SEMANA DEL 21AL 28-3'!W14+#REF! -> #REF! | X11: =+'SEMANA DEL 2 AL 7-3-26'!X11+'SEMANA DEL 7 AL 14'!X13+'SEMANA DEL 14 AL 21 '!X13+'SEMANA DEL 21AL 28-3'!X14+#REF! -> #REF! | Y11: =+'SEMANA DEL 2 AL 7-3-26'!Y11+'SEMANA DEL 7 AL 14'!Y13+'SEMANA DEL 14 AL 21 '!Y13+'SEMANA DEL 21AL 28-3'!Y14+#REF! -> #REF! | ... AW11: =+'SEMANA DEL 2 AL 7-3-26'!AW11+'SEMANA DEL 7 AL 14'!AW13+'SEMANA DEL 14 AL 21 '!AW13+'SEMANA DEL 21AL 28-3'!AW14+#REF! -> #REF! | AX11: =+B11+R11-AH11 -> #REF! | AY11: =+C11+S11-AI11 -> #REF! | AZ11: =+D11+T11-AJ11 -> #REF! | BA11: =+E11+U11-AK11 -> #REF! | BB11: =+F11+V11-AL11 -> #REF! | BC11: =+G11+W11-AM11 -> #REF! | BD11: =+H11+X11-AN11 -> #REF! | BE11: =+I11+Y11-AO11 -> #REF! | ... BM11: =+Q11+AG11-AW11 -> #REF! | BN11: =+'SEMANA DEL 2 AL 7-3-26'!BN11+'SEMANA DEL 7 AL 14'!BN13+'SEMANA DEL 14 AL 21 '!BN13+'SEMANA DEL 21AL 28-3'!BN14+#REF! -> #REF! | BO11: =+'SEMANA DEL 2 AL 7-3-26'!BO11+'SEMANA DEL 7 AL 14'!BO13+'SEMANA DEL 14 AL 21 '!BO13+'SEMANA DEL 21AL 28-3'!BO14+#REF! -> #REF! | BP11: =+'SEMANA DEL 2 AL 7-3-26'!BP11+'SEMANA DEL 7 AL 14'!BP13+'SEMANA DEL 14 AL 21 '!BP13+'SEMANA DEL 21AL 28-3'!BP14+#REF! -> #REF! | BQ11: =+'SEMANA DEL 2 AL 7-3-26'!BQ11+'SEMANA DEL 7 AL 14'!BQ13+'SEMANA DEL 14 AL 21 '!BQ13+'SEMANA DEL 21AL 28-3'!BQ14+#REF! -> #REF! | BR11: =+'SEMANA DEL 2 AL 7-3-26'!BR11+'SEMANA DEL 7 AL 14'!BR13+'SEMANA DEL 14 AL 21 '!BR13+'SEMANA DEL 21AL 28-3'!BR14+#REF! -> #REF! | BS11: =+'SEMANA DEL 2 AL 7-3-26'!BS11+'SEMANA DEL 7 AL 14'!BS13+'SEMANA DEL 14 AL 21 '!BS13+'SEMANA DEL 21AL 28-3'!BS14+#REF! -> #REF! | BT11: =+'SEMANA DEL 2 AL 7-3-26'!BT11+'SEMANA DEL 7 AL 14'!BT13+'SEMANA DEL 14 AL 21 '!BT13+'SEMANA DEL 21AL 28-3'!BT14+#REF! -> #REF! | BU11: =+'SEMANA DEL 2 AL 7-3-26'!BU11+'SEMANA DEL 7 AL 14'!BU13+'SEMANA DEL 14 AL 21 '!BU13+'SEMANA DEL 21AL 28-3'!BU14+#REF! -> #REF! | ... CI11: =+'SEMANA DEL 2 AL 7-3-26'!CI11+'SEMANA DEL 7 AL 14'!CI13+'SEMANA DEL 14 AL 21 '!CI13+'SEMANA DEL 21AL 28-3'!CI14+#REF! -> #REF!
A12: =+'SEMANA DEL 2 AL 7-3-26'!A12 -> GUILLERMO ZAMBRANO | B12: =+'SEMANA DEL 2 AL 7-3-26'!B12 -> 0.35 | C12: =+'SEMANA DEL 2 AL 7-3-26'!C12 -> 1.63 | D12: =+'SEMANA DEL 2 AL 7-3-26'!D12 -> 4.45 | E12: =+'SEMANA DEL 2 AL 7-3-26'!E12 -> 0 | F12: =+'SEMANA DEL 2 AL 7-3-26'!F12 -> 0 | G12: =+'SEMANA DEL 2 AL 7-3-26'!G12 -> 0 | H12: =+'SEMANA DEL 2 AL 7-3-26'!H12 -> 0 | ... Q12: =+'SEMANA DEL 2 AL 7-3-26'!Q12 -> 0 | R12: =+'SEMANA DEL 2 AL 7-3-26'!R12+'SEMANA DEL 7 AL 14'!R16+'SEMANA DEL 14 AL 21 '!R16+'SEMANA DEL 21AL 28-3'!R17+#REF! -> #REF! | S12: =+'SEMANA DEL 2 AL 7-3-26'!S12+'SEMANA DEL 7 AL 14'!S16+'SEMANA DEL 14 AL 21 '!S16+'SEMANA DEL 21AL 28-3'!S17+#REF! -> #REF! | T12: =+'SEMANA DEL 2 AL 7-3-26'!T12+'SEMANA DEL 7 AL 14'!T16+'SEMANA DEL 14 AL 21 '!T16+'SEMANA DEL 21AL 28-3'!T17+#REF! -> #REF! | U12: =+'SEMANA DEL 2 AL 7-3-26'!U12+'SEMANA DEL 7 AL 14'!U16+'SEMANA DEL 14 AL 21 '!U16+'SEMANA DEL 21AL 28-3'!U17+#REF! -> #REF! | V12: =+'SEMANA DEL 2 AL 7-3-26'!V12+'SEMANA DEL 7 AL 14'!V16+'SEMANA DEL 14 AL 21 '!V16+'SEMANA DEL 21AL 28-3'!V17+#REF! -> #REF! | W12: =+'SEMANA DEL 2 AL 7-3-26'!W12+'SEMANA DEL 7 AL 14'!W16+'SEMANA DEL 14 AL 21 '!W16+'SEMANA DEL 21AL 28-3'!W17+#REF! -> #REF! | X12: =+'SEMANA DEL 2 AL 7-3-26'!X12+'SEMANA DEL 7 AL 14'!X16+'SEMANA DEL 14 AL 21 '!X16+'SEMANA DEL 21AL 28-3'!X17+#REF! -> #REF! | Y12: =+'SEMANA DEL 2 AL 7-3-26'!Y12+'SEMANA DEL 7 AL 14'!Y16+'SEMANA DEL 14 AL 21 '!Y16+'SEMANA DEL 21AL 28-3'!Y17+#REF! -> #REF! | ... AW12: =+'SEMANA DEL 2 AL 7-3-26'!AW12+'SEMANA DEL 7 AL 14'!AW16+'SEMANA DEL 14 AL 21 '!AW16+'SEMANA DEL 21AL 28-3'!AW17+#REF! -> #REF! | AX12: =+B12+R12-AH12 -> #REF! | AY12: =+C12+S12-AI12 -> #REF! | AZ12: =+D12+T12-AJ12 -> #REF! | BA12: =+E12+U12-AK12 -> #REF! | BB12: =+F12+V12-AL12 -> #REF! | BC12: =+G12+W12-AM12 -> #REF! | BD12: =+H12+X12-AN12 -> #REF! | BE12: =+I12+Y12-AO12 -> #REF! | ... BM12: =+Q12+AG12-AW12 -> #REF! | BN12: =+'SEMANA DEL 2 AL 7-3-26'!BN12+'SEMANA DEL 7 AL 14'!BN16+'SEMANA DEL 14 AL 21 '!BN16+'SEMANA DEL 21AL 28-3'!BN17+#REF! -> #REF! | BO12: =+'SEMANA DEL 2 AL 7-3-26'!BO12+'SEMANA DEL 7 AL 14'!BO16+'SEMANA DEL 14 AL 21 '!BO16+'SEMANA DEL 21AL 28-3'!BO17+#REF! -> #REF! | BP12: =+'SEMANA DEL 2 AL 7-3-26'!BP12+'SEMANA DEL 7 AL 14'!BP16+'SEMANA DEL 14 AL 21 '!BP16+'SEMANA DEL 21AL 28-3'!BP17+#REF! -> #REF! | BQ12: =+'SEMANA DEL 2 AL 7-3-26'!BQ12+'SEMANA DEL 7 AL 14'!BQ16+'SEMANA DEL 14 AL 21 '!BQ16+'SEMANA DEL 21AL 28-3'!BQ17+#REF! -> #REF! | BR12: =+'SEMANA DEL 2 AL 7-3-26'!BR12+'SEMANA DEL 7 AL 14'!BR16+'SEMANA DEL 14 AL 21 '!BR16+'SEMANA DEL 21AL 28-3'!BR17+#REF! -> #REF! | BS12: =+'SEMANA DEL 2 AL 7-3-26'!BS12+'SEMANA DEL 7 AL 14'!BS16+'SEMANA DEL 14 AL 21 '!BS16+'SEMANA DEL 21AL 28-3'!BS17+#REF! -> #REF! | BT12: =+'SEMANA DEL 2 AL 7-3-26'!BT12+'SEMANA DEL 7 AL 14'!BT16+'SEMANA DEL 14 AL 21 '!BT16+'SEMANA DEL 21AL 28-3'!BT17+#REF! -> #REF! | BU12: =+'SEMANA DEL 2 AL 7-3-26'!BU12+'SEMANA DEL 7 AL 14'!BU16+'SEMANA DEL 14 AL 21 '!BU16+'SEMANA DEL 21AL 28-3'!BU17+#REF! -> #REF! | ... CI12: =+'SEMANA DEL 2 AL 7-3-26'!CI12+'SEMANA DEL 7 AL 14'!CI16+'SEMANA DEL 14 AL 21 '!CI16+'SEMANA DEL 21AL 28-3'!CI17+#REF! -> #REF!
A13: =+'SEMANA DEL 2 AL 7-3-26'!#REF! -> #REF! | B13: =+'SEMANA DEL 2 AL 7-3-26'!#REF! -> #REF! | C13: =+'SEMANA DEL 2 AL 7-3-26'!#REF! -> #REF! | D13: =+'SEMANA DEL 2 AL 7-3-26'!#REF! -> #REF! | E13: =+'SEMANA DEL 2 AL 7-3-26'!#REF! -> #REF! | F13: =+'SEMANA DEL 2 AL 7-3-26'!#REF! -> #REF! | G13: =+'SEMANA DEL 2 AL 7-3-26'!#REF! -> #REF! | H13: =+'SEMANA DEL 2 AL 7-3-26'!#REF! -> #REF! | ... Q13: =+'SEMANA DEL 2 AL 7-3-26'!#REF! -> #REF! | R13: =+'SEMANA DEL 2 AL 7-3-26'!R13+'SEMANA DEL 7 AL 14'!R17+'SEMANA DEL 14 AL 21 '!R17+'SEMANA DEL 21AL 28-3'!R18+#REF! -> #REF! | S13: =+'SEMANA DEL 2 AL 7-3-26'!S13+'SEMANA DEL 7 AL 14'!S17+'SEMANA DEL 14 AL 21 '!S17+'SEMANA DEL 21AL 28-3'!S18+#REF! -> #REF! | T13: =+'SEMANA DEL 2 AL 7-3-26'!T13+'SEMANA DEL 7 AL 14'!T17+'SEMANA DEL 14 AL 21 '!T17+'SEMANA DEL 21AL 28-3'!T18+#REF! -> #REF! | U13: =+'SEMANA DEL 2 AL 7-3-26'!U13+'SEMANA DEL 7 AL 14'!U17+'SEMANA DEL 14 AL 21 '!U17+'SEMANA DEL 21AL 28-3'!U18+#REF! -> #REF! | V13: =+'SEMANA DEL 2 AL 7-3-26'!V13+'SEMANA DEL 7 AL 14'!V17+'SEMANA DEL 14 AL 21 '!V17+'SEMANA DEL 21AL 28-3'!V18+#REF! -> #REF! | W13: =+'SEMANA DEL 2 AL 7-3-26'!W13+'SEMANA DEL 7 AL 14'!W17+'SEMANA DEL 14 AL 21 '!W17+'SEMANA DEL 21AL 28-3'!W18+#REF! -> #REF! | X13: =+'SEMANA DEL 2 AL 7-3-26'!X13+'SEMANA DEL 7 AL 14'!X17+'SEMANA DEL 14 AL 21 '!X17+'SEMANA DEL 21AL 28-3'!X18+#REF! -> #REF! | Y13: =+'SEMANA DEL 2 AL 7-3-26'!Y13+'SEMANA DEL 7 AL 14'!Y17+'SEMANA DEL 14 AL 21 '!Y17+'SEMANA DEL 21AL 28-3'!Y18+#REF! -> #REF! | ... AW13: =+'SEMANA DEL 2 AL 7-3-26'!AW13+'SEMANA DEL 7 AL 14'!AW17+'SEMANA DEL 14 AL 21 '!AW17+'SEMANA DEL 21AL 28-3'!AW18+#REF! -> #REF! | AX13: =+B13+R13-AH13 -> #REF! | AY13: =+C13+S13-AI13 -> #REF! | AZ13: =+D13+T13-AJ13 -> #REF! | BA13: =+E13+U13-AK13 -> #REF! | BB13: =+F13+V13-AL13 -> #REF! | BC13: =+G13+W13-AM13 -> #REF! | BD13: =+H13+X13-AN13 -> #REF! | BE13: =+I13+Y13-AO13 -> #REF! | ... BM13: =+Q13+AG13-AW13 -> #REF! | BN13: =+'SEMANA DEL 2 AL 7-3-26'!BN13+'SEMANA DEL 7 AL 14'!BN17+'SEMANA DEL 14 AL 21 '!BN17+'SEMANA DEL 21AL 28-3'!BN18+#REF! -> #REF! | BO13: =+'SEMANA DEL 2 AL 7-3-26'!BO13+'SEMANA DEL 7 AL 14'!BO17+'SEMANA DEL 14 AL 21 '!BO17+'SEMANA DEL 21AL 28-3'!BO18+#REF! -> #REF! | BP13: =+'SEMANA DEL 2 AL 7-3-26'!BP13+'SEMANA DEL 7 AL 14'!BP17+'SEMANA DEL 14 AL 21 '!BP17+'SEMANA DEL 21AL 28-3'!BP18+#REF! -> #REF! | BQ13: =+'SEMANA DEL 2 AL 7-3-26'!BQ13+'SEMANA DEL 7 AL 14'!BQ17+'SEMANA DEL 14 AL 21 '!BQ17+'SEMANA DEL 21AL 28-3'!BQ18+#REF! -> #REF! | BR13: =+'SEMANA DEL 2 AL 7-3-26'!BR13+'SEMANA DEL 7 AL 14'!BR17+'SEMANA DEL 14 AL 21 '!BR17+'SEMANA DEL 21AL 28-3'!BR18+#REF! -> #REF! | BS13: =+'SEMANA DEL 2 AL 7-3-26'!BS13+'SEMANA DEL 7 AL 14'!BS17+'SEMANA DEL 14 AL 21 '!BS17+'SEMANA DEL 21AL 28-3'!BS18+#REF! -> #REF! | BT13: =+'SEMANA DEL 2 AL 7-3-26'!BT13+'SEMANA DEL 7 AL 14'!BT17+'SEMANA DEL 14 AL 21 '!BT17+'SEMANA DEL 21AL 28-3'!BT18+#REF! -> #REF! | BU13: =+'SEMANA DEL 2 AL 7-3-26'!BU13+'SEMANA DEL 7 AL 14'!BU17+'SEMANA DEL 14 AL 21 '!BU17+'SEMANA DEL 21AL 28-3'!BU18+#REF! -> #REF! | ... CI13: =+'SEMANA DEL 2 AL 7-3-26'!CI13+'SEMANA DEL 7 AL 14'!CI17+'SEMANA DEL 14 AL 21 '!CI17+'SEMANA DEL 21AL 28-3'!CI18+#REF! -> #REF!
A14: =+'SEMANA DEL 2 AL 7-3-26'!A13 -> HUGO ALMEIDA | B14: =+'SEMANA DEL 2 AL 7-3-26'!B13 -> 0 | C14: =+'SEMANA DEL 2 AL 7-3-26'!C13 -> 0 | D14: =+'SEMANA DEL 2 AL 7-3-26'!D13 -> 0 | E14: =+'SEMANA DEL 2 AL 7-3-26'!E13 -> 0 | F14: =+'SEMANA DEL 2 AL 7-3-26'!F13 -> 0 | G14: =+'SEMANA DEL 2 AL 7-3-26'!G13 -> 0 | H14: =+'SEMANA DEL 2 AL 7-3-26'!H13 -> 0 | ... Q14: =+'SEMANA DEL 2 AL 7-3-26'!Q13 -> 0 | R14: =+'SEMANA DEL 2 AL 7-3-26'!R14+'SEMANA DEL 7 AL 14'!#REF!+'SEMANA DEL 14 AL 21 '!#REF!+'SEMANA DEL 21AL 28-3'!#REF!+#REF! -> #REF! | S14: =+'SEMANA DEL 2 AL 7-3-26'!S14+'SEMANA DEL 7 AL 14'!#REF!+'SEMANA DEL 14 AL 21 '!#REF!+'SEMANA DEL 21AL 28-3'!#REF!+#REF! -> #REF! | T14: =+'SEMANA DEL 2 AL 7-3-26'!T14+'SEMANA DEL 7 AL 14'!#REF!+'SEMANA DEL 14 AL 21 '!#REF!+'SEMANA DEL 21AL 28-3'!#REF!+#REF! -> #REF! | U14: =+'SEMANA DEL 2 AL 7-3-26'!U14+'SEMANA DEL 7 AL 14'!#REF!+'SEMANA DEL 14 AL 21 '!#REF!+'SEMANA DEL 21AL 28-3'!#REF!+#REF! -> #REF! | V14: =+'SEMANA DEL 2 AL 7-3-26'!V14+'SEMANA DEL 7 AL 14'!#REF!+'SEMANA DEL 14 AL 21 '!#REF!+'SEMANA DEL 21AL 28-3'!#REF!+#REF! -> #REF! | W14: =+'SEMANA DEL 2 AL 7-3-26'!W14+'SEMANA DEL 7 AL 14'!#REF!+'SEMANA DEL 14 AL 21 '!#REF!+'SEMANA DEL 21AL 28-3'!#REF!+#REF! -> #REF! | X14: =+'SEMANA DEL 2 AL 7-3-26'!X14+'SEMANA DEL 7 AL 14'!#REF!+'SEMANA DEL 14 AL 21 '!#REF!+'SEMANA DEL 21AL 28-3'!#REF!+#REF! -> #REF! | Y14: =+'SEMANA DEL 2 AL 7-3-26'!Y14+'SEMANA DEL 7 AL 14'!#REF!+'SEMANA DEL 14 AL 21 '!#REF!+'SEMANA DEL 21AL 28-3'!#REF!+#REF! -> #REF! | ... AW14: =+'SEMANA DEL 2 AL 7-3-26'!AW14+'SEMANA DEL 7 AL 14'!#REF!+'SEMANA DEL 14 AL 21 '!#REF!+'SEMANA DEL 21AL 28-3'!#REF!+#REF! -> #REF! | AX14: =+B14+R14-AH14 -> #REF! | AY14: =+C14+S14-AI14 -> #REF! | AZ14: =+D14+T14-AJ14 -> #REF! | BA14: =+E14+U14-AK14 -> #REF! | BB14: =+F14+V14-AL14 -> #REF! | BC14: =+G14+W14-AM14 -> #REF! | BD14: =+H14+X14-AN14 -> #REF! | BE14: =+I14+Y14-AO14 -> #REF! | ... BM14: =+Q14+AG14-AW14 -> #REF! | BN14: =+'SEMANA DEL 2 AL 7-3-26'!BN14+'SEMANA DEL 7 AL 14'!#REF!+'SEMANA DEL 14 AL 21 '!#REF!+'SEMANA DEL 21AL 28-3'!#REF!+#REF! -> #REF! | BO14: =+'SEMANA DEL 2 AL 7-3-26'!BO14+'SEMANA DEL 7 AL 14'!#REF!+'SEMANA DEL 14 AL 21 '!#REF!+'SEMANA DEL 21AL 28-3'!#REF!+#REF! -> #REF! | BP14: =+'SEMANA DEL 2 AL 7-3-26'!BP14+'SEMANA DEL 7 AL 14'!#REF!+'SEMANA DEL 14 AL 21 '!#REF!+'SEMANA DEL 21AL 28-3'!#REF!+#REF! -> #REF! | BQ14: =+'SEMANA DEL 2 AL 7-3-26'!BQ14+'SEMANA DEL 7 AL 14'!#REF!+'SEMANA DEL 14 AL 21 '!#REF!+'SEMANA DEL 21AL 28-3'!#REF!+#REF! -> #REF! | BR14: =+'SEMANA DEL 2 AL 7-3-26'!BR14+'SEMANA DEL 7 AL 14'!#REF!+'SEMANA DEL 14 AL 21 '!#REF!+'SEMANA DEL 21AL 28-3'!#REF!+#REF! -> #REF! | BS14: =+'SEMANA DEL 2 AL 7-3-26'!BS14+'SEMANA DEL 7 AL 14'!#REF!+'SEMANA DEL 14 AL 21 '!#REF!+'SEMANA DEL 21AL 28-3'!#REF!+#REF! -> #REF! | BT14: =+'SEMANA DEL 2 AL 7-3-26'!BT14+'SEMANA DEL 7 AL 14'!#REF!+'SEMANA DEL 14 AL 21 '!#REF!+'SEMANA DEL 21AL 28-3'!#REF!+#REF! -> #REF! | BU14: =+'SEMANA DEL 2 AL 7-3-26'!BU14+'SEMANA DEL 7 AL 14'!#REF!+'SEMANA DEL 14 AL 21 '!#REF!+'SEMANA DEL 21AL 28-3'!#REF!+#REF! -> #REF! | ... CI14: =+'SEMANA DEL 2 AL 7-3-26'!CI14+'SEMANA DEL 7 AL 14'!#REF!+'SEMANA DEL 14 AL 21 '!#REF!+'SEMANA DEL 21AL 28-3'!#REF!+#REF! -> #REF!
A15: =+'SEMANA DEL 2 AL 7-3-26'!A14 -> HILDA SERRANO | B15: =+'SEMANA DEL 2 AL 7-3-26'!B14 -> 1 | C15: =+'SEMANA DEL 2 AL 7-3-26'!C14 -> 1.8 | D15: =+'SEMANA DEL 2 AL 7-3-26'!D14 -> 7 | E15: =+'SEMANA DEL 2 AL 7-3-26'!E14 -> 0 | F15: =+'SEMANA DEL 2 AL 7-3-26'!F14 -> 0 | G15: =+'SEMANA DEL 2 AL 7-3-26'!G14 -> 0 | H15: =+'SEMANA DEL 2 AL 7-3-26'!H14 -> 0 | ... Q15: =+'SEMANA DEL 2 AL 7-3-26'!Q14 -> 0 | R15: =+'SEMANA DEL 2 AL 7-3-26'!R16+'SEMANA DEL 7 AL 14'!R20+'SEMANA DEL 14 AL 21 '!R20+'SEMANA DEL 21AL 28-3'!R21+#REF! -> #REF! | S15: =+'SEMANA DEL 2 AL 7-3-26'!S16+'SEMANA DEL 7 AL 14'!S20+'SEMANA DEL 14 AL 21 '!S20+'SEMANA DEL 21AL 28-3'!S21+#REF! -> #REF! | T15: =+'SEMANA DEL 2 AL 7-3-26'!T16+'SEMANA DEL 7 AL 14'!T20+'SEMANA DEL 14 AL 21 '!T20+'SEMANA DEL 21AL 28-3'!T21+#REF! -> #REF! | U15: =+'SEMANA DEL 2 AL 7-3-26'!U16+'SEMANA DEL 7 AL 14'!U20+'SEMANA DEL 14 AL 21 '!U20+'SEMANA DEL 21AL 28-3'!U21+#REF! -> #REF! | V15: =+'SEMANA DEL 2 AL 7-3-26'!V16+'SEMANA DEL 7 AL 14'!V20+'SEMANA DEL 14 AL 21 '!V20+'SEMANA DEL 21AL 28-3'!V21+#REF! -> #REF! | W15: =+'SEMANA DEL 2 AL 7-3-26'!W16+'SEMANA DEL 7 AL 14'!W20+'SEMANA DEL 14 AL 21 '!W20+'SEMANA DEL 21AL 28-3'!W21+#REF! -> #REF! | X15: =+'SEMANA DEL 2 AL 7-3-26'!X16+'SEMANA DEL 7 AL 14'!X20+'SEMANA DEL 14 AL 21 '!X20+'SEMANA DEL 21AL 28-3'!X21+#REF! -> #REF! | Y15: =+'SEMANA DEL 2 AL 7-3-26'!Y16+'SEMANA DEL 7 AL 14'!Y20+'SEMANA DEL 14 AL 21 '!Y20+'SEMANA DEL 21AL 28-3'!Y21+#REF! -> #REF! | ... AW15: =+'SEMANA DEL 2 AL 7-3-26'!AW16+'SEMANA DEL 7 AL 14'!AW20+'SEMANA DEL 14 AL 21 '!AW20+'SEMANA DEL 21AL 28-3'!AW21+#REF! -> #REF! | AX15: =+B15+R15-AH15 -> #REF! | AY15: =+C15+S15-AI15 -> #REF! | AZ15: =+D15+T15-AJ15 -> #REF! | BA15: =+E15+U15-AK15 -> #REF! | BB15: =+F15+V15-AL15 -> #REF! | BC15: =+G15+W15-AM15 -> #REF! | BD15: =+H15+X15-AN15 -> #REF! | BE15: =+I15+Y15-AO15 -> #REF! | ... BM15: =+Q15+AG15-AW15 -> #REF! | BN15: =+'SEMANA DEL 2 AL 7-3-26'!BN16+'SEMANA DEL 7 AL 14'!BN20+'SEMANA DEL 14 AL 21 '!BN20+'SEMANA DEL 21AL 28-3'!BN21+#REF! -> #REF! | BO15: =+'SEMANA DEL 2 AL 7-3-26'!BO16+'SEMANA DEL 7 AL 14'!BO20+'SEMANA DEL 14 AL 21 '!BO20+'SEMANA DEL 21AL 28-3'!BO21+#REF! -> #REF! | BP15: =+'SEMANA DEL 2 AL 7-3-26'!BP16+'SEMANA DEL 7 AL 14'!BP20+'SEMANA DEL 14 AL 21 '!BP20+'SEMANA DEL 21AL 28-3'!BP21+#REF! -> #REF! | BQ15: =+'SEMANA DEL 2 AL 7-3-26'!BQ16+'SEMANA DEL 7 AL 14'!BQ20+'SEMANA DEL 14 AL 21 '!BQ20+'SEMANA DEL 21AL 28-3'!BQ21+#REF! -> #REF! | BR15: =+'SEMANA DEL 2 AL 7-3-26'!BR16+'SEMANA DEL 7 AL 14'!BR20+'SEMANA DEL 14 AL 21 '!BR20+'SEMANA DEL 21AL 28-3'!BR21+#REF! -> #REF! | BS15: =+'SEMANA DEL 2 AL 7-3-26'!BS16+'SEMANA DEL 7 AL 14'!BS20+'SEMANA DEL 14 AL 21 '!BS20+'SEMANA DEL 21AL 28-3'!BS21+#REF! -> #REF! | BT15: =+'SEMANA DEL 2 AL 7-3-26'!BT16+'SEMANA DEL 7 AL 14'!BT20+'SEMANA DEL 14 AL 21 '!BT20+'SEMANA DEL 21AL 28-3'!BT21+#REF! -> #REF! | BU15: =+'SEMANA DEL 2 AL 7-3-26'!BU16+'SEMANA DEL 7 AL 14'!BU20+'SEMANA DEL 14 AL 21 '!BU20+'SEMANA DEL 21AL 28-3'!BU21+#REF! -> #REF! | ... CI15: =+'SEMANA DEL 2 AL 7-3-26'!CI16+'SEMANA DEL 7 AL 14'!CI20+'SEMANA DEL 14 AL 21 '!CI20+'SEMANA DEL 21AL 28-3'!CI21+#REF! -> #REF!
A16: =+'SEMANA DEL 2 AL 7-3-26'!A16 -> JOSE EBLAN GIRON | B16: =+'SEMANA DEL 2 AL 7-3-26'!B16 -> 0.2 | C16: =+'SEMANA DEL 2 AL 7-3-26'!C16 -> 0.36 | D16: =+'SEMANA DEL 2 AL 7-3-26'!D16 -> 1.4 | E16: =+'SEMANA DEL 2 AL 7-3-26'!E16 -> 1 | F16: =+'SEMANA DEL 2 AL 7-3-26'!F16 -> 0 | G16: =+'SEMANA DEL 2 AL 7-3-26'!G16 -> 0 | H16: =+'SEMANA DEL 2 AL 7-3-26'!H16 -> 0 | ... Q16: =+'SEMANA DEL 2 AL 7-3-26'!Q16 -> 0 | R16: =+'SEMANA DEL 2 AL 7-3-26'!R17+'SEMANA DEL 7 AL 14'!R23+'SEMANA DEL 14 AL 21 '!R21+'SEMANA DEL 21AL 28-3'!R22+#REF! -> #REF! | S16: =+'SEMANA DEL 2 AL 7-3-26'!S17+'SEMANA DEL 7 AL 14'!S23+'SEMANA DEL 14 AL 21 '!S21+'SEMANA DEL 21AL 28-3'!S22+#REF! -> #REF! | T16: =+'SEMANA DEL 2 AL 7-3-26'!T17+'SEMANA DEL 7 AL 14'!T23+'SEMANA DEL 14 AL 21 '!T21+'SEMANA DEL 21AL 28-3'!T22+#REF! -> #REF! | U16: =+'SEMANA DEL 2 AL 7-3-26'!U17+'SEMANA DEL 7 AL 14'!U23+'SEMANA DEL 14 AL 21 '!U21+'SEMANA DEL 21AL 28-3'!U22+#REF! -> #REF! | V16: =+'SEMANA DEL 2 AL 7-3-26'!V17+'SEMANA DEL 7 AL 14'!V23+'SEMANA DEL 14 AL 21 '!V21+'SEMANA DEL 21AL 28-3'!V22+#REF! -> #REF! | W16: =+'SEMANA DEL 2 AL 7-3-26'!W17+'SEMANA DEL 7 AL 14'!W23+'SEMANA DEL 14 AL 21 '!W21+'SEMANA DEL 21AL 28-3'!W22+#REF! -> #REF! | X16: =+'SEMANA DEL 2 AL 7-3-26'!X17+'SEMANA DEL 7 AL 14'!X23+'SEMANA DEL 14 AL 21 '!X21+'SEMANA DEL 21AL 28-3'!X22+#REF! -> #REF! | Y16: =+'SEMANA DEL 2 AL 7-3-26'!Y17+'SEMANA DEL 7 AL 14'!Y23+'SEMANA DEL 14 AL 21 '!Y21+'SEMANA DEL 21AL 28-3'!Y22+#REF! -> #REF! | ... AW16: =+'SEMANA DEL 2 AL 7-3-26'!AW17+'SEMANA DEL 7 AL 14'!AW23+'SEMANA DEL 14 AL 21 '!AW21+'SEMANA DEL 21AL 28-3'!AW22+#REF! -> #REF! | AX16: =+B16+R16-AH16 -> #REF! | AY16: =+C16+S16-AI16 -> #REF! | AZ16: =+D16+T16-AJ16 -> #REF! | BA16: =+E16+U16-AK16 -> #REF! | BB16: =+F16+V16-AL16 -> #REF! | BC16: =+G16+W16-AM16 -> #REF! | BD16: =+H16+X16-AN16 -> #REF! | BE16: =+I16+Y16-AO16 -> #REF! | ... BM16: =+Q16+AG16-AW16 -> #REF! | BN16: =+'SEMANA DEL 2 AL 7-3-26'!BN17+'SEMANA DEL 7 AL 14'!BN23+'SEMANA DEL 14 AL 21 '!BN21+'SEMANA DEL 21AL 28-3'!BN22+#REF! -> #REF! | BO16: =+'SEMANA DEL 2 AL 7-3-26'!BO17+'SEMANA DEL 7 AL 14'!BO23+'SEMANA DEL 14 AL 21 '!BO21+'SEMANA DEL 21AL 28-3'!BO22+#REF! -> #REF! | BP16: =+'SEMANA DEL 2 AL 7-3-26'!BP17+'SEMANA DEL 7 AL 14'!BP23+'SEMANA DEL 14 AL 21 '!BP21+'SEMANA DEL 21AL 28-3'!BP22+#REF! -> #REF! | BQ16: =+'SEMANA DEL 2 AL 7-3-26'!BQ17+'SEMANA DEL 7 AL 14'!BQ23+'SEMANA DEL 14 AL 21 '!BQ21+'SEMANA DEL 21AL 28-3'!BQ22+#REF! -> #REF! | BR16: =+'SEMANA DEL 2 AL 7-3-26'!BR17+'SEMANA DEL 7 AL 14'!BR23+'SEMANA DEL 14 AL 21 '!BR21+'SEMANA DEL 21AL 28-3'!BR22+#REF! -> #REF! | BS16: =+'SEMANA DEL 2 AL 7-3-26'!BS17+'SEMANA DEL 7 AL 14'!BS23+'SEMANA DEL 14 AL 21 '!BS21+'SEMANA DEL 21AL 28-3'!BS22+#REF! -> #REF! | BT16: =+'SEMANA DEL 2 AL 7-3-26'!BT17+'SEMANA DEL 7 AL 14'!BT23+'SEMANA DEL 14 AL 21 '!BT21+'SEMANA DEL 21AL 28-3'!BT22+#REF! -> #REF! | BU16: =+'SEMANA DEL 2 AL 7-3-26'!BU17+'SEMANA DEL 7 AL 14'!BU23+'SEMANA DEL 14 AL 21 '!BU21+'SEMANA DEL 21AL 28-3'!BU22+#REF! -> #REF! | ... CI16: =+'SEMANA DEL 2 AL 7-3-26'!CI17+'SEMANA DEL 7 AL 14'!CI23+'SEMANA DEL 14 AL 21 '!CI21+'SEMANA DEL 21AL 28-3'!CI22+#REF! -> #REF!
A17: =+'SEMANA DEL 2 AL 7-3-26'!A17 -> JOSE JURADO | B17: =+'SEMANA DEL 2 AL 7-3-26'!B17 -> 0 | C17: =+'SEMANA DEL 2 AL 7-3-26'!C17 -> 0 | D17: =+'SEMANA DEL 2 AL 7-3-26'!D17 -> 0 | E17: =+'SEMANA DEL 2 AL 7-3-26'!E17 -> 0 | F17: =+'SEMANA DEL 2 AL 7-3-26'!F17 -> 0 | G17: =+'SEMANA DEL 2 AL 7-3-26'!G17 -> 0 | H17: =+'SEMANA DEL 2 AL 7-3-26'!H17 -> 0 | ... Q17: =+'SEMANA DEL 2 AL 7-3-26'!Q17 -> 0 | R17: =+'SEMANA DEL 2 AL 7-3-26'!#REF!+'SEMANA DEL 7 AL 14'!R24+'SEMANA DEL 14 AL 21 '!R22+'SEMANA DEL 21AL 28-3'!R23+#REF! -> #REF! | S17: =+'SEMANA DEL 2 AL 7-3-26'!#REF!+'SEMANA DEL 7 AL 14'!S24+'SEMANA DEL 14 AL 21 '!S22+'SEMANA DEL 21AL 28-3'!S23+#REF! -> #REF! | T17: =+'SEMANA DEL 2 AL 7-3-26'!#REF!+'SEMANA DEL 7 AL 14'!T24+'SEMANA DEL 14 AL 21 '!T22+'SEMANA DEL 21AL 28-3'!T23+#REF! -> #REF! | U17: =+'SEMANA DEL 2 AL 7-3-26'!#REF!+'SEMANA DEL 7 AL 14'!U24+'SEMANA DEL 14 AL 21 '!U22+'SEMANA DEL 21AL 28-3'!U23+#REF! -> #REF! | V17: =+'SEMANA DEL 2 AL 7-3-26'!#REF!+'SEMANA DEL 7 AL 14'!V24+'SEMANA DEL 14 AL 21 '!V22+'SEMANA DEL 21AL 28-3'!V23+#REF! -> #REF! | W17: =+'SEMANA DEL 2 AL 7-3-26'!#REF!+'SEMANA DEL 7 AL 14'!W24+'SEMANA DEL 14 AL 21 '!W22+'SEMANA DEL 21AL 28-3'!W23+#REF! -> #REF! | X17: =+'SEMANA DEL 2 AL 7-3-26'!#REF!+'SEMANA DEL 7 AL 14'!X24+'SEMANA DEL 14 AL 21 '!X22+'SEMANA DEL 21AL 28-3'!X23+#REF! -> #REF! | Y17: =+'SEMANA DEL 2 AL 7-3-26'!#REF!+'SEMANA DEL 7 AL 14'!Y24+'SEMANA DEL 14 AL 21 '!Y22+'SEMANA DEL 21AL 28-3'!Y23+#REF! -> #REF! | ... AW17: =+'SEMANA DEL 2 AL 7-3-26'!#REF!+'SEMANA DEL 7 AL 14'!AW24+'SEMANA DEL 14 AL 21 '!AW22+'SEMANA DEL 21AL 28-3'!AW23+#REF! -> #REF! | AX17: =+B17+R17-AH17 -> #REF! | AY17: =+C17+S17-AI17 -> #REF! | AZ17: =+D17+T17-AJ17 -> #REF! | BA17: =+E17+U17-AK17 -> #REF! | BB17: =+F17+V17-AL17 -> #REF! | BC17: =+G17+W17-AM17 -> #REF! | BD17: =+H17+X17-AN17 -> #REF! | BE17: =+I17+Y17-AO17 -> #REF! | ... BM17: =+Q17+AG17-AW17 -> #REF! | BN17: =+'SEMANA DEL 2 AL 7-3-26'!#REF!+'SEMANA DEL 7 AL 14'!BN24+'SEMANA DEL 14 AL 21 '!BN22+'SEMANA DEL 21AL 28-3'!BN23+#REF! -> #REF! | BO17: =+'SEMANA DEL 2 AL 7-3-26'!#REF!+'SEMANA DEL 7 AL 14'!BO24+'SEMANA DEL 14 AL 21 '!BO22+'SEMANA DEL 21AL 28-3'!BO23+#REF! -> #REF! | BP17: =+'SEMANA DEL 2 AL 7-3-26'!#REF!+'SEMANA DEL 7 AL 14'!BP24+'SEMANA DEL 14 AL 21 '!BP22+'SEMANA DEL 21AL 28-3'!BP23+#REF! -> #REF! | BQ17: =+'SEMANA DEL 2 AL 7-3-26'!#REF!+'SEMANA DEL 7 AL 14'!BQ24+'SEMANA DEL 14 AL 21 '!BQ22+'SEMANA DEL 21AL 28-3'!BQ23+#REF! -> #REF! | BR17: =+'SEMANA DEL 2 AL 7-3-26'!#REF!+'SEMANA DEL 7 AL 14'!BR24+'SEMANA DEL 14 AL 21 '!BR22+'SEMANA DEL 21AL 28-3'!BR23+#REF! -> #REF! | BS17: =+'SEMANA DEL 2 AL 7-3-26'!#REF!+'SEMANA DEL 7 AL 14'!BS24+'SEMANA DEL 14 AL 21 '!BS22+'SEMANA DEL 21AL 28-3'!BS23+#REF! -> #REF! | BT17: =+'SEMANA DEL 2 AL 7-3-26'!#REF!+'SEMANA DEL 7 AL 14'!BT24+'SEMANA DEL 14 AL 21 '!BT22+'SEMANA DEL 21AL 28-3'!BT23+#REF! -> #REF! | BU17: =+'SEMANA DEL 2 AL 7-3-26'!#REF!+'SEMANA DEL 7 AL 14'!BU24+'SEMANA DEL 14 AL 21 '!BU22+'SEMANA DEL 21AL 28-3'!BU23+#REF! -> #REF! | ... CI17: =+'SEMANA DEL 2 AL 7-3-26'!#REF!+'SEMANA DEL 7 AL 14'!CI24+'SEMANA DEL 14 AL 21 '!CI22+'SEMANA DEL 21AL 28-3'!CI23+#REF! -> #REF!
A18: =+'SEMANA DEL 2 AL 7-3-26'!#REF! -> #REF! | B18: =+'SEMANA DEL 2 AL 7-3-26'!#REF! -> #REF! | C18: =+'SEMANA DEL 2 AL 7-3-26'!#REF! -> #REF! | D18: =+'SEMANA DEL 2 AL 7-3-26'!#REF! -> #REF! | E18: =+'SEMANA DEL 2 AL 7-3-26'!#REF! -> #REF! | F18: =+'SEMANA DEL 2 AL 7-3-26'!#REF! -> #REF! | G18: =+'SEMANA DEL 2 AL 7-3-26'!#REF! -> #REF! | H18: =+'SEMANA DEL 2 AL 7-3-26'!#REF! -> #REF! | ... Q18: =+'SEMANA DEL 2 AL 7-3-26'!#REF! -> #REF! | R18: =+'SEMANA DEL 2 AL 7-3-26'!#REF!+'SEMANA DEL 7 AL 14'!R25+'SEMANA DEL 14 AL 21 '!R23+'SEMANA DEL 21AL 28-3'!R24+#REF! -> #REF! | S18: =+'SEMANA DEL 2 AL 7-3-26'!#REF!+'SEMANA DEL 7 AL 14'!S25+'SEMANA DEL 14 AL 21 '!S23+'SEMANA DEL 21AL 28-3'!S24+#REF! -> #REF! | T18: =+'SEMANA DEL 2 AL 7-3-26'!#REF!+'SEMANA DEL 7 AL 14'!T25+'SEMANA DEL 14 AL 21 '!T23+'SEMANA DEL 21AL 28-3'!T24+#REF! -> #REF! | U18: =+'SEMANA DEL 2 AL 7-3-26'!#REF!+'SEMANA DEL 7 AL 14'!U25+'SEMANA DEL 14 AL 21 '!U23+'SEMANA DEL 21AL 28-3'!U24+#REF! -> #REF! | V18: =+'SEMANA DEL 2 AL 7-3-26'!#REF!+'SEMANA DEL 7 AL 14'!V25+'SEMANA DEL 14 AL 21 '!V23+'SEMANA DEL 21AL 28-3'!V24+#REF! -> #REF! | W18: =+'SEMANA DEL 2 AL 7-3-26'!#REF!+'SEMANA DEL 7 AL 14'!W25+'SEMANA DEL 14 AL 21 '!W23+'SEMANA DEL 21AL 28-3'!W24+#REF! -> #REF! | X18: =+'SEMANA DEL 2 AL 7-3-26'!#REF!+'SEMANA DEL 7 AL 14'!X25+'SEMANA DEL 14 AL 21 '!X23+'SEMANA DEL 21AL 28-3'!X24+#REF! -> #REF! | Y18: =+'SEMANA DEL 2 AL 7-3-26'!#REF!+'SEMANA DEL 7 AL 14'!Y25+'SEMANA DEL 14 AL 21 '!Y23+'SEMANA DEL 21AL 28-3'!Y24+#REF! -> #REF! | ... AW18: =+'SEMANA DEL 2 AL 7-3-26'!#REF!+'SEMANA DEL 7 AL 14'!AW25+'SEMANA DEL 14 AL 21 '!AW23+'SEMANA DEL 21AL 28-3'!AW24+#REF! -> #REF! | AX18: =+B18+R18-AH18 -> #REF! | AY18: =+C18+S18-AI18 -> #REF! | AZ18: =+D18+T18-AJ18 -> #REF! | BA18: =+E18+U18-AK18 -> #REF! | BB18: =+F18+V18-AL18 -> #REF! | BC18: =+G18+W18-AM18 -> #REF! | BD18: =+H18+X18-AN18 -> #REF! | BE18: =+I18+Y18-AO18 -> #REF! | ... BM18: =+Q18+AG18-AW18 -> #REF! | BN18: =+'SEMANA DEL 2 AL 7-3-26'!#REF!+'SEMANA DEL 7 AL 14'!BN25+'SEMANA DEL 14 AL 21 '!BN23+'SEMANA DEL 21AL 28-3'!BN24+#REF! -> #REF! | BO18: =+'SEMANA DEL 2 AL 7-3-26'!#REF!+'SEMANA DEL 7 AL 14'!BO25+'SEMANA DEL 14 AL 21 '!BO23+'SEMANA DEL 21AL 28-3'!BO24+#REF! -> #REF! | BP18: =+'SEMANA DEL 2 AL 7-3-26'!#REF!+'SEMANA DEL 7 AL 14'!BP25+'SEMANA DEL 14 AL 21 '!BP23+'SEMANA DEL 21AL 28-3'!BP24+#REF! -> #REF! | BQ18: =+'SEMANA DEL 2 AL 7-3-26'!#REF!+'SEMANA DEL 7 AL 14'!BQ25+'SEMANA DEL 14 AL 21 '!BQ23+'SEMANA DEL 21AL 28-3'!BQ24+#REF! -> #REF! | BR18: =+'SEMANA DEL 2 AL 7-3-26'!#REF!+'SEMANA DEL 7 AL 14'!BR25+'SEMANA DEL 14 AL 21 '!BR23+'SEMANA DEL 21AL 28-3'!BR24+#REF! -> #REF! | BS18: =+'SEMANA DEL 2 AL 7-3-26'!#REF!+'SEMANA DEL 7 AL 14'!BS25+'SEMANA DEL 14 AL 21 '!BS23+'SEMANA DEL 21AL 28-3'!BS24+#REF! -> #REF! | BT18: =+'SEMANA DEL 2 AL 7-3-26'!#REF!+'SEMANA DEL 7 AL 14'!BT25+'SEMANA DEL 14 AL 21 '!BT23+'SEMANA DEL 21AL 28-3'!BT24+#REF! -> #REF! | BU18: =+'SEMANA DEL 2 AL 7-3-26'!#REF!+'SEMANA DEL 7 AL 14'!BU25+'SEMANA DEL 14 AL 21 '!BU23+'SEMANA DEL 21AL 28-3'!BU24+#REF! -> #REF! | ... CI18: =+'SEMANA DEL 2 AL 7-3-26'!#REF!+'SEMANA DEL 7 AL 14'!CI25+'SEMANA DEL 14 AL 21 '!CI23+'SEMANA DEL 21AL 28-3'!CI24+#REF! -> #REF!
A19: =+'SEMANA DEL 2 AL 7-3-26'!#REF! -> #REF! | B19: =+'SEMANA DEL 2 AL 7-3-26'!#REF! -> #REF! | C19: =+'SEMANA DEL 2 AL 7-3-26'!#REF! -> #REF! | D19: =+'SEMANA DEL 2 AL 7-3-26'!#REF! -> #REF! | E19: =+'SEMANA DEL 2 AL 7-3-26'!#REF! -> #REF! | F19: =+'SEMANA DEL 2 AL 7-3-26'!#REF! -> #REF! | G19: =+'SEMANA DEL 2 AL 7-3-26'!#REF! -> #REF! | H19: =+'SEMANA DEL 2 AL 7-3-26'!#REF! -> #REF! | ... Q19: =+'SEMANA DEL 2 AL 7-3-26'!#REF! -> #REF! | R19: =+'SEMANA DEL 2 AL 7-3-26'!R20+'SEMANA DEL 7 AL 14'!R26+'SEMANA DEL 14 AL 21 '!R24+'SEMANA DEL 21AL 28-3'!R25+#REF! -> #REF! | S19: =+'SEMANA DEL 2 AL 7-3-26'!S20+'SEMANA DEL 7 AL 14'!S26+'SEMANA DEL 14 AL 21 '!S24+'SEMANA DEL 21AL 28-3'!S25+#REF! -> #REF! | T19: =+'SEMANA DEL 2 AL 7-3-26'!T20+'SEMANA DEL 7 AL 14'!T26+'SEMANA DEL 14 AL 21 '!T24+'SEMANA DEL 21AL 28-3'!T25+#REF! -> #REF! | U19: =+'SEMANA DEL 2 AL 7-3-26'!U20+'SEMANA DEL 7 AL 14'!U26+'SEMANA DEL 14 AL 21 '!U24+'SEMANA DEL 21AL 28-3'!U25+#REF! -> #REF! | V19: =+'SEMANA DEL 2 AL 7-3-26'!V20+'SEMANA DEL 7 AL 14'!V26+'SEMANA DEL 14 AL 21 '!V24+'SEMANA DEL 21AL 28-3'!V25+#REF! -> #REF! | W19: =+'SEMANA DEL 2 AL 7-3-26'!W20+'SEMANA DEL 7 AL 14'!W26+'SEMANA DEL 14 AL 21 '!W24+'SEMANA DEL 21AL 28-3'!W25+#REF! -> #REF! | X19: =+'SEMANA DEL 2 AL 7-3-26'!X20+'SEMANA DEL 7 AL 14'!X26+'SEMANA DEL 14 AL 21 '!X24+'SEMANA DEL 21AL 28-3'!X25+#REF! -> #REF! | Y19: =+'SEMANA DEL 2 AL 7-3-26'!Y20+'SEMANA DEL 7 AL 14'!Y26+'SEMANA DEL 14 AL 21 '!Y24+'SEMANA DEL 21AL 28-3'!Y25+#REF! -> #REF! | ... AW19: =+'SEMANA DEL 2 AL 7-3-26'!AW20+'SEMANA DEL 7 AL 14'!AW26+'SEMANA DEL 14 AL 21 '!AW24+'SEMANA DEL 21AL 28-3'!AW25+#REF! -> #REF! | AX19: =+B19+R19-AH19 -> #REF! | AY19: =+C19+S19-AI19 -> #REF! | AZ19: =+D19+T19-AJ19 -> #REF! | BA19: =+E19+U19-AK19 -> #REF! | BB19: =+F19+V19-AL19 -> #REF! | BC19: =+G19+W19-AM19 -> #REF! | BD19: =+H19+X19-AN19 -> #REF! | BE19: =+I19+Y19-AO19 -> #REF! | ... BM19: =+Q19+AG19-AW19 -> #REF! | BN19: =+'SEMANA DEL 2 AL 7-3-26'!BN20+'SEMANA DEL 7 AL 14'!BN26+'SEMANA DEL 14 AL 21 '!BN24+'SEMANA DEL 21AL 28-3'!BN25+#REF! -> #REF! | BO19: =+'SEMANA DEL 2 AL 7-3-26'!BO20+'SEMANA DEL 7 AL 14'!BO26+'SEMANA DEL 14 AL 21 '!BO24+'SEMANA DEL 21AL 28-3'!BO25+#REF! -> #REF! | BP19: =+'SEMANA DEL 2 AL 7-3-26'!BP20+'SEMANA DEL 7 AL 14'!BP26+'SEMANA DEL 14 AL 21 '!BP24+'SEMANA DEL 21AL 28-3'!BP25+#REF! -> #REF! | BQ19: =+'SEMANA DEL 2 AL 7-3-26'!BQ20+'SEMANA DEL 7 AL 14'!BQ26+'SEMANA DEL 14 AL 21 '!BQ24+'SEMANA DEL 21AL 28-3'!BQ25+#REF! -> #REF! | BR19: =+'SEMANA DEL 2 AL 7-3-26'!BR20+'SEMANA DEL 7 AL 14'!BR26+'SEMANA DEL 14 AL 21 '!BR24+'SEMANA DEL 21AL 28-3'!BR25+#REF! -> #REF! | BS19: =+'SEMANA DEL 2 AL 7-3-26'!BS20+'SEMANA DEL 7 AL 14'!BS26+'SEMANA DEL 14 AL 21 '!BS24+'SEMANA DEL 21AL 28-3'!BS25+#REF! -> #REF! | BT19: =+'SEMANA DEL 2 AL 7-3-26'!BT20+'SEMANA DEL 7 AL 14'!BT26+'SEMANA DEL 14 AL 21 '!BT24+'SEMANA DEL 21AL 28-3'!BT25+#REF! -> #REF! | BU19: =+'SEMANA DEL 2 AL 7-3-26'!BU20+'SEMANA DEL 7 AL 14'!BU26+'SEMANA DEL 14 AL 21 '!BU24+'SEMANA DEL 21AL 28-3'!BU25+#REF! -> #REF! | ... CI19: =+'SEMANA DEL 2 AL 7-3-26'!CI20+'SEMANA DEL 7 AL 14'!CI26+'SEMANA DEL 14 AL 21 '!CI24+'SEMANA DEL 21AL 28-3'!CI25+#REF! -> #REF!
A20: =+'SEMANA DEL 2 AL 7-3-26'!A20 -> LUIS ROJAS | B20: =+'SEMANA DEL 2 AL 7-3-26'!B20 -> 0 | C20: =+'SEMANA DEL 2 AL 7-3-26'!C20 -> 0 | D20: =+'SEMANA DEL 2 AL 7-3-26'!D20 -> 0 | E20: =+'SEMANA DEL 2 AL 7-3-26'!E20 -> 0 | F20: =+'SEMANA DEL 2 AL 7-3-26'!F20 -> 0 | G20: =+'SEMANA DEL 2 AL 7-3-26'!G20 -> 0 | H20: =+'SEMANA DEL 2 AL 7-3-26'!H20 -> 0 | ... Q20: =+'SEMANA DEL 2 AL 7-3-26'!Q20 -> 0 | R20: =+'SEMANA DEL 2 AL 7-3-26'!R21+'SEMANA DEL 7 AL 14'!#REF!+'SEMANA DEL 14 AL 21 '!R25+'SEMANA DEL 21AL 28-3'!R26+#REF! -> #REF! | S20: =+'SEMANA DEL 2 AL 7-3-26'!S21+'SEMANA DEL 7 AL 14'!#REF!+'SEMANA DEL 14 AL 21 '!S25+'SEMANA DEL 21AL 28-3'!S26+#REF! -> #REF! | T20: =+'SEMANA DEL 2 AL 7-3-26'!T21+'SEMANA DEL 7 AL 14'!#REF!+'SEMANA DEL 14 AL 21 '!T25+'SEMANA DEL 21AL 28-3'!T26+#REF! -> #REF! | U20: =+'SEMANA DEL 2 AL 7-3-26'!U21+'SEMANA DEL 7 AL 14'!#REF!+'SEMANA DEL 14 AL 21 '!U25+'SEMANA DEL 21AL 28-3'!U26+#REF! -> #REF! | V20: =+'SEMANA DEL 2 AL 7-3-26'!V21+'SEMANA DEL 7 AL 14'!#REF!+'SEMANA DEL 14 AL 21 '!V25+'SEMANA DEL 21AL 28-3'!V26+#REF! -> #REF! | W20: =+'SEMANA DEL 2 AL 7-3-26'!W21+'SEMANA DEL 7 AL 14'!#REF!+'SEMANA DEL 14 AL 21 '!W25+'SEMANA DEL 21AL 28-3'!W26+#REF! -> #REF! | X20: =+'SEMANA DEL 2 AL 7-3-26'!X21+'SEMANA DEL 7 AL 14'!#REF!+'SEMANA DEL 14 AL 21 '!X25+'SEMANA DEL 21AL 28-3'!X26+#REF! -> #REF! | Y20: =+'SEMANA DEL 2 AL 7-3-26'!Y21+'SEMANA DEL 7 AL 14'!#REF!+'SEMANA DEL 14 AL 21 '!Y25+'SEMANA DEL 21AL 28-3'!Y26+#REF! -> #REF! | ... AW20: =+'SEMANA DEL 2 AL 7-3-26'!AW21+'SEMANA DEL 7 AL 14'!#REF!+'SEMANA DEL 14 AL 21 '!AW25+'SEMANA DEL 21AL 28-3'!AW26+#REF! -> #REF! | AX20: =+B20+R20-AH20 -> #REF! | AY20: =+C20+S20-AI20 -> #REF! | AZ20: =+D20+T20-AJ20 -> #REF! | BA20: =+E20+U20-AK20 -> #REF! | BB20: =+F20+V20-AL20 -> #REF! | BC20: =+G20+W20-AM20 -> #REF! | BD20: =+H20+X20-AN20 -> #REF! | BE20: =+I20+Y20-AO20 -> #REF! | ... BM20: =+Q20+AG20-AW20 -> #REF! | BN20: =+'SEMANA DEL 2 AL 7-3-26'!BN21+'SEMANA DEL 7 AL 14'!#REF!+'SEMANA DEL 14 AL 21 '!BN25+'SEMANA DEL 21AL 28-3'!BN26+#REF! -> #REF! | BO20: =+'SEMANA DEL 2 AL 7-3-26'!BO21+'SEMANA DEL 7 AL 14'!#REF!+'SEMANA DEL 14 AL 21 '!BO25+'SEMANA DEL 21AL 28-3'!BO26+#REF! -> #REF! | BP20: =+'SEMANA DEL 2 AL 7-3-26'!BP21+'SEMANA DEL 7 AL 14'!#REF!+'SEMANA DEL 14 AL 21 '!BP25+'SEMANA DEL 21AL 28-3'!BP26+#REF! -> #REF! | BQ20: =+'SEMANA DEL 2 AL 7-3-26'!BQ21+'SEMANA DEL 7 AL 14'!#REF!+'SEMANA DEL 14 AL 21 '!BQ25+'SEMANA DEL 21AL 28-3'!BQ26+#REF! -> #REF! | BR20: =+'SEMANA DEL 2 AL 7-3-26'!BR21+'SEMANA DEL 7 AL 14'!#REF!+'SEMANA DEL 14 AL 21 '!BR25+'SEMANA DEL 21AL 28-3'!BR26+#REF! -> #REF! | BS20: =+'SEMANA DEL 2 AL 7-3-26'!BS21+'SEMANA DEL 7 AL 14'!#REF!+'SEMANA DEL 14 AL 21 '!BS25+'SEMANA DEL 21AL 28-3'!BS26+#REF! -> #REF! | BT20: =+'SEMANA DEL 2 AL 7-3-26'!BT21+'SEMANA DEL 7 AL 14'!#REF!+'SEMANA DEL 14 AL 21 '!BT25+'SEMANA DEL 21AL 28-3'!BT26+#REF! -> #REF! | BU20: =+'SEMANA DEL 2 AL 7-3-26'!BU21+'SEMANA DEL 7 AL 14'!#REF!+'SEMANA DEL 14 AL 21 '!BU25+'SEMANA DEL 21AL 28-3'!BU26+#REF! -> #REF! | ... CI20: =+'SEMANA DEL 2 AL 7-3-26'!CI21+'SEMANA DEL 7 AL 14'!#REF!+'SEMANA DEL 14 AL 21 '!CI25+'SEMANA DEL 21AL 28-3'!CI26+#REF! -> #REF!
A21: =+'SEMANA DEL 2 AL 7-3-26'!A21 -> LUIS VALDERRAMA | B21: =+'SEMANA DEL 2 AL 7-3-26'!B21 -> 0 | C21: =+'SEMANA DEL 2 AL 7-3-26'!C21 -> 0 | D21: =+'SEMANA DEL 2 AL 7-3-26'!D21 -> 0 | E21: =+'SEMANA DEL 2 AL 7-3-26'!E21 -> 0 | F21: =+'SEMANA DEL 2 AL 7-3-26'!F21 -> 0 | G21: =+'SEMANA DEL 2 AL 7-3-26'!G21 -> 0 | H21: =+'SEMANA DEL 2 AL 7-3-26'!H21 -> 0 | ... Q21: =+'SEMANA DEL 2 AL 7-3-26'!Q21 -> 0 | R21: =+'SEMANA DEL 2 AL 7-3-26'!R22+'SEMANA DEL 7 AL 14'!R27+'SEMANA DEL 14 AL 21 '!#REF!+'SEMANA DEL 21AL 28-3'!#REF!+#REF! -> #REF! | S21: =+'SEMANA DEL 2 AL 7-3-26'!S22+'SEMANA DEL 7 AL 14'!S27+'SEMANA DEL 14 AL 21 '!#REF!+'SEMANA DEL 21AL 28-3'!#REF!+#REF! -> #REF! | T21: =+'SEMANA DEL 2 AL 7-3-26'!T22+'SEMANA DEL 7 AL 14'!T27+'SEMANA DEL 14 AL 21 '!#REF!+'SEMANA DEL 21AL 28-3'!#REF!+#REF! -> #REF! | U21: =+'SEMANA DEL 2 AL 7-3-26'!U22+'SEMANA DEL 7 AL 14'!U27+'SEMANA DEL 14 AL 21 '!#REF!+'SEMANA DEL 21AL 28-3'!#REF!+#REF! -> #REF! | V21: =+'SEMANA DEL 2 AL 7-3-26'!V22+'SEMANA DEL 7 AL 14'!V27+'SEMANA DEL 14 AL 21 '!#REF!+'SEMANA DEL 21AL 28-3'!#REF!+#REF! -> #REF! | W21: =+'SEMANA DEL 2 AL 7-3-26'!W22+'SEMANA DEL 7 AL 14'!W27+'SEMANA DEL 14 AL 21 '!#REF!+'SEMANA DEL 21AL 28-3'!#REF!+#REF! -> #REF! | X21: =+'SEMANA DEL 2 AL 7-3-26'!X22+'SEMANA DEL 7 AL 14'!X27+'SEMANA DEL 14 AL 21 '!#REF!+'SEMANA DEL 21AL 28-3'!#REF!+#REF! -> #REF! | Y21: =+'SEMANA DEL 2 AL 7-3-26'!Y22+'SEMANA DEL 7 AL 14'!Y27+'SEMANA DEL 14 AL 21 '!#REF!+'SEMANA DEL 21AL 28-3'!#REF!+#REF! -> #REF! | ... AW21: =+'SEMANA DEL 2 AL 7-3-26'!AW22+'SEMANA DEL 7 AL 14'!AW27+'SEMANA DEL 14 AL 21 '!#REF!+'SEMANA DEL 21AL 28-3'!#REF!+#REF! -> #REF! | AX21: =+B21+R21-AH21 -> #REF! | AY21: =+C21+S21-AI21 -> #REF! | AZ21: =+D21+T21-AJ21 -> #REF! | BA21: =+E21+U21-AK21 -> #REF! | BB21: =+F21+V21-AL21 -> #REF! | BC21: =+G21+W21-AM21 -> #REF! | BD21: =+H21+X21-AN21 -> #REF! | BE21: =+I21+Y21-AO21 -> #REF! | ... BM21: =+Q21+AG21-AW21 -> #REF! | BN21: =+'SEMANA DEL 2 AL 7-3-26'!BN22+'SEMANA DEL 7 AL 14'!BN27+'SEMANA DEL 14 AL 21 '!#REF!+'SEMANA DEL 21AL 28-3'!#REF!+#REF! -> #REF! | BO21: =+'SEMANA DEL 2 AL 7-3-26'!BO22+'SEMANA DEL 7 AL 14'!BO27+'SEMANA DEL 14 AL 21 '!#REF!+'SEMANA DEL 21AL 28-3'!#REF!+#REF! -> #REF! | BP21: =+'SEMANA DEL 2 AL 7-3-26'!BP22+'SEMANA DEL 7 AL 14'!BP27+'SEMANA DEL 14 AL 21 '!#REF!+'SEMANA DEL 21AL 28-3'!#REF!+#REF! -> #REF! | BQ21: =+'SEMANA DEL 2 AL 7-3-26'!BQ22+'SEMANA DEL 7 AL 14'!BQ27+'SEMANA DEL 14 AL 21 '!#REF!+'SEMANA DEL 21AL 28-3'!#REF!+#REF! -> #REF! | BR21: =+'SEMANA DEL 2 AL 7-3-26'!BR22+'SEMANA DEL 7 AL 14'!BR27+'SEMANA DEL 14 AL 21 '!#REF!+'SEMANA DEL 21AL 28-3'!#REF!+#REF! -> #REF! | BS21: =+'SEMANA DEL 2 AL 7-3-26'!BS22+'SEMANA DEL 7 AL 14'!BS27+'SEMANA DEL 14 AL 21 '!#REF!+'SEMANA DEL 21AL 28-3'!#REF!+#REF! -> #REF! | BT21: =+'SEMANA DEL 2 AL 7-3-26'!BT22+'SEMANA DEL 7 AL 14'!BT27+'SEMANA DEL 14 AL 21 '!#REF!+'SEMANA DEL 21AL 28-3'!#REF!+#REF! -> #REF! | BU21: =+'SEMANA DEL 2 AL 7-3-26'!BU22+'SEMANA DEL 7 AL 14'!BU27+'SEMANA DEL 14 AL 21 '!#REF!+'SEMANA DEL 21AL 28-3'!#REF!+#REF! -> #REF! | ... CI21: =+'SEMANA DEL 2 AL 7-3-26'!CI22+'SEMANA DEL 7 AL 14'!CI27+'SEMANA DEL 14 AL 21 '!#REF!+'SEMANA DEL 21AL 28-3'!#REF!+#REF! -> #REF!
A22: =+'SEMANA DEL 2 AL 7-3-26'!A22 -> LILIANA VEGA | B22: =+'SEMANA DEL 2 AL 7-3-26'!B22 -> 0 | C22: =+'SEMANA DEL 2 AL 7-3-26'!C22 -> 0 | D22: =+'SEMANA DEL 2 AL 7-3-26'!D22 -> 0 | E22: =+'SEMANA DEL 2 AL 7-3-26'!E22 -> 1 | F22: =+'SEMANA DEL 2 AL 7-3-26'!F22 -> 0 | G22: =+'SEMANA DEL 2 AL 7-3-26'!G22 -> 0 | H22: =+'SEMANA DEL 2 AL 7-3-26'!H22 -> 0 | ... Q22: =+'SEMANA DEL 2 AL 7-3-26'!Q22 -> 0 | R22: =+'SEMANA DEL 2 AL 7-3-26'!R26+'SEMANA DEL 7 AL 14'!R30+'SEMANA DEL 14 AL 21 '!R28+'SEMANA DEL 21AL 28-3'!R29+#REF! -> #REF! | S22: =+'SEMANA DEL 2 AL 7-3-26'!S26+'SEMANA DEL 7 AL 14'!S30+'SEMANA DEL 14 AL 21 '!S28+'SEMANA DEL 21AL 28-3'!S29+#REF! -> #REF! | T22: =+'SEMANA DEL 2 AL 7-3-26'!T26+'SEMANA DEL 7 AL 14'!T30+'SEMANA DEL 14 AL 21 '!T28+'SEMANA DEL 21AL 28-3'!T29+#REF! -> #REF! | U22: =+'SEMANA DEL 2 AL 7-3-26'!U26+'SEMANA DEL 7 AL 14'!U30+'SEMANA DEL 14 AL 21 '!U28+'SEMANA DEL 21AL 28-3'!U29+#REF! -> #REF! | V22: =+'SEMANA DEL 2 AL 7-3-26'!V26+'SEMANA DEL 7 AL 14'!V30+'SEMANA DEL 14 AL 21 '!V28+'SEMANA DEL 21AL 28-3'!V29+#REF! -> #REF! | W22: =+'SEMANA DEL 2 AL 7-3-26'!W26+'SEMANA DEL 7 AL 14'!W30+'SEMANA DEL 14 AL 21 '!W28+'SEMANA DEL 21AL 28-3'!W29+#REF! -> #REF! | X22: =+'SEMANA DEL 2 AL 7-3-26'!X26+'SEMANA DEL 7 AL 14'!X30+'SEMANA DEL 14 AL 21 '!X28+'SEMANA DEL 21AL 28-3'!X29+#REF! -> #REF! | Y22: =+'SEMANA DEL 2 AL 7-3-26'!Y26+'SEMANA DEL 7 AL 14'!Y30+'SEMANA DEL 14 AL 21 '!Y28+'SEMANA DEL 21AL 28-3'!Y29+#REF! -> #REF! | ... AW22: =+'SEMANA DEL 2 AL 7-3-26'!AW26+'SEMANA DEL 7 AL 14'!AW30+'SEMANA DEL 14 AL 21 '!AW28+'SEMANA DEL 21AL 28-3'!AW29+#REF! -> #REF! | AX22: =+B22+R22-AH22 -> #REF! | AY22: =+C22+S22-AI22 -> #REF! | AZ22: =+D22+T22-AJ22 -> #REF! | BA22: =+E22+U22-AK22 -> #REF! | BB22: =+F22+V22-AL22 -> #REF! | BC22: =+G22+W22-AM22 -> #REF! | BD22: =+H22+X22-AN22 -> #REF! | BE22: =+I22+Y22-AO22 -> #REF! | ... BM22: =+Q22+AG22-AW22 -> #REF! | BN22: =+'SEMANA DEL 2 AL 7-3-26'!BN26+'SEMANA DEL 7 AL 14'!BN30+'SEMANA DEL 14 AL 21 '!BN28+'SEMANA DEL 21AL 28-3'!BN29+#REF! -> #REF! | BO22: =+'SEMANA DEL 2 AL 7-3-26'!BO26+'SEMANA DEL 7 AL 14'!BO30+'SEMANA DEL 14 AL 21 '!BO28+'SEMANA DEL 21AL 28-3'!BO29+#REF! -> #REF! | BP22: =+'SEMANA DEL 2 AL 7-3-26'!BP26+'SEMANA DEL 7 AL 14'!BP30+'SEMANA DEL 14 AL 21 '!BP28+'SEMANA DEL 21AL 28-3'!BP29+#REF! -> #REF! | BQ22: =+'SEMANA DEL 2 AL 7-3-26'!BQ26+'SEMANA DEL 7 AL 14'!BQ30+'SEMANA DEL 14 AL 21 '!BQ28+'SEMANA DEL 21AL 28-3'!BQ29+#REF! -> #REF! | BR22: =+'SEMANA DEL 2 AL 7-3-26'!BR26+'SEMANA DEL 7 AL 14'!BR30+'SEMANA DEL 14 AL 21 '!BR28+'SEMANA DEL 21AL 28-3'!BR29+#REF! -> #REF! | BS22: =+'SEMANA DEL 2 AL 7-3-26'!BS26+'SEMANA DEL 7 AL 14'!BS30+'SEMANA DEL 14 AL 21 '!BS28+'SEMANA DEL 21AL 28-3'!BS29+#REF! -> #REF! | BT22: =+'SEMANA DEL 2 AL 7-3-26'!BT26+'SEMANA DEL 7 AL 14'!BT30+'SEMANA DEL 14 AL 21 '!BT28+'SEMANA DEL 21AL 28-3'!BT29+#REF! -> #REF! | BU22: =+'SEMANA DEL 2 AL 7-3-26'!BU26+'SEMANA DEL 7 AL 14'!BU30+'SEMANA DEL 14 AL 21 '!BU28+'SEMANA DEL 21AL 28-3'!BU29+#REF! -> #REF! | ... CI22: =+'SEMANA DEL 2 AL 7-3-26'!CI26+'SEMANA DEL 7 AL 14'!CI30+'SEMANA DEL 14 AL 21 '!CI28+'SEMANA DEL 21AL 28-3'!CI29+#REF! -> #REF!
A23: =+'SEMANA DEL 2 AL 7-3-26'!A23 -> LUIS ERNESTO ALMEIDA | B23: =+'SEMANA DEL 2 AL 7-3-26'!B23 -> 0 | C23: =+'SEMANA DEL 2 AL 7-3-26'!C23 -> 0 | D23: =+'SEMANA DEL 2 AL 7-3-26'!D23 -> 0 | E23: =+'SEMANA DEL 2 AL 7-3-26'!E23 -> 0 | F23: =+'SEMANA DEL 2 AL 7-3-26'!F23 -> 0 | G23: =+'SEMANA DEL 2 AL 7-3-26'!G23 -> 0 | H23: =+'SEMANA DEL 2 AL 7-3-26'!H23 -> 0 | ... Q23: =+'SEMANA DEL 2 AL 7-3-26'!Q23 -> 0 | R23: =+'SEMANA DEL 2 AL 7-3-26'!#REF!+'SEMANA DEL 7 AL 14'!R33+'SEMANA DEL 14 AL 21 '!R31+'SEMANA DEL 21AL 28-3'!R32+#REF! -> #REF! | S23: =+'SEMANA DEL 2 AL 7-3-26'!#REF!+'SEMANA DEL 7 AL 14'!S33+'SEMANA DEL 14 AL 21 '!S31+'SEMANA DEL 21AL 28-3'!S32+#REF! -> #REF! | T23: =+'SEMANA DEL 2 AL 7-3-26'!#REF!+'SEMANA DEL 7 AL 14'!T33+'SEMANA DEL 14 AL 21 '!T31+'SEMANA DEL 21AL 28-3'!T32+#REF! -> #REF! | U23: =+'SEMANA DEL 2 AL 7-3-26'!#REF!+'SEMANA DEL 7 AL 14'!U33+'SEMANA DEL 14 AL 21 '!U31+'SEMANA DEL 21AL 28-3'!U32+#REF! -> #REF! | V23: =+'SEMANA DEL 2 AL 7-3-26'!#REF!+'SEMANA DEL 7 AL 14'!V33+'SEMANA DEL 14 AL 21 '!V31+'SEMANA DEL 21AL 28-3'!V32+#REF! -> #REF! | W23: =+'SEMANA DEL 2 AL 7-3-26'!#REF!+'SEMANA DEL 7 AL 14'!W33+'SEMANA DEL 14 AL 21 '!W31+'SEMANA DEL 21AL 28-3'!W32+#REF! -> #REF! | X23: =+'SEMANA DEL 2 AL 7-3-26'!#REF!+'SEMANA DEL 7 AL 14'!X33+'SEMANA DEL 14 AL 21 '!X31+'SEMANA DEL 21AL 28-3'!X32+#REF! -> #REF! | Y23: =+'SEMANA DEL 2 AL 7-3-26'!#REF!+'SEMANA DEL 7 AL 14'!Y33+'SEMANA DEL 14 AL 21 '!Y31+'SEMANA DEL 21AL 28-3'!Y32+#REF! -> #REF! | ... AW23: =+'SEMANA DEL 2 AL 7-3-26'!#REF!+'SEMANA DEL 7 AL 14'!AW33+'SEMANA DEL 14 AL 21 '!AW31+'SEMANA DEL 21AL 28-3'!AW32+#REF! -> #REF! | AX23: =+B23+R23-AH23 -> #REF! | AY23: =+C23+S23-AI23 -> #REF! | AZ23: =+D23+T23-AJ23 -> #REF! | BA23: =+E23+U23-AK23 -> #REF! | BB23: =+F23+V23-AL23 -> #REF! | BC23: =+G23+W23-AM23 -> #REF! | BD23: =+H23+X23-AN23 -> #REF! | BE23: =+I23+Y23-AO23 -> #REF! | ... BM23: =+Q23+AG23-AW23 -> #REF! | BN23: =+'SEMANA DEL 2 AL 7-3-26'!#REF!+'SEMANA DEL 7 AL 14'!BN33+'SEMANA DEL 14 AL 21 '!BN31+'SEMANA DEL 21AL 28-3'!BN32+#REF! -> #REF! | BO23: =+'SEMANA DEL 2 AL 7-3-26'!#REF!+'SEMANA DEL 7 AL 14'!BO33+'SEMANA DEL 14 AL 21 '!BO31+'SEMANA DEL 21AL 28-3'!BO32+#REF! -> #REF! | BP23: =+'SEMANA DEL 2 AL 7-3-26'!#REF!+'SEMANA DEL 7 AL 14'!BP33+'SEMANA DEL 14 AL 21 '!BP31+'SEMANA DEL 21AL 28-3'!BP32+#REF! -> #REF! | BQ23: =+'SEMANA DEL 2 AL 7-3-26'!#REF!+'SEMANA DEL 7 AL 14'!BQ33+'SEMANA DEL 14 AL 21 '!BQ31+'SEMANA DEL 21AL 28-3'!BQ32+#REF! -> #REF! | BR23: =+'SEMANA DEL 2 AL 7-3-26'!#REF!+'SEMANA DEL 7 AL 14'!BR33+'SEMANA DEL 14 AL 21 '!BR31+'SEMANA DEL 21AL 28-3'!BR32+#REF! -> #REF! | BS23: =+'SEMANA DEL 2 AL 7-3-26'!#REF!+'SEMANA DEL 7 AL 14'!BS33+'SEMANA DEL 14 AL 21 '!BS31+'SEMANA DEL 21AL 28-3'!BS32+#REF! -> #REF! | BT23: =+'SEMANA DEL 2 AL 7-3-26'!#REF!+'SEMANA DEL 7 AL 14'!BT33+'SEMANA DEL 14 AL 21 '!BT31+'SEMANA DEL 21AL 28-3'!BT32+#REF! -> #REF! | BU23: =+'SEMANA DEL 2 AL 7-3-26'!#REF!+'SEMANA DEL 7 AL 14'!BU33+'SEMANA DEL 14 AL 21 '!BU31+'SEMANA DEL 21AL 28-3'!BU32+#REF! -> #REF! | ... CI23: =+'SEMANA DEL 2 AL 7-3-26'!#REF!+'SEMANA DEL 7 AL 14'!CI33+'SEMANA DEL 14 AL 21 '!CI31+'SEMANA DEL 21AL 28-3'!CI32+#REF! -> #REF!
A24: =+'SEMANA DEL 2 AL 7-3-26'!A25 -> MAYERLIN BOLIVAR | B24: =+'SEMANA DEL 2 AL 7-3-26'!B25 -> 0.3 | C24: =+'SEMANA DEL 2 AL 7-3-26'!C25 -> 1.34 | D24: =+'SEMANA DEL 2 AL 7-3-26'!D25 -> 2.1 | E24: =+'SEMANA DEL 2 AL 7-3-26'!E25 -> 0 | F24: =+'SEMANA DEL 2 AL 7-3-26'!F25 -> 0 | G24: =+'SEMANA DEL 2 AL 7-3-26'!G25 -> 0 | H24: =+'SEMANA DEL 2 AL 7-3-26'!H25 -> 0 | ... Q24: =+'SEMANA DEL 2 AL 7-3-26'!Q25 -> 0 | R24: =+'SEMANA DEL 2 AL 7-3-26'!#REF!+'SEMANA DEL 7 AL 14'!R35+'SEMANA DEL 14 AL 21 '!R35+'SEMANA DEL 21AL 28-3'!R34+#REF! -> #REF! | S24: =+'SEMANA DEL 2 AL 7-3-26'!#REF!+'SEMANA DEL 7 AL 14'!S35+'SEMANA DEL 14 AL 21 '!S35+'SEMANA DEL 21AL 28-3'!S34+#REF! -> #REF! | T24: =+'SEMANA DEL 2 AL 7-3-26'!#REF!+'SEMANA DEL 7 AL 14'!T35+'SEMANA DEL 14 AL 21 '!T35+'SEMANA DEL 21AL 28-3'!T34+#REF! -> #REF! | U24: =+'SEMANA DEL 2 AL 7-3-26'!#REF!+'SEMANA DEL 7 AL 14'!U35+'SEMANA DEL 14 AL 21 '!U35+'SEMANA DEL 21AL 28-3'!U34+#REF! -> #REF! | V24: =+'SEMANA DEL 2 AL 7-3-26'!#REF!+'SEMANA DEL 7 AL 14'!V35+'SEMANA DEL 14 AL 21 '!V35+'SEMANA DEL 21AL 28-3'!V34+#REF! -> #REF! | W24: =+'SEMANA DEL 2 AL 7-3-26'!#REF!+'SEMANA DEL 7 AL 14'!W35+'SEMANA DEL 14 AL 21 '!W35+'SEMANA DEL 21AL 28-3'!W34+#REF! -> #REF! | X24: =+'SEMANA DEL 2 AL 7-3-26'!#REF!+'SEMANA DEL 7 AL 14'!X35+'SEMANA DEL 14 AL 21 '!X35+'SEMANA DEL 21AL 28-3'!X34+#REF! -> #REF! | Y24: =+'SEMANA DEL 2 AL 7-3-26'!#REF!+'SEMANA DEL 7 AL 14'!Y35+'SEMANA DEL 14 AL 21 '!Y35+'SEMANA DEL 21AL 28-3'!Y34+#REF! -> #REF! | ... AW24: =+'SEMANA DEL 2 AL 7-3-26'!#REF!+'SEMANA DEL 7 AL 14'!AW35+'SEMANA DEL 14 AL 21 '!AW35+'SEMANA DEL 21AL 28-3'!AW34+#REF! -> #REF! | AX24: =+B24+R24-AH24 -> #REF! | AY24: =+C24+S24-AI24 -> #REF! | AZ24: =+D24+T24-AJ24 -> #REF! | BA24: =+E24+U24-AK24 -> #REF! | BB24: =+F24+V24-AL24 -> #REF! | BC24: =+G24+W24-AM24 -> #REF! | BD24: =+H24+X24-AN24 -> #REF! | BE24: =+I24+Y24-AO24 -> #REF! | ... BM24: =+Q24+AG24-AW24 -> #REF! | BN24: =+'SEMANA DEL 2 AL 7-3-26'!#REF!+'SEMANA DEL 7 AL 14'!BN35+'SEMANA DEL 14 AL 21 '!BN35+'SEMANA DEL 21AL 28-3'!BN34+#REF! -> #REF! | BO24: =+'SEMANA DEL 2 AL 7-3-26'!#REF!+'SEMANA DEL 7 AL 14'!BO35+'SEMANA DEL 14 AL 21 '!BO35+'SEMANA DEL 21AL 28-3'!BO34+#REF! -> #REF! | BP24: =+'SEMANA DEL 2 AL 7-3-26'!#REF!+'SEMANA DEL 7 AL 14'!BP35+'SEMANA DEL 14 AL 21 '!BP35+'SEMANA DEL 21AL 28-3'!BP34+#REF! -> #REF! | BQ24: =+'SEMANA DEL 2 AL 7-3-26'!#REF!+'SEMANA DEL 7 AL 14'!BQ35+'SEMANA DEL 14 AL 21 '!BQ35+'SEMANA DEL 21AL 28-3'!BQ34+#REF! -> #REF! | BR24: =+'SEMANA DEL 2 AL 7-3-26'!#REF!+'SEMANA DEL 7 AL 14'!BR35+'SEMANA DEL 14 AL 21 '!BR35+'SEMANA DEL 21AL 28-3'!BR34+#REF! -> #REF! | BS24: =+'SEMANA DEL 2 AL 7-3-26'!#REF!+'SEMANA DEL 7 AL 14'!BS35+'SEMANA DEL 14 AL 21 '!BS35+'SEMANA DEL 21AL 28-3'!BS34+#REF! -> #REF! | BT24: =+'SEMANA DEL 2 AL 7-3-26'!#REF!+'SEMANA DEL 7 AL 14'!BT35+'SEMANA DEL 14 AL 21 '!BT35+'SEMANA DEL 21AL 28-3'!BT34+#REF! -> #REF! | BU24: =+'SEMANA DEL 2 AL 7-3-26'!#REF!+'SEMANA DEL 7 AL 14'!BU35+'SEMANA DEL 14 AL 21 '!BU35+'SEMANA DEL 21AL 28-3'!BU34+#REF! -> #REF! | ... CI24: =+'SEMANA DEL 2 AL 7-3-26'!#REF!+'SEMANA DEL 7 AL 14'!CI35+'SEMANA DEL 14 AL 21 '!CI35+'SEMANA DEL 21AL 28-3'!CI34+#REF! -> #REF!
A25: =+'SEMANA DEL 2 AL 7-3-26'!A26 -> MARTHA SILVA | B25: =+'SEMANA DEL 2 AL 7-3-26'!B26 -> 0.1 | C25: =+'SEMANA DEL 2 AL 7-3-26'!C26 -> 0.18 | D25: =+'SEMANA DEL 2 AL 7-3-26'!D26 -> 12 | E25: =+'SEMANA DEL 2 AL 7-3-26'!E26 -> 0 | F25: =+'SEMANA DEL 2 AL 7-3-26'!F26 -> 0 | G25: =+'SEMANA DEL 2 AL 7-3-26'!G26 -> 0 | H25: =+'SEMANA DEL 2 AL 7-3-26'!H26 -> 0 | ... Q25: =+'SEMANA DEL 2 AL 7-3-26'!Q26 -> 0 | R25: =+'SEMANA DEL 2 AL 7-3-26'!R32+'SEMANA DEL 7 AL 14'!R36+'SEMANA DEL 14 AL 21 '!R36+'SEMANA DEL 21AL 28-3'!R35+#REF! -> #REF! | S25: =+'SEMANA DEL 2 AL 7-3-26'!S32+'SEMANA DEL 7 AL 14'!S36+'SEMANA DEL 14 AL 21 '!S36+'SEMANA DEL 21AL 28-3'!S35+#REF! -> #REF! | T25: =+'SEMANA DEL 2 AL 7-3-26'!T32+'SEMANA DEL 7 AL 14'!T36+'SEMANA DEL 14 AL 21 '!T36+'SEMANA DEL 21AL 28-3'!T35+#REF! -> #REF! | U25: =+'SEMANA DEL 2 AL 7-3-26'!U32+'SEMANA DEL 7 AL 14'!U36+'SEMANA DEL 14 AL 21 '!U36+'SEMANA DEL 21AL 28-3'!U35+#REF! -> #REF! | V25: =+'SEMANA DEL 2 AL 7-3-26'!V32+'SEMANA DEL 7 AL 14'!V36+'SEMANA DEL 14 AL 21 '!V36+'SEMANA DEL 21AL 28-3'!V35+#REF! -> #REF! | W25: =+'SEMANA DEL 2 AL 7-3-26'!W32+'SEMANA DEL 7 AL 14'!W36+'SEMANA DEL 14 AL 21 '!W36+'SEMANA DEL 21AL 28-3'!W35+#REF! -> #REF! | X25: =+'SEMANA DEL 2 AL 7-3-26'!X32+'SEMANA DEL 7 AL 14'!X36+'SEMANA DEL 14 AL 21 '!X36+'SEMANA DEL 21AL 28-3'!X35+#REF! -> #REF! | Y25: =+'SEMANA DEL 2 AL 7-3-26'!Y32+'SEMANA DEL 7 AL 14'!Y36+'SEMANA DEL 14 AL 21 '!Y36+'SEMANA DEL 21AL 28-3'!Y35+#REF! -> #REF! | ... AW25: =+'SEMANA DEL 2 AL 7-3-26'!AW32+'SEMANA DEL 7 AL 14'!AW36+'SEMANA DEL 14 AL 21 '!AW36+'SEMANA DEL 21AL 28-3'!AW35+#REF! -> #REF! | AX25: =+B25+R25-AH25 -> #REF! | AY25: =+C25+S25-AI25 -> #REF! | AZ25: =+D25+T25-AJ25 -> #REF! | BA25: =+E25+U25-AK25 -> #REF! | BB25: =+F25+V25-AL25 -> #REF! | BC25: =+G25+W25-AM25 -> #REF! | BD25: =+H25+X25-AN25 -> #REF! | BE25: =+I25+Y25-AO25 -> #REF! | ... BM25: =+Q25+AG25-AW25 -> #REF! | BN25: =+'SEMANA DEL 2 AL 7-3-26'!BN32+'SEMANA DEL 7 AL 14'!BN36+'SEMANA DEL 14 AL 21 '!BN36+'SEMANA DEL 21AL 28-3'!BN35+#REF! -> #REF! | BO25: =+'SEMANA DEL 2 AL 7-3-26'!BO32+'SEMANA DEL 7 AL 14'!BO36+'SEMANA DEL 14 AL 21 '!BO36+'SEMANA DEL 21AL 28-3'!BO35+#REF! -> #REF! | BP25: =+'SEMANA DEL 2 AL 7-3-26'!BP32+'SEMANA DEL 7 AL 14'!BP36+'SEMANA DEL 14 AL 21 '!BP36+'SEMANA DEL 21AL 28-3'!BP35+#REF! -> #REF! | BQ25: =+'SEMANA DEL 2 AL 7-3-26'!BQ32+'SEMANA DEL 7 AL 14'!BQ36+'SEMANA DEL 14 AL 21 '!BQ36+'SEMANA DEL 21AL 28-3'!BQ35+#REF! -> #REF! | BR25: =+'SEMANA DEL 2 AL 7-3-26'!BR32+'SEMANA DEL 7 AL 14'!BR36+'SEMANA DEL 14 AL 21 '!BR36+'SEMANA DEL 21AL 28-3'!BR35+#REF! -> #REF! | BS25: =+'SEMANA DEL 2 AL 7-3-26'!BS32+'SEMANA DEL 7 AL 14'!BS36+'SEMANA DEL 14 AL 21 '!BS36+'SEMANA DEL 21AL 28-3'!BS35+#REF! -> #REF! | BT25: =+'SEMANA DEL 2 AL 7-3-26'!BT32+'SEMANA DEL 7 AL 14'!BT36+'SEMANA DEL 14 AL 21 '!BT36+'SEMANA DEL 21AL 28-3'!BT35+#REF! -> #REF! | BU25: =+'SEMANA DEL 2 AL 7-3-26'!BU32+'SEMANA DEL 7 AL 14'!BU36+'SEMANA DEL 14 AL 21 '!BU36+'SEMANA DEL 21AL 28-3'!BU35+#REF! -> #REF! | ... CI25: =+'SEMANA DEL 2 AL 7-3-26'!CI32+'SEMANA DEL 7 AL 14'!CI36+'SEMANA DEL 14 AL 21 '!CI36+'SEMANA DEL 21AL 28-3'!CI35+#REF! -> #REF!
A26: =+'SEMANA DEL 2 AL 7-3-26'!#REF! -> #REF! | B26: =+'SEMANA DEL 2 AL 7-3-26'!#REF! -> #REF! | C26: =+'SEMANA DEL 2 AL 7-3-26'!#REF! -> #REF! | D26: =+'SEMANA DEL 2 AL 7-3-26'!#REF! -> #REF! | E26: =+'SEMANA DEL 2 AL 7-3-26'!#REF! -> #REF! | F26: =+'SEMANA DEL 2 AL 7-3-26'!#REF! -> #REF! | G26: =+'SEMANA DEL 2 AL 7-3-26'!#REF! -> #REF! | H26: =+'SEMANA DEL 2 AL 7-3-26'!#REF! -> #REF! | ... Q26: =+'SEMANA DEL 2 AL 7-3-26'!#REF! -> #REF! | R26: =+'SEMANA DEL 2 AL 7-3-26'!R34+'SEMANA DEL 7 AL 14'!R38+'SEMANA DEL 14 AL 21 '!R38+'SEMANA DEL 21AL 28-3'!R39+#REF! -> #REF! | S26: =+'SEMANA DEL 2 AL 7-3-26'!S34+'SEMANA DEL 7 AL 14'!S38+'SEMANA DEL 14 AL 21 '!S38+'SEMANA DEL 21AL 28-3'!S39+#REF! -> #REF! | T26: =+'SEMANA DEL 2 AL 7-3-26'!T34+'SEMANA DEL 7 AL 14'!T38+'SEMANA DEL 14 AL 21 '!T38+'SEMANA DEL 21AL 28-3'!T39+#REF! -> #REF! | U26: =+'SEMANA DEL 2 AL 7-3-26'!U34+'SEMANA DEL 7 AL 14'!U38+'SEMANA DEL 14 AL 21 '!U38+'SEMANA DEL 21AL 28-3'!U39+#REF! -> #REF! | V26: =+'SEMANA DEL 2 AL 7-3-26'!V34+'SEMANA DEL 7 AL 14'!V38+'SEMANA DEL 14 AL 21 '!V38+'SEMANA DEL 21AL 28-3'!V39+#REF! -> #REF! | W26: =+'SEMANA DEL 2 AL 7-3-26'!W34+'SEMANA DEL 7 AL 14'!W38+'SEMANA DEL 14 AL 21 '!W38+'SEMANA DEL 21AL 28-3'!W39+#REF! -> #REF! | X26: =+'SEMANA DEL 2 AL 7-3-26'!X34+'SEMANA DEL 7 AL 14'!X38+'SEMANA DEL 14 AL 21 '!X38+'SEMANA DEL 21AL 28-3'!X39+#REF! -> #REF! | Y26: =+'SEMANA DEL 2 AL 7-3-26'!Y34+'SEMANA DEL 7 AL 14'!Y38+'SEMANA DEL 14 AL 21 '!Y38+'SEMANA DEL 21AL 28-3'!Y39+#REF! -> #REF! | ... AW26: =+'SEMANA DEL 2 AL 7-3-26'!AW34+'SEMANA DEL 7 AL 14'!AW38+'SEMANA DEL 14 AL 21 '!AW38+'SEMANA DEL 21AL 28-3'!AW39+#REF! -> #REF! | AX26: =+B26+R26-AH26 -> #REF! | AY26: =+C26+S26-AI26 -> #REF! | AZ26: =+D26+T26-AJ26 -> #REF! | BA26: =+E26+U26-AK26 -> #REF! | BB26: =+F26+V26-AL26 -> #REF! | BC26: =+G26+W26-AM26 -> #REF! | BD26: =+H26+X26-AN26 -> #REF! | BE26: =+I26+Y26-AO26 -> #REF! | ... BM26: =+Q26+AG26-AW26 -> #REF! | BN26: =+'SEMANA DEL 2 AL 7-3-26'!BN34+'SEMANA DEL 7 AL 14'!BN38+'SEMANA DEL 14 AL 21 '!BN38+'SEMANA DEL 21AL 28-3'!BN39+#REF! -> #REF! | BO26: =+'SEMANA DEL 2 AL 7-3-26'!BO34+'SEMANA DEL 7 AL 14'!BO38+'SEMANA DEL 14 AL 21 '!BO38+'SEMANA DEL 21AL 28-3'!BO39+#REF! -> #REF! | BP26: =+'SEMANA DEL 2 AL 7-3-26'!BP34+'SEMANA DEL 7 AL 14'!BP38+'SEMANA DEL 14 AL 21 '!BP38+'SEMANA DEL 21AL 28-3'!BP39+#REF! -> #REF! | BQ26: =+'SEMANA DEL 2 AL 7-3-26'!BQ34+'SEMANA DEL 7 AL 14'!BQ38+'SEMANA DEL 14 AL 21 '!BQ38+'SEMANA DEL 21AL 28-3'!BQ39+#REF! -> #REF! | BR26: =+'SEMANA DEL 2 AL 7-3-26'!BR34+'SEMANA DEL 7 AL 14'!BR38+'SEMANA DEL 14 AL 21 '!BR38+'SEMANA DEL 21AL 28-3'!BR39+#REF! -> #REF! | BS26: =+'SEMANA DEL 2 AL 7-3-26'!BS34+'SEMANA DEL 7 AL 14'!BS38+'SEMANA DEL 14 AL 21 '!BS38+'SEMANA DEL 21AL 28-3'!BS39+#REF! -> #REF! | BT26: =+'SEMANA DEL 2 AL 7-3-26'!BT34+'SEMANA DEL 7 AL 14'!BT38+'SEMANA DEL 14 AL 21 '!BT38+'SEMANA DEL 21AL 28-3'!BT39+#REF! -> #REF! | BU26: =+'SEMANA DEL 2 AL 7-3-26'!BU34+'SEMANA DEL 7 AL 14'!BU38+'SEMANA DEL 14 AL 21 '!BU38+'SEMANA DEL 21AL 28-3'!BU39+#REF! -> #REF! | ... CI26: =+'SEMANA DEL 2 AL 7-3-26'!CI34+'SEMANA DEL 7 AL 14'!CI38+'SEMANA DEL 14 AL 21 '!CI38+'SEMANA DEL 21AL 28-3'!CI39+#REF! -> #REF!
A27: =+'SEMANA DEL 2 AL 7-3-26'!#REF! -> #REF! | B27: =+'SEMANA DEL 2 AL 7-3-26'!#REF! -> #REF! | C27: =+'SEMANA DEL 2 AL 7-3-26'!#REF! -> #REF! | D27: =+'SEMANA DEL 2 AL 7-3-26'!#REF! -> #REF! | E27: =+'SEMANA DEL 2 AL 7-3-26'!#REF! -> #REF! | F27: =+'SEMANA DEL 2 AL 7-3-26'!#REF! -> #REF! | G27: =+'SEMANA DEL 2 AL 7-3-26'!#REF! -> #REF! | H27: =+'SEMANA DEL 2 AL 7-3-26'!#REF! -> #REF! | ... Q27: =+'SEMANA DEL 2 AL 7-3-26'!#REF! -> #REF! | R27: =+'SEMANA DEL 2 AL 7-3-26'!R35+'SEMANA DEL 7 AL 14'!R39+'SEMANA DEL 14 AL 21 '!R39+'SEMANA DEL 21AL 28-3'!R40+#REF! -> #REF! | S27: =+'SEMANA DEL 2 AL 7-3-26'!S35+'SEMANA DEL 7 AL 14'!S39+'SEMANA DEL 14 AL 21 '!S39+'SEMANA DEL 21AL 28-3'!S40+#REF! -> #REF! | T27: =+'SEMANA DEL 2 AL 7-3-26'!T35+'SEMANA DEL 7 AL 14'!T39+'SEMANA DEL 14 AL 21 '!T39+'SEMANA DEL 21AL 28-3'!T40+#REF! -> #REF! | U27: =+'SEMANA DEL 2 AL 7-3-26'!U35+'SEMANA DEL 7 AL 14'!U39+'SEMANA DEL 14 AL 21 '!U39+'SEMANA DEL 21AL 28-3'!U40+#REF! -> #REF! | V27: =+'SEMANA DEL 2 AL 7-3-26'!V35+'SEMANA DEL 7 AL 14'!V39+'SEMANA DEL 14 AL 21 '!V39+'SEMANA DEL 21AL 28-3'!V40+#REF! -> #REF! | W27: =+'SEMANA DEL 2 AL 7-3-26'!W35+'SEMANA DEL 7 AL 14'!W39+'SEMANA DEL 14 AL 21 '!W39+'SEMANA DEL 21AL 28-3'!W40+#REF! -> #REF! | X27: =+'SEMANA DEL 2 AL 7-3-26'!X35+'SEMANA DEL 7 AL 14'!X39+'SEMANA DEL 14 AL 21 '!X39+'SEMANA DEL 21AL 28-3'!X40+#REF! -> #REF! | Y27: =+'SEMANA DEL 2 AL 7-3-26'!Y35+'SEMANA DEL 7 AL 14'!Y39+'SEMANA DEL 14 AL 21 '!Y39+'SEMANA DEL 21AL 28-3'!Y40+#REF! -> #REF! | ... AW27: =+'SEMANA DEL 2 AL 7-3-26'!AW35+'SEMANA DEL 7 AL 14'!AW39+'SEMANA DEL 14 AL 21 '!AW39+'SEMANA DEL 21AL 28-3'!AW40+#REF! -> #REF! | AX27: =+B27+R27-AH27 -> #REF! | AY27: =+C27+S27-AI27 -> #REF! | AZ27: =+D27+T27-AJ27 -> #REF! | BA27: =+E27+U27-AK27 -> #REF! | BB27: =+F27+V27-AL27 -> #REF! | BC27: =+G27+W27-AM27 -> #REF! | BD27: =+H27+X27-AN27 -> #REF! | BE27: =+I27+Y27-AO27 -> #REF! | ... BM27: =+Q27+AG27-AW27 -> #REF! | BN27: =+'SEMANA DEL 2 AL 7-3-26'!BN35+'SEMANA DEL 7 AL 14'!BN39+'SEMANA DEL 14 AL 21 '!BN39+'SEMANA DEL 21AL 28-3'!BN40+#REF! -> #REF! | BO27: =+'SEMANA DEL 2 AL 7-3-26'!BO35+'SEMANA DEL 7 AL 14'!BO39+'SEMANA DEL 14 AL 21 '!BO39+'SEMANA DEL 21AL 28-3'!BO40+#REF! -> #REF! | BP27: =+'SEMANA DEL 2 AL 7-3-26'!BP35+'SEMANA DEL 7 AL 14'!BP39+'SEMANA DEL 14 AL 21 '!BP39+'SEMANA DEL 21AL 28-3'!BP40+#REF! -> #REF! | BQ27: =+'SEMANA DEL 2 AL 7-3-26'!BQ35+'SEMANA DEL 7 AL 14'!BQ39+'SEMANA DEL 14 AL 21 '!BQ39+'SEMANA DEL 21AL 28-3'!BQ40+#REF! -> #REF! | BR27: =+'SEMANA DEL 2 AL 7-3-26'!BR35+'SEMANA DEL 7 AL 14'!BR39+'SEMANA DEL 14 AL 21 '!BR39+'SEMANA DEL 21AL 28-3'!BR40+#REF! -> #REF! | BS27: =+'SEMANA DEL 2 AL 7-3-26'!BS35+'SEMANA DEL 7 AL 14'!BS39+'SEMANA DEL 14 AL 21 '!BS39+'SEMANA DEL 21AL 28-3'!BS40+#REF! -> #REF! | BT27: =+'SEMANA DEL 2 AL 7-3-26'!BT35+'SEMANA DEL 7 AL 14'!BT39+'SEMANA DEL 14 AL 21 '!BT39+'SEMANA DEL 21AL 28-3'!BT40+#REF! -> #REF! | BU27: =+'SEMANA DEL 2 AL 7-3-26'!BU35+'SEMANA DEL 7 AL 14'!BU39+'SEMANA DEL 14 AL 21 '!BU39+'SEMANA DEL 21AL 28-3'!BU40+#REF! -> #REF! | ... CI27: =+'SEMANA DEL 2 AL 7-3-26'!CI35+'SEMANA DEL 7 AL 14'!CI39+'SEMANA DEL 14 AL 21 '!CI39+'SEMANA DEL 21AL 28-3'!CI40+#REF! -> #REF!
A28: =+'SEMANA DEL 2 AL 7-3-26'!#REF! -> #REF! | B28: =+'SEMANA DEL 2 AL 7-3-26'!#REF! -> #REF! | C28: =+'SEMANA DEL 2 AL 7-3-26'!#REF! -> #REF! | D28: =+'SEMANA DEL 2 AL 7-3-26'!#REF! -> #REF! | E28: =+'SEMANA DEL 2 AL 7-3-26'!#REF! -> #REF! | F28: =+'SEMANA DEL 2 AL 7-3-26'!#REF! -> #REF! | G28: =+'SEMANA DEL 2 AL 7-3-26'!#REF! -> #REF! | H28: =+'SEMANA DEL 2 AL 7-3-26'!#REF! -> #REF! | ... Q28: =+'SEMANA DEL 2 AL 7-3-26'!#REF! -> #REF! | R28: =+'SEMANA DEL 2 AL 7-3-26'!#REF!+'SEMANA DEL 7 AL 14'!R40+'SEMANA DEL 14 AL 21 '!R40+'SEMANA DEL 21AL 28-3'!R45+#REF! -> #REF! | S28: =+'SEMANA DEL 2 AL 7-3-26'!#REF!+'SEMANA DEL 7 AL 14'!S40+'SEMANA DEL 14 AL 21 '!S40+'SEMANA DEL 21AL 28-3'!S45+#REF! -> #REF! | T28: =+'SEMANA DEL 2 AL 7-3-26'!#REF!+'SEMANA DEL 7 AL 14'!T40+'SEMANA DEL 14 AL 21 '!T40+'SEMANA DEL 21AL 28-3'!T45+#REF! -> #REF! | U28: =+'SEMANA DEL 2 AL 7-3-26'!#REF!+'SEMANA DEL 7 AL 14'!U40+'SEMANA DEL 14 AL 21 '!U40+'SEMANA DEL 21AL 28-3'!U45+#REF! -> #REF! | V28: =+'SEMANA DEL 2 AL 7-3-26'!#REF!+'SEMANA DEL 7 AL 14'!V40+'SEMANA DEL 14 AL 21 '!V40+'SEMANA DEL 21AL 28-3'!V45+#REF! -> #REF! | W28: =+'SEMANA DEL 2 AL 7-3-26'!#REF!+'SEMANA DEL 7 AL 14'!W40+'SEMANA DEL 14 AL 21 '!W40+'SEMANA DEL 21AL 28-3'!W45+#REF! -> #REF! | X28: =+'SEMANA DEL 2 AL 7-3-26'!#REF!+'SEMANA DEL 7 AL 14'!X40+'SEMANA DEL 14 AL 21 '!X40+'SEMANA DEL 21AL 28-3'!X45+#REF! -> #REF! | Y28: =+'SEMANA DEL 2 AL 7-3-26'!#REF!+'SEMANA DEL 7 AL 14'!Y40+'SEMANA DEL 14 AL 21 '!Y40+'SEMANA DEL 21AL 28-3'!Y45+#REF! -> #REF! | ... AW28: =+'SEMANA DEL 2 AL 7-3-26'!#REF!+'SEMANA DEL 7 AL 14'!AW40+'SEMANA DEL 14 AL 21 '!AW40+'SEMANA DEL 21AL 28-3'!AW45+#REF! -> #REF! | AX28: =+B28+R28-AH28 -> #REF! | AY28: =+C28+S28-AI28 -> #REF! | AZ28: =+D28+T28-AJ28 -> #REF! | BA28: =+E28+U28-AK28 -> #REF! | BB28: =+F28+V28-AL28 -> #REF! | BC28: =+G28+W28-AM28 -> #REF! | BD28: =+H28+X28-AN28 -> #REF! | BE28: =+I28+Y28-AO28 -> #REF! | ... BM28: =+Q28+AG28-AW28 -> #REF! | BN28: =+'SEMANA DEL 2 AL 7-3-26'!#REF!+'SEMANA DEL 7 AL 14'!BN40+'SEMANA DEL 14 AL 21 '!BN40+'SEMANA DEL 21AL 28-3'!BN45+#REF! -> #REF! | BO28: =+'SEMANA DEL 2 AL 7-3-26'!#REF!+'SEMANA DEL 7 AL 14'!BO40+'SEMANA DEL 14 AL 21 '!BO40+'SEMANA DEL 21AL 28-3'!BO45+#REF! -> #REF! | BP28: =+'SEMANA DEL 2 AL 7-3-26'!#REF!+'SEMANA DEL 7 AL 14'!BP40+'SEMANA DEL 14 AL 21 '!BP40+'SEMANA DEL 21AL 28-3'!BP45+#REF! -> #REF! | BQ28: =+'SEMANA DEL 2 AL 7-3-26'!#REF!+'SEMANA DEL 7 AL 14'!BQ40+'SEMANA DEL 14 AL 21 '!BQ40+'SEMANA DEL 21AL 28-3'!BQ45+#REF! -> #REF! | BR28: =+'SEMANA DEL 2 AL 7-3-26'!#REF!+'SEMANA DEL 7 AL 14'!BR40+'SEMANA DEL 14 AL 21 '!BR40+'SEMANA DEL 21AL 28-3'!BR45+#REF! -> #REF! | BS28: =+'SEMANA DEL 2 AL 7-3-26'!#REF!+'SEMANA DEL 7 AL 14'!BS40+'SEMANA DEL 14 AL 21 '!BS40+'SEMANA DEL 21AL 28-3'!BS45+#REF! -> #REF! | BT28: =+'SEMANA DEL 2 AL 7-3-26'!#REF!+'SEMANA DEL 7 AL 14'!BT40+'SEMANA DEL 14 AL 21 '!BT40+'SEMANA DEL 21AL 28-3'!BT45+#REF! -> #REF! | BU28: =+'SEMANA DEL 2 AL 7-3-26'!#REF!+'SEMANA DEL 7 AL 14'!BU40+'SEMANA DEL 14 AL 21 '!BU40+'SEMANA DEL 21AL 28-3'!BU45+#REF! -> #REF! | ... CI28: =+'SEMANA DEL 2 AL 7-3-26'!#REF!+'SEMANA DEL 7 AL 14'!CI40+'SEMANA DEL 14 AL 21 '!CI40+'SEMANA DEL 21AL 28-3'!CI45+#REF! -> #REF!
A29: =+'SEMANA DEL 2 AL 7-3-26'!#REF! -> #REF! | B29: =+'SEMANA DEL 2 AL 7-3-26'!#REF! -> #REF! | C29: =+'SEMANA DEL 2 AL 7-3-26'!#REF! -> #REF! | D29: =+'SEMANA DEL 2 AL 7-3-26'!#REF! -> #REF! | E29: =+'SEMANA DEL 2 AL 7-3-26'!#REF! -> #REF! | F29: =+'SEMANA DEL 2 AL 7-3-26'!#REF! -> #REF! | G29: =+'SEMANA DEL 2 AL 7-3-26'!#REF! -> #REF! | H29: =+'SEMANA DEL 2 AL 7-3-26'!#REF! -> #REF! | ... Q29: =+'SEMANA DEL 2 AL 7-3-26'!#REF! -> #REF! | R29: =+'SEMANA DEL 2 AL 7-3-26'!R36+'SEMANA DEL 7 AL 14'!R41+'SEMANA DEL 14 AL 21 '!R41+'SEMANA DEL 21AL 28-3'!#REF!+#REF! -> #REF! | S29: =+'SEMANA DEL 2 AL 7-3-26'!S36+'SEMANA DEL 7 AL 14'!S41+'SEMANA DEL 14 AL 21 '!S41+'SEMANA DEL 21AL 28-3'!#REF!+#REF! -> #REF! | T29: =+'SEMANA DEL 2 AL 7-3-26'!T36+'SEMANA DEL 7 AL 14'!T41+'SEMANA DEL 14 AL 21 '!T41+'SEMANA DEL 21AL 28-3'!#REF!+#REF! -> #REF! | U29: =+'SEMANA DEL 2 AL 7-3-26'!U36+'SEMANA DEL 7 AL 14'!U41+'SEMANA DEL 14 AL 21 '!U41+'SEMANA DEL 21AL 28-3'!#REF!+#REF! -> #REF! | V29: =+'SEMANA DEL 2 AL 7-3-26'!V36+'SEMANA DEL 7 AL 14'!V41+'SEMANA DEL 14 AL 21 '!V41+'SEMANA DEL 21AL 28-3'!#REF!+#REF! -> #REF! | W29: =+'SEMANA DEL 2 AL 7-3-26'!W36+'SEMANA DEL 7 AL 14'!W41+'SEMANA DEL 14 AL 21 '!W41+'SEMANA DEL 21AL 28-3'!#REF!+#REF! -> #REF! | X29: =+'SEMANA DEL 2 AL 7-3-26'!X36+'SEMANA DEL 7 AL 14'!X41+'SEMANA DEL 14 AL 21 '!X41+'SEMANA DEL 21AL 28-3'!#REF!+#REF! -> #REF! | Y29: =+'SEMANA DEL 2 AL 7-3-26'!Y36+'SEMANA DEL 7 AL 14'!Y41+'SEMANA DEL 14 AL 21 '!Y41+'SEMANA DEL 21AL 28-3'!#REF!+#REF! -> #REF! | ... AW29: =+'SEMANA DEL 2 AL 7-3-26'!AW36+'SEMANA DEL 7 AL 14'!AW41+'SEMANA DEL 14 AL 21 '!AW41+'SEMANA DEL 21AL 28-3'!#REF!+#REF! -> #REF! | AX29: =+B29+R29-AH29 -> #REF! | AY29: =+C29+S29-AI29 -> #REF! | AZ29: =+D29+T29-AJ29 -> #REF! | BA29: =+E29+U29-AK29 -> #REF! | BB29: =+F29+V29-AL29 -> #REF! | BC29: =+G29+W29-AM29 -> #REF! | BD29: =+H29+X29-AN29 -> #REF! | BE29: =+I29+Y29-AO29 -> #REF! | ... BM29: =+Q29+AG29-AW29 -> #REF! | BN29: =+'SEMANA DEL 2 AL 7-3-26'!BN36+'SEMANA DEL 7 AL 14'!BN41+'SEMANA DEL 14 AL 21 '!BN41+'SEMANA DEL 21AL 28-3'!#REF!+#REF! -> #REF! | BO29: =+'SEMANA DEL 2 AL 7-3-26'!BO36+'SEMANA DEL 7 AL 14'!BO41+'SEMANA DEL 14 AL 21 '!BO41+'SEMANA DEL 21AL 28-3'!#REF!+#REF! -> #REF! | BP29: =+'SEMANA DEL 2 AL 7-3-26'!BP36+'SEMANA DEL 7 AL 14'!BP41+'SEMANA DEL 14 AL 21 '!BP41+'SEMANA DEL 21AL 28-3'!#REF!+#REF! -> #REF! | BQ29: =+'SEMANA DEL 2 AL 7-3-26'!BQ36+'SEMANA DEL 7 AL 14'!BQ41+'SEMANA DEL 14 AL 21 '!BQ41+'SEMANA DEL 21AL 28-3'!#REF!+#REF! -> #REF! | BR29: =+'SEMANA DEL 2 AL 7-3-26'!BR36+'SEMANA DEL 7 AL 14'!BR41+'SEMANA DEL 14 AL 21 '!BR41+'SEMANA DEL 21AL 28-3'!#REF!+#REF! -> #REF! | BS29: =+'SEMANA DEL 2 AL 7-3-26'!BS36+'SEMANA DEL 7 AL 14'!BS41+'SEMANA DEL 14 AL 21 '!BS41+'SEMANA DEL 21AL 28-3'!#REF!+#REF! -> #REF! | BT29: =+'SEMANA DEL 2 AL 7-3-26'!BT36+'SEMANA DEL 7 AL 14'!BT41+'SEMANA DEL 14 AL 21 '!BT41+'SEMANA DEL 21AL 28-3'!#REF!+#REF! -> #REF! | BU29: =+'SEMANA DEL 2 AL 7-3-26'!BU36+'SEMANA DEL 7 AL 14'!BU41+'SEMANA DEL 14 AL 21 '!BU41+'SEMANA DEL 21AL 28-3'!#REF!+#REF! -> #REF! | ... CI29: =+'SEMANA DEL 2 AL 7-3-26'!CI36+'SEMANA DEL 7 AL 14'!CI41+'SEMANA DEL 14 AL 21 '!CI41+'SEMANA DEL 21AL 28-3'!#REF!+#REF! -> #REF!
A30: =+'SEMANA DEL 2 AL 7-3-26'!#REF! -> #REF! | B30: =+'SEMANA DEL 2 AL 7-3-26'!#REF! -> #REF! | C30: =+'SEMANA DEL 2 AL 7-3-26'!#REF! -> #REF! | D30: =+'SEMANA DEL 2 AL 7-3-26'!#REF! -> #REF! | E30: =+'SEMANA DEL 2 AL 7-3-26'!#REF! -> #REF! | F30: =+'SEMANA DEL 2 AL 7-3-26'!#REF! -> #REF! | G30: =+'SEMANA DEL 2 AL 7-3-26'!#REF! -> #REF! | H30: =+'SEMANA DEL 2 AL 7-3-26'!#REF! -> #REF! | ... Q30: =+'SEMANA DEL 2 AL 7-3-26'!#REF! -> #REF! | R30: =+'SEMANA DEL 2 AL 7-3-26'!#REF!+'SEMANA DEL 7 AL 14'!R45+'SEMANA DEL 14 AL 21 '!R45+'SEMANA DEL 21AL 28-3'!#REF!+#REF! -> #REF! | S30: =+'SEMANA DEL 2 AL 7-3-26'!#REF!+'SEMANA DEL 7 AL 14'!S45+'SEMANA DEL 14 AL 21 '!S45+'SEMANA DEL 21AL 28-3'!#REF!+#REF! -> #REF! | T30: =+'SEMANA DEL 2 AL 7-3-26'!#REF!+'SEMANA DEL 7 AL 14'!T45+'SEMANA DEL 14 AL 21 '!T45+'SEMANA DEL 21AL 28-3'!#REF!+#REF! -> #REF! | U30: =+'SEMANA DEL 2 AL 7-3-26'!#REF!+'SEMANA DEL 7 AL 14'!U45+'SEMANA DEL 14 AL 21 '!U45+'SEMANA DEL 21AL 28-3'!#REF!+#REF! -> #REF! | V30: =+'SEMANA DEL 2 AL 7-3-26'!#REF!+'SEMANA DEL 7 AL 14'!V45+'SEMANA DEL 14 AL 21 '!V45+'SEMANA DEL 21AL 28-3'!#REF!+#REF! -> #REF! | W30: =+'SEMANA DEL 2 AL 7-3-26'!#REF!+'SEMANA DEL 7 AL 14'!W45+'SEMANA DEL 14 AL 21 '!W45+'SEMANA DEL 21AL 28-3'!#REF!+#REF! -> #REF! | X30: =+'SEMANA DEL 2 AL 7-3-26'!#REF!+'SEMANA DEL 7 AL 14'!X45+'SEMANA DEL 14 AL 21 '!X45+'SEMANA DEL 21AL 28-3'!#REF!+#REF! -> #REF! | Y30: =+'SEMANA DEL 2 AL 7-3-26'!#REF!+'SEMANA DEL 7 AL 14'!Y45+'SEMANA DEL 14 AL 21 '!Y45+'SEMANA DEL 21AL 28-3'!#REF!+#REF! -> #REF! | ... AW30: =+'SEMANA DEL 2 AL 7-3-26'!#REF!+'SEMANA DEL 7 AL 14'!AW45+'SEMANA DEL 14 AL 21 '!AW45+'SEMANA DEL 21AL 28-3'!#REF!+#REF! -> #REF! | AX30: =+B30+R30-AH30 -> #REF! | AY30: =+C30+S30-AI30 -> #REF! | AZ30: =+D30+T30-AJ30 -> #REF! | BA30: =+E30+U30-AK30 -> #REF! | BB30: =+F30+V30-AL30 -> #REF! | BC30: =+G30+W30-AM30 -> #REF! | BD30: =+H30+X30-AN30 -> #REF! | BE30: =+I30+Y30-AO30 -> #REF! | ... BM30: =+Q30+AG30-AW30 -> #REF! | BN30: =+'SEMANA DEL 2 AL 7-3-26'!#REF!+'SEMANA DEL 7 AL 14'!BN45+'SEMANA DEL 14 AL 21 '!BN45+'SEMANA DEL 21AL 28-3'!#REF!+#REF! -> #REF! | BO30: =+'SEMANA DEL 2 AL 7-3-26'!#REF!+'SEMANA DEL 7 AL 14'!BO45+'SEMANA DEL 14 AL 21 '!BO45+'SEMANA DEL 21AL 28-3'!#REF!+#REF! -> #REF! | BP30: =+'SEMANA DEL 2 AL 7-3-26'!#REF!+'SEMANA DEL 7 AL 14'!BP45+'SEMANA DEL 14 AL 21 '!BP45+'SEMANA DEL 21AL 28-3'!#REF!+#REF! -> #REF! | BQ30: =+'SEMANA DEL 2 AL 7-3-26'!#REF!+'SEMANA DEL 7 AL 14'!BQ45+'SEMANA DEL 14 AL 21 '!BQ45+'SEMANA DEL 21AL 28-3'!#REF!+#REF! -> #REF! | BR30: =+'SEMANA DEL 2 AL 7-3-26'!#REF!+'SEMANA DEL 7 AL 14'!BR45+'SEMANA DEL 14 AL 21 '!BR45+'SEMANA DEL 21AL 28-3'!#REF!+#REF! -> #REF! | BS30: =+'SEMANA DEL 2 AL 7-3-26'!#REF!+'SEMANA DEL 7 AL 14'!BS45+'SEMANA DEL 14 AL 21 '!BS45+'SEMANA DEL 21AL 28-3'!#REF!+#REF! -> #REF! | BT30: =+'SEMANA DEL 2 AL 7-3-26'!#REF!+'SEMANA DEL 7 AL 14'!BT45+'SEMANA DEL 14 AL 21 '!BT45+'SEMANA DEL 21AL 28-3'!#REF!+#REF! -> #REF! | BU30: =+'SEMANA DEL 2 AL 7-3-26'!#REF!+'SEMANA DEL 7 AL 14'!BU45+'SEMANA DEL 14 AL 21 '!BU45+'SEMANA DEL 21AL 28-3'!#REF!+#REF! -> #REF! | ... CI30: =+'SEMANA DEL 2 AL 7-3-26'!#REF!+'SEMANA DEL 7 AL 14'!CI45+'SEMANA DEL 14 AL 21 '!CI45+'SEMANA DEL 21AL 28-3'!#REF!+#REF! -> #REF!
A31: =+'SEMANA DEL 2 AL 7-3-26'!A31 -> RAMON PARRA | B31: =+'SEMANA DEL 2 AL 7-3-26'!B31 -> 0 | C31: =+'SEMANA DEL 2 AL 7-3-26'!C31 -> 0 | D31: =+'SEMANA DEL 2 AL 7-3-26'!D31 -> 0 | E31: =+'SEMANA DEL 2 AL 7-3-26'!E31 -> 0 | F31: =+'SEMANA DEL 2 AL 7-3-26'!F31 -> 0 | G31: =+'SEMANA DEL 2 AL 7-3-26'!G31 -> 0 | H31: =+'SEMANA DEL 2 AL 7-3-26'!H31 -> 0 | ... Q31: =+'SEMANA DEL 2 AL 7-3-26'!Q31 -> 0 | R31: =+'SEMANA DEL 2 AL 7-3-26'!R37+'SEMANA DEL 7 AL 14'!#REF!+'SEMANA DEL 14 AL 21 '!#REF!+'SEMANA DEL 21AL 28-3'!#REF!+#REF! -> #REF! | S31: =+'SEMANA DEL 2 AL 7-3-26'!S37+'SEMANA DEL 7 AL 14'!#REF!+'SEMANA DEL 14 AL 21 '!#REF!+'SEMANA DEL 21AL 28-3'!#REF!+#REF! -> #REF! | T31: =+'SEMANA DEL 2 AL 7-3-26'!T37+'SEMANA DEL 7 AL 14'!#REF!+'SEMANA DEL 14 AL 21 '!#REF!+'SEMANA DEL 21AL 28-3'!#REF!+#REF! -> #REF! | U31: =+'SEMANA DEL 2 AL 7-3-26'!U37+'SEMANA DEL 7 AL 14'!#REF!+'SEMANA DEL 14 AL 21 '!#REF!+'SEMANA DEL 21AL 28-3'!#REF!+#REF! -> #REF! | V31: =+'SEMANA DEL 2 AL 7-3-26'!V37+'SEMANA DEL 7 AL 14'!#REF!+'SEMANA DEL 14 AL 21 '!#REF!+'SEMANA DEL 21AL 28-3'!#REF!+#REF! -> #REF! | W31: =+'SEMANA DEL 2 AL 7-3-26'!W37+'SEMANA DEL 7 AL 14'!#REF!+'SEMANA DEL 14 AL 21 '!#REF!+'SEMANA DEL 21AL 28-3'!#REF!+#REF! -> #REF! | X31: =+'SEMANA DEL 2 AL 7-3-26'!X37+'SEMANA DEL 7 AL 14'!#REF!+'SEMANA DEL 14 AL 21 '!#REF!+'SEMANA DEL 21AL 28-3'!#REF!+#REF! -> #REF! | Y31: =+'SEMANA DEL 2 AL 7-3-26'!Y37+'SEMANA DEL 7 AL 14'!#REF!+'SEMANA DEL 14 AL 21 '!#REF!+'SEMANA DEL 21AL 28-3'!#REF!+#REF! -> #REF! | ... AW31: =+'SEMANA DEL 2 AL 7-3-26'!AW37+'SEMANA DEL 7 AL 14'!#REF!+'SEMANA DEL 14 AL 21 '!#REF!+'SEMANA DEL 21AL 28-3'!#REF!+#REF! -> #REF! | AX31: =+B31+R31-AH31 -> #REF! | AY31: =+C31+S31-AI31 -> #REF! | AZ31: =+D31+T31-AJ31 -> #REF! | BA31: =+E31+U31-AK31 -> #REF! | BB31: =+F31+V31-AL31 -> #REF! | BC31: =+G31+W31-AM31 -> #REF! | BD31: =+H31+X31-AN31 -> #REF! | BE31: =+I31+Y31-AO31 -> #REF! | ... BM31: =+Q31+AG31-AW31 -> #REF! | BN31: =+'SEMANA DEL 2 AL 7-3-26'!BN37+'SEMANA DEL 7 AL 14'!#REF!+'SEMANA DEL 14 AL 21 '!#REF!+'SEMANA DEL 21AL 28-3'!#REF!+#REF! -> #REF! | BO31: =+'SEMANA DEL 2 AL 7-3-26'!BO37+'SEMANA DEL 7 AL 14'!#REF!+'SEMANA DEL 14 AL 21 '!#REF!+'SEMANA DEL 21AL 28-3'!#REF!+#REF! -> #REF! | BP31: =+'SEMANA DEL 2 AL 7-3-26'!BP37+'SEMANA DEL 7 AL 14'!#REF!+'SEMANA DEL 14 AL 21 '!#REF!+'SEMANA DEL 21AL 28-3'!#REF!+#REF! -> #REF! | BQ31: =+'SEMANA DEL 2 AL 7-3-26'!BQ37+'SEMANA DEL 7 AL 14'!#REF!+'SEMANA DEL 14 AL 21 '!#REF!+'SEMANA DEL 21AL 28-3'!#REF!+#REF! -> #REF! | BR31: =+'SEMANA DEL 2 AL 7-3-26'!BR37+'SEMANA DEL 7 AL 14'!#REF!+'SEMANA DEL 14 AL 21 '!#REF!+'SEMANA DEL 21AL 28-3'!#REF!+#REF! -> #REF! | BS31: =+'SEMANA DEL 2 AL 7-3-26'!BS37+'SEMANA DEL 7 AL 14'!#REF!+'SEMANA DEL 14 AL 21 '!#REF!+'SEMANA DEL 21AL 28-3'!#REF!+#REF! -> #REF! | BT31: =+'SEMANA DEL 2 AL 7-3-26'!BT37+'SEMANA DEL 7 AL 14'!#REF!+'SEMANA DEL 14 AL 21 '!#REF!+'SEMANA DEL 21AL 28-3'!#REF!+#REF! -> #REF! | BU31: =+'SEMANA DEL 2 AL 7-3-26'!BU37+'SEMANA DEL 7 AL 14'!#REF!+'SEMANA DEL 14 AL 21 '!#REF!+'SEMANA DEL 21AL 28-3'!#REF!+#REF! -> #REF! | ... CI31: =+'SEMANA DEL 2 AL 7-3-26'!CI37+'SEMANA DEL 7 AL 14'!#REF!+'SEMANA DEL 14 AL 21 '!#REF!+'SEMANA DEL 21AL 28-3'!#REF!+#REF! -> #REF!
A32: =+'SEMANA DEL 2 AL 7-3-26'!A32 -> SULAY ALMEIDA | B32: =+'SEMANA DEL 2 AL 7-3-26'!B32 -> 1 | C32: =+'SEMANA DEL 2 AL 7-3-26'!C32 -> 1.81 | D32: =+'SEMANA DEL 2 AL 7-3-26'!D32 -> 6.95 | E32: =+'SEMANA DEL 2 AL 7-3-26'!E32 -> 0 | F32: =+'SEMANA DEL 2 AL 7-3-26'!F32 -> 0 | G32: =+'SEMANA DEL 2 AL 7-3-26'!G32 -> 0 | H32: =+'SEMANA DEL 2 AL 7-3-26'!H32 -> 0 | ... Q32: =+'SEMANA DEL 2 AL 7-3-26'!Q32 -> 0 | R32: =+'SEMANA DEL 2 AL 7-3-26'!#REF!+'SEMANA DEL 7 AL 14'!#REF!+'SEMANA DEL 14 AL 21 '!#REF!+'SEMANA DEL 21AL 28-3'!#REF!+#REF! -> #REF! | S32: =+'SEMANA DEL 2 AL 7-3-26'!#REF!+'SEMANA DEL 7 AL 14'!#REF!+'SEMANA DEL 14 AL 21 '!#REF!+'SEMANA DEL 21AL 28-3'!#REF!+#REF! -> #REF! | T32: =+'SEMANA DEL 2 AL 7-3-26'!#REF!+'SEMANA DEL 7 AL 14'!#REF!+'SEMANA DEL 14 AL 21 '!#REF!+'SEMANA DEL 21AL 28-3'!#REF!+#REF! -> #REF! | U32: =+'SEMANA DEL 2 AL 7-3-26'!#REF!+'SEMANA DEL 7 AL 14'!#REF!+'SEMANA DEL 14 AL 21 '!#REF!+'SEMANA DEL 21AL 28-3'!#REF!+#REF! -> #REF! | V32: =+'SEMANA DEL 2 AL 7-3-26'!#REF!+'SEMANA DEL 7 AL 14'!#REF!+'SEMANA DEL 14 AL 21 '!#REF!+'SEMANA DEL 21AL 28-3'!#REF!+#REF! -> #REF! | W32: =+'SEMANA DEL 2 AL 7-3-26'!#REF!+'SEMANA DEL 7 AL 14'!#REF!+'SEMANA DEL 14 AL 21 '!#REF!+'SEMANA DEL 21AL 28-3'!#REF!+#REF! -> #REF! | X32: =+'SEMANA DEL 2 AL 7-3-26'!#REF!+'SEMANA DEL 7 AL 14'!#REF!+'SEMANA DEL 14 AL 21 '!#REF!+'SEMANA DEL 21AL 28-3'!#REF!+#REF! -> #REF! | Y32: =+'SEMANA DEL 2 AL 7-3-26'!#REF!+'SEMANA DEL 7 AL 14'!#REF!+'SEMANA DEL 14 AL 21 '!#REF!+'SEMANA DEL 21AL 28-3'!#REF!+#REF! -> #REF! | ... AW32: =+'SEMANA DEL 2 AL 7-3-26'!#REF!+'SEMANA DEL 7 AL 14'!#REF!+'SEMANA DEL 14 AL 21 '!#REF!+'SEMANA DEL 21AL 28-3'!#REF!+#REF! -> #REF! | AX32: =+B32+R32-AH32 -> #REF! | AY32: =+C32+S32-AI32 -> #REF! | AZ32: =+D32+T32-AJ32 -> #REF! | BA32: =+E32+U32-AK32 -> #REF! | BB32: =+F32+V32-AL32 -> #REF! | BC32: =+G32+W32-AM32 -> #REF! | BD32: =+H32+X32-AN32 -> #REF! | BE32: =+I32+Y32-AO32 -> #REF! | ... BM32: =+Q32+AG32-AW32 -> #REF! | BN32: =+'SEMANA DEL 2 AL 7-3-26'!#REF!+'SEMANA DEL 7 AL 14'!#REF!+'SEMANA DEL 14 AL 21 '!#REF!+'SEMANA DEL 21AL 28-3'!#REF!+#REF! -> #REF! | BO32: =+'SEMANA DEL 2 AL 7-3-26'!#REF!+'SEMANA DEL 7 AL 14'!#REF!+'SEMANA DEL 14 AL 21 '!#REF!+'SEMANA DEL 21AL 28-3'!#REF!+#REF! -> #REF! | BP32: =+'SEMANA DEL 2 AL 7-3-26'!#REF!+'SEMANA DEL 7 AL 14'!#REF!+'SEMANA DEL 14 AL 21 '!#REF!+'SEMANA DEL 21AL 28-3'!#REF!+#REF! -> #REF! | BQ32: =+'SEMANA DEL 2 AL 7-3-26'!#REF!+'SEMANA DEL 7 AL 14'!#REF!+'SEMANA DEL 14 AL 21 '!#REF!+'SEMANA DEL 21AL 28-3'!#REF!+#REF! -> #REF! | BR32: =+'SEMANA DEL 2 AL 7-3-26'!#REF!+'SEMANA DEL 7 AL 14'!#REF!+'SEMANA DEL 14 AL 21 '!#REF!+'SEMANA DEL 21AL 28-3'!#REF!+#REF! -> #REF! | BS32: =+'SEMANA DEL 2 AL 7-3-26'!#REF!+'SEMANA DEL 7 AL 14'!#REF!+'SEMANA DEL 14 AL 21 '!#REF!+'SEMANA DEL 21AL 28-3'!#REF!+#REF! -> #REF! | BT32: =+'SEMANA DEL 2 AL 7-3-26'!#REF!+'SEMANA DEL 7 AL 14'!#REF!+'SEMANA DEL 14 AL 21 '!#REF!+'SEMANA DEL 21AL 28-3'!#REF!+#REF! -> #REF! | BU32: =+'SEMANA DEL 2 AL 7-3-26'!#REF!+'SEMANA DEL 7 AL 14'!#REF!+'SEMANA DEL 14 AL 21 '!#REF!+'SEMANA DEL 21AL 28-3'!#REF!+#REF! -> #REF! | ... CI32: =+'SEMANA DEL 2 AL 7-3-26'!#REF!+'SEMANA DEL 7 AL 14'!#REF!+'SEMANA DEL 14 AL 21 '!#REF!+'SEMANA DEL 21AL 28-3'!#REF!+#REF! -> #REF!
A33: =+'SEMANA DEL 2 AL 7-3-26'!A33 -> RENE ALMEIDA | B33: =+'SEMANA DEL 2 AL 7-3-26'!B33 -> 1.35 | C33: =+'SEMANA DEL 2 AL 7-3-26'!C33 -> 1.43 | D33: =+'SEMANA DEL 2 AL 7-3-26'!D33 -> 12.75 | E33: =+'SEMANA DEL 2 AL 7-3-26'!E33 -> 0 | F33: =+'SEMANA DEL 2 AL 7-3-26'!F33 -> 0 | G33: =+'SEMANA DEL 2 AL 7-3-26'!G33 -> 0 | H33: =+'SEMANA DEL 2 AL 7-3-26'!H33 -> 0 | ... Q33: =+'SEMANA DEL 2 AL 7-3-26'!Q33 -> 0 | R33: =+'SEMANA DEL 2 AL 7-3-26'!#REF!+'SEMANA DEL 7 AL 14'!#REF!+'SEMANA DEL 14 AL 21 '!#REF!+'SEMANA DEL 21AL 28-3'!#REF!+#REF! -> #REF! | S33: =+'SEMANA DEL 2 AL 7-3-26'!#REF!+'SEMANA DEL 7 AL 14'!#REF!+'SEMANA DEL 14 AL 21 '!#REF!+'SEMANA DEL 21AL 28-3'!#REF!+#REF! -> #REF! | T33: =+'SEMANA DEL 2 AL 7-3-26'!#REF!+'SEMANA DEL 7 AL 14'!#REF!+'SEMANA DEL 14 AL 21 '!#REF!+'SEMANA DEL 21AL 28-3'!#REF!+#REF! -> #REF! | U33: =+'SEMANA DEL 2 AL 7-3-26'!#REF!+'SEMANA DEL 7 AL 14'!#REF!+'SEMANA DEL 14 AL 21 '!#REF!+'SEMANA DEL 21AL 28-3'!#REF!+#REF! -> #REF! | V33: =+'SEMANA DEL 2 AL 7-3-26'!#REF!+'SEMANA DEL 7 AL 14'!#REF!+'SEMANA DEL 14 AL 21 '!#REF!+'SEMANA DEL 21AL 28-3'!#REF!+#REF! -> #REF! | W33: =+'SEMANA DEL 2 AL 7-3-26'!#REF!+'SEMANA DEL 7 AL 14'!#REF!+'SEMANA DEL 14 AL 21 '!#REF!+'SEMANA DEL 21AL 28-3'!#REF!+#REF! -> #REF! | X33: =+'SEMANA DEL 2 AL 7-3-26'!#REF!+'SEMANA DEL 7 AL 14'!#REF!+'SEMANA DEL 14 AL 21 '!#REF!+'SEMANA DEL 21AL 28-3'!#REF!+#REF! -> #REF! | Y33: =+'SEMANA DEL 2 AL 7-3-26'!#REF!+'SEMANA DEL 7 AL 14'!#REF!+'SEMANA DEL 14 AL 21 '!#REF!+'SEMANA DEL 21AL 28-3'!#REF!+#REF! -> #REF! | ... AW33: =+'SEMANA DEL 2 AL 7-3-26'!#REF!+'SEMANA DEL 7 AL 14'!#REF!+'SEMANA DEL 14 AL 21 '!#REF!+'SEMANA DEL 21AL 28-3'!#REF!+#REF! -> #REF! | AX33: =+B33+R33-AH33 -> #REF! | AY33: =+C33+S33-AI33 -> #REF! | AZ33: =+D33+T33-AJ33 -> #REF! | BA33: =+E33+U33-AK33 -> #REF! | BB33: =+F33+V33-AL33 -> #REF! | BC33: =+G33+W33-AM33 -> #REF! | BD33: =+H33+X33-AN33 -> #REF! | BE33: =+I33+Y33-AO33 -> #REF! | ... BM33: =+Q33+AG33-AW33 -> #REF! | BN33: =+'SEMANA DEL 2 AL 7-3-26'!#REF!+'SEMANA DEL 7 AL 14'!#REF!+'SEMANA DEL 14 AL 21 '!#REF!+'SEMANA DEL 21AL 28-3'!#REF!+#REF! -> #REF! | BO33: =+'SEMANA DEL 2 AL 7-3-26'!#REF!+'SEMANA DEL 7 AL 14'!#REF!+'SEMANA DEL 14 AL 21 '!#REF!+'SEMANA DEL 21AL 28-3'!#REF!+#REF! -> #REF! | BP33: =+'SEMANA DEL 2 AL 7-3-26'!#REF!+'SEMANA DEL 7 AL 14'!#REF!+'SEMANA DEL 14 AL 21 '!#REF!+'SEMANA DEL 21AL 28-3'!#REF!+#REF! -> #REF! | BQ33: =+'SEMANA DEL 2 AL 7-3-26'!#REF!+'SEMANA DEL 7 AL 14'!#REF!+'SEMANA DEL 14 AL 21 '!#REF!+'SEMANA DEL 21AL 28-3'!#REF!+#REF! -> #REF! | BR33: =+'SEMANA DEL 2 AL 7-3-26'!#REF!+'SEMANA DEL 7 AL 14'!#REF!+'SEMANA DEL 14 AL 21 '!#REF!+'SEMANA DEL 21AL 28-3'!#REF!+#REF! -> #REF! | BS33: =+'SEMANA DEL 2 AL 7-3-26'!#REF!+'SEMANA DEL 7 AL 14'!#REF!+'SEMANA DEL 14 AL 21 '!#REF!+'SEMANA DEL 21AL 28-3'!#REF!+#REF! -> #REF! | BT33: =+'SEMANA DEL 2 AL 7-3-26'!#REF!+'SEMANA DEL 7 AL 14'!#REF!+'SEMANA DEL 14 AL 21 '!#REF!+'SEMANA DEL 21AL 28-3'!#REF!+#REF! -> #REF! | BU33: =+'SEMANA DEL 2 AL 7-3-26'!#REF!+'SEMANA DEL 7 AL 14'!#REF!+'SEMANA DEL 14 AL 21 '!#REF!+'SEMANA DEL 21AL 28-3'!#REF!+#REF! -> #REF! | ... CI33: =+'SEMANA DEL 2 AL 7-3-26'!#REF!+'SEMANA DEL 7 AL 14'!#REF!+'SEMANA DEL 14 AL 21 '!#REF!+'SEMANA DEL 21AL 28-3'!#REF!+#REF! -> #REF!
A34: =+'SEMANA DEL 2 AL 7-3-26'!A34 -> RUBIELA MARTINEZ | B34: =+'SEMANA DEL 2 AL 7-3-26'!B34 -> 0 | C34: =+'SEMANA DEL 2 AL 7-3-26'!C34 -> 1.56 | D34: =+'SEMANA DEL 2 AL 7-3-26'!D34 -> -0.002 | E34: =+'SEMANA DEL 2 AL 7-3-26'!E34 -> 0 | F34: =+'SEMANA DEL 2 AL 7-3-26'!F34 -> 0 | G34: =+'SEMANA DEL 2 AL 7-3-26'!G34 -> 0 | H34: =+'SEMANA DEL 2 AL 7-3-26'!H34 -> 0 | ... Q34: =+'SEMANA DEL 2 AL 7-3-26'!Q34 -> 0 | R34: =+'SEMANA DEL 2 AL 7-3-26'!R42+'SEMANA DEL 7 AL 14'!#REF!+'SEMANA DEL 14 AL 21 '!#REF!+'SEMANA DEL 21AL 28-3'!#REF!+#REF! -> #REF! | S34: =+'SEMANA DEL 2 AL 7-3-26'!S42+'SEMANA DEL 7 AL 14'!#REF!+'SEMANA DEL 14 AL 21 '!#REF!+'SEMANA DEL 21AL 28-3'!#REF!+#REF! -> #REF! | T34: =+'SEMANA DEL 2 AL 7-3-26'!T42+'SEMANA DEL 7 AL 14'!#REF!+'SEMANA DEL 14 AL 21 '!#REF!+'SEMANA DEL 21AL 28-3'!#REF!+#REF! -> #REF! | U34: =+'SEMANA DEL 2 AL 7-3-26'!U42+'SEMANA DEL 7 AL 14'!#REF!+'SEMANA DEL 14 AL 21 '!#REF!+'SEMANA DEL 21AL 28-3'!#REF!+#REF! -> #REF! | V34: =+'SEMANA DEL 2 AL 7-3-26'!V42+'SEMANA DEL 7 AL 14'!#REF!+'SEMANA DEL 14 AL 21 '!#REF!+'SEMANA DEL 21AL 28-3'!#REF!+#REF! -> #REF! | W34: =+'SEMANA DEL 2 AL 7-3-26'!W42+'SEMANA DEL 7 AL 14'!#REF!+'SEMANA DEL 14 AL 21 '!#REF!+'SEMANA DEL 21AL 28-3'!#REF!+#REF! -> #REF! | X34: =+'SEMANA DEL 2 AL 7-3-26'!X42+'SEMANA DEL 7 AL 14'!#REF!+'SEMANA DEL 14 AL 21 '!#REF!+'SEMANA DEL 21AL 28-3'!#REF!+#REF! -> #REF! | Y34: =+'SEMANA DEL 2 AL 7-3-26'!Y42+'SEMANA DEL 7 AL 14'!#REF!+'SEMANA DEL 14 AL 21 '!#REF!+'SEMANA DEL 21AL 28-3'!#REF!+#REF! -> #REF! | ... AW34: =+'SEMANA DEL 2 AL 7-3-26'!AW42+'SEMANA DEL 7 AL 14'!#REF!+'SEMANA DEL 14 AL 21 '!#REF!+'SEMANA DEL 21AL 28-3'!#REF!+#REF! -> #REF! | AX34: =+B34+R34-AH34 -> #REF! | AY34: =+C34+S34-AI34 -> #REF! | AZ34: =+D34+T34-AJ34 -> #REF! | BA34: =+E34+U34-AK34 -> #REF! | BB34: =+F34+V34-AL34 -> #REF! | BC34: =+G34+W34-AM34 -> #REF! | BD34: =+H34+X34-AN34 -> #REF! | BE34: =+I34+Y34-AO34 -> #REF! | ... BM34: =+Q34+AG34-AW34 -> #REF! | BN34: =+'SEMANA DEL 2 AL 7-3-26'!BN42+'SEMANA DEL 7 AL 14'!#REF!+'SEMANA DEL 14 AL 21 '!#REF!+'SEMANA DEL 21AL 28-3'!#REF!+#REF! -> #REF! | BO34: =+'SEMANA DEL 2 AL 7-3-26'!BO42+'SEMANA DEL 7 AL 14'!#REF!+'SEMANA DEL 14 AL 21 '!#REF!+'SEMANA DEL 21AL 28-3'!#REF!+#REF! -> #REF! | BP34: =+'SEMANA DEL 2 AL 7-3-26'!BP42+'SEMANA DEL 7 AL 14'!#REF!+'SEMANA DEL 14 AL 21 '!#REF!+'SEMANA DEL 21AL 28-3'!#REF!+#REF! -> #REF! | BQ34: =+'SEMANA DEL 2 AL 7-3-26'!BQ42+'SEMANA DEL 7 AL 14'!#REF!+'SEMANA DEL 14 AL 21 '!#REF!+'SEMANA DEL 21AL 28-3'!#REF!+#REF! -> #REF! | BR34: =+'SEMANA DEL 2 AL 7-3-26'!BR42+'SEMANA DEL 7 AL 14'!#REF!+'SEMANA DEL 14 AL 21 '!#REF!+'SEMANA DEL 21AL 28-3'!#REF!+#REF! -> #REF! | BS34: =+'SEMANA DEL 2 AL 7-3-26'!BS42+'SEMANA DEL 7 AL 14'!#REF!+'SEMANA DEL 14 AL 21 '!#REF!+'SEMANA DEL 21AL 28-3'!#REF!+#REF! -> #REF! | BT34: =+'SEMANA DEL 2 AL 7-3-26'!BT42+'SEMANA DEL 7 AL 14'!#REF!+'SEMANA DEL 14 AL 21 '!#REF!+'SEMANA DEL 21AL 28-3'!#REF!+#REF! -> #REF! | BU34: =+'SEMANA DEL 2 AL 7-3-26'!BU42+'SEMANA DEL 7 AL 14'!#REF!+'SEMANA DEL 14 AL 21 '!#REF!+'SEMANA DEL 21AL 28-3'!#REF!+#REF! -> #REF! | ... CI34: =+'SEMANA DEL 2 AL 7-3-26'!CI42+'SEMANA DEL 7 AL 14'!#REF!+'SEMANA DEL 14 AL 21 '!#REF!+'SEMANA DEL 21AL 28-3'!#REF!+#REF! -> #REF!
A35: =+'SEMANA DEL 2 AL 7-3-26'!A35 -> ROSMIRA DURAN | B35: =+'SEMANA DEL 2 AL 7-3-26'!B35 -> 0.996 | C35: =+'SEMANA DEL 2 AL 7-3-26'!C35 -> 0.9 | D35: =+'SEMANA DEL 2 AL 7-3-26'!D35 -> 3.5 | E35: =+'SEMANA DEL 2 AL 7-3-26'!E35 -> 1 | F35: =+'SEMANA DEL 2 AL 7-3-26'!F35 -> 0 | G35: =+'SEMANA DEL 2 AL 7-3-26'!G35 -> 0 | H35: =+'SEMANA DEL 2 AL 7-3-26'!H35 -> 0 | ... Q35: =+'SEMANA DEL 2 AL 7-3-26'!Q35 -> 0 | R35: =+'SEMANA DEL 2 AL 7-3-26'!#REF!+'SEMANA DEL 7 AL 14'!#REF!+'SEMANA DEL 14 AL 21 '!#REF!+'SEMANA DEL 21AL 28-3'!#REF!+#REF! -> #REF! | S35: =+'SEMANA DEL 2 AL 7-3-26'!#REF!+'SEMANA DEL 7 AL 14'!#REF!+'SEMANA DEL 14 AL 21 '!#REF!+'SEMANA DEL 21AL 28-3'!#REF!+#REF! -> #REF! | T35: =+'SEMANA DEL 2 AL 7-3-26'!#REF!+'SEMANA DEL 7 AL 14'!#REF!+'SEMANA DEL 14 AL 21 '!#REF!+'SEMANA DEL 21AL 28-3'!#REF!+#REF! -> #REF! | U35: =+'SEMANA DEL 2 AL 7-3-26'!#REF!+'SEMANA DEL 7 AL 14'!#REF!+'SEMANA DEL 14 AL 21 '!#REF!+'SEMANA DEL 21AL 28-3'!#REF!+#REF! -> #REF! | V35: =+'SEMANA DEL 2 AL 7-3-26'!#REF!+'SEMANA DEL 7 AL 14'!#REF!+'SEMANA DEL 14 AL 21 '!#REF!+'SEMANA DEL 21AL 28-3'!#REF!+#REF! -> #REF! | W35: =+'SEMANA DEL 2 AL 7-3-26'!#REF!+'SEMANA DEL 7 AL 14'!#REF!+'SEMANA DEL 14 AL 21 '!#REF!+'SEMANA DEL 21AL 28-3'!#REF!+#REF! -> #REF! | X35: =+'SEMANA DEL 2 AL 7-3-26'!#REF!+'SEMANA DEL 7 AL 14'!#REF!+'SEMANA DEL 14 AL 21 '!#REF!+'SEMANA DEL 21AL 28-3'!#REF!+#REF! -> #REF! | Y35: =+'SEMANA DEL 2 AL 7-3-26'!#REF!+'SEMANA DEL 7 AL 14'!#REF!+'SEMANA DEL 14 AL 21 '!#REF!+'SEMANA DEL 21AL 28-3'!#REF!+#REF! -> #REF! | ... AW35: =+'SEMANA DEL 2 AL 7-3-26'!#REF!+'SEMANA DEL 7 AL 14'!#REF!+'SEMANA DEL 14 AL 21 '!#REF!+'SEMANA DEL 21AL 28-3'!#REF!+#REF! -> #REF! | AX35: =+B35+R35-AH35 -> #REF! | AY35: =+C35+S35-AI35 -> #REF! | AZ35: =+D35+T35-AJ35 -> #REF! | BA35: =+E35+U35-AK35 -> #REF! | BB35: =+F35+V35-AL35 -> #REF! | BC35: =+G35+W35-AM35 -> #REF! | BD35: =+H35+X35-AN35 -> #REF! | BE35: =+I35+Y35-AO35 -> #REF! | ... BM35: =+Q35+AG35-AW35 -> #REF! | BN35: =+'SEMANA DEL 2 AL 7-3-26'!#REF!+'SEMANA DEL 7 AL 14'!#REF!+'SEMANA DEL 14 AL 21 '!#REF!+'SEMANA DEL 21AL 28-3'!#REF!+#REF! -> #REF! | BO35: =+'SEMANA DEL 2 AL 7-3-26'!#REF!+'SEMANA DEL 7 AL 14'!#REF!+'SEMANA DEL 14 AL 21 '!#REF!+'SEMANA DEL 21AL 28-3'!#REF!+#REF! -> #REF! | BP35: =+'SEMANA DEL 2 AL 7-3-26'!#REF!+'SEMANA DEL 7 AL 14'!#REF!+'SEMANA DEL 14 AL 21 '!#REF!+'SEMANA DEL 21AL 28-3'!#REF!+#REF! -> #REF! | BQ35: =+'SEMANA DEL 2 AL 7-3-26'!#REF!+'SEMANA DEL 7 AL 14'!#REF!+'SEMANA DEL 14 AL 21 '!#REF!+'SEMANA DEL 21AL 28-3'!#REF!+#REF! -> #REF! | BR35: =+'SEMANA DEL 2 AL 7-3-26'!#REF!+'SEMANA DEL 7 AL 14'!#REF!+'SEMANA DEL 14 AL 21 '!#REF!+'SEMANA DEL 21AL 28-3'!#REF!+#REF! -> #REF! | BS35: =+'SEMANA DEL 2 AL 7-3-26'!#REF!+'SEMANA DEL 7 AL 14'!#REF!+'SEMANA DEL 14 AL 21 '!#REF!+'SEMANA DEL 21AL 28-3'!#REF!+#REF! -> #REF! | BT35: =+'SEMANA DEL 2 AL 7-3-26'!#REF!+'SEMANA DEL 7 AL 14'!#REF!+'SEMANA DEL 14 AL 21 '!#REF!+'SEMANA DEL 21AL 28-3'!#REF!+#REF! -> #REF! | BU35: =+'SEMANA DEL 2 AL 7-3-26'!#REF!+'SEMANA DEL 7 AL 14'!#REF!+'SEMANA DEL 14 AL 21 '!#REF!+'SEMANA DEL 21AL 28-3'!#REF!+#REF! -> #REF! | ... CI35: =+'SEMANA DEL 2 AL 7-3-26'!#REF!+'SEMANA DEL 7 AL 14'!#REF!+'SEMANA DEL 14 AL 21 '!#REF!+'SEMANA DEL 21AL 28-3'!#REF!+#REF! -> #REF!
A36: =+'SEMANA DEL 2 AL 7-3-26'!#REF! -> #REF! | B36: =+'SEMANA DEL 2 AL 7-3-26'!#REF! -> #REF! | C36: =+'SEMANA DEL 2 AL 7-3-26'!#REF! -> #REF! | D36: =+'SEMANA DEL 2 AL 7-3-26'!#REF! -> #REF! | E36: =+'SEMANA DEL 2 AL 7-3-26'!#REF! -> #REF! | F36: =+'SEMANA DEL 2 AL 7-3-26'!#REF! -> #REF! | G36: =+'SEMANA DEL 2 AL 7-3-26'!#REF! -> #REF! | H36: =+'SEMANA DEL 2 AL 7-3-26'!#REF! -> #REF! | ... Q36: =+'SEMANA DEL 2 AL 7-3-26'!#REF! -> #REF! | R36: =+'SEMANA DEL 2 AL 7-3-26'!R43+'SEMANA DEL 7 AL 14'!#REF!+'SEMANA DEL 14 AL 21 '!#REF!+'SEMANA DEL 21AL 28-3'!#REF!+#REF! -> #REF! | S36: =+'SEMANA DEL 2 AL 7-3-26'!S43+'SEMANA DEL 7 AL 14'!#REF!+'SEMANA DEL 14 AL 21 '!#REF!+'SEMANA DEL 21AL 28-3'!#REF!+#REF! -> #REF! | T36: =+'SEMANA DEL 2 AL 7-3-26'!T43+'SEMANA DEL 7 AL 14'!#REF!+'SEMANA DEL 14 AL 21 '!#REF!+'SEMANA DEL 21AL 28-3'!#REF!+#REF! -> #REF! | U36: =+'SEMANA DEL 2 AL 7-3-26'!U43+'SEMANA DEL 7 AL 14'!#REF!+'SEMANA DEL 14 AL 21 '!#REF!+'SEMANA DEL 21AL 28-3'!#REF!+#REF! -> #REF! | V36: =+'SEMANA DEL 2 AL 7-3-26'!V43+'SEMANA DEL 7 AL 14'!#REF!+'SEMANA DEL 14 AL 21 '!#REF!+'SEMANA DEL 21AL 28-3'!#REF!+#REF! -> #REF! | W36: =+'SEMANA DEL 2 AL 7-3-26'!W43+'SEMANA DEL 7 AL 14'!#REF!+'SEMANA DEL 14 AL 21 '!#REF!+'SEMANA DEL 21AL 28-3'!#REF!+#REF! -> #REF! | X36: =+'SEMANA DEL 2 AL 7-3-26'!X43+'SEMANA DEL 7 AL 14'!#REF!+'SEMANA DEL 14 AL 21 '!#REF!+'SEMANA DEL 21AL 28-3'!#REF!+#REF! -> #REF! | Y36: =+'SEMANA DEL 2 AL 7-3-26'!Y43+'SEMANA DEL 7 AL 14'!#REF!+'SEMANA DEL 14 AL 21 '!#REF!+'SEMANA DEL 21AL 28-3'!#REF!+#REF! -> #REF! | ... AW36: =+'SEMANA DEL 2 AL 7-3-26'!AW43+'SEMANA DEL 7 AL 14'!#REF!+'SEMANA DEL 14 AL 21 '!#REF!+'SEMANA DEL 21AL 28-3'!#REF!+#REF! -> #REF! | AX36: =+B36+R36-AH36 -> #REF! | AY36: =+C36+S36-AI36 -> #REF! | AZ36: =+D36+T36-AJ36 -> #REF! | BA36: =+E36+U36-AK36 -> #REF! | BB36: =+F36+V36-AL36 -> #REF! | BC36: =+G36+W36-AM36 -> #REF! | BD36: =+H36+X36-AN36 -> #REF! | BE36: =+I36+Y36-AO36 -> #REF! | ... BM36: =+Q36+AG36-AW36 -> #REF! | BN36: =+'SEMANA DEL 2 AL 7-3-26'!BN43+'SEMANA DEL 7 AL 14'!#REF!+'SEMANA DEL 14 AL 21 '!#REF!+'SEMANA DEL 21AL 28-3'!#REF!+#REF! -> #REF! | BO36: =+'SEMANA DEL 2 AL 7-3-26'!BO43+'SEMANA DEL 7 AL 14'!#REF!+'SEMANA DEL 14 AL 21 '!#REF!+'SEMANA DEL 21AL 28-3'!#REF!+#REF! -> #REF! | BP36: =+'SEMANA DEL 2 AL 7-3-26'!BP43+'SEMANA DEL 7 AL 14'!#REF!+'SEMANA DEL 14 AL 21 '!#REF!+'SEMANA DEL 21AL 28-3'!#REF!+#REF! -> #REF! | BQ36: =+'SEMANA DEL 2 AL 7-3-26'!BQ43+'SEMANA DEL 7 AL 14'!#REF!+'SEMANA DEL 14 AL 21 '!#REF!+'SEMANA DEL 21AL 28-3'!#REF!+#REF! -> #REF! | BR36: =+'SEMANA DEL 2 AL 7-3-26'!BR43+'SEMANA DEL 7 AL 14'!#REF!+'SEMANA DEL 14 AL 21 '!#REF!+'SEMANA DEL 21AL 28-3'!#REF!+#REF! -> #REF! | BS36: =+'SEMANA DEL 2 AL 7-3-26'!BS43+'SEMANA DEL 7 AL 14'!#REF!+'SEMANA DEL 14 AL 21 '!#REF!+'SEMANA DEL 21AL 28-3'!#REF!+#REF! -> #REF! | BT36: =+'SEMANA DEL 2 AL 7-3-26'!BT43+'SEMANA DEL 7 AL 14'!#REF!+'SEMANA DEL 14 AL 21 '!#REF!+'SEMANA DEL 21AL 28-3'!#REF!+#REF! -> #REF! | BU36: =+'SEMANA DEL 2 AL 7-3-26'!BU43+'SEMANA DEL 7 AL 14'!#REF!+'SEMANA DEL 14 AL 21 '!#REF!+'SEMANA DEL 21AL 28-3'!#REF!+#REF! -> #REF! | ... CI36: =+'SEMANA DEL 2 AL 7-3-26'!CI43+'SEMANA DEL 7 AL 14'!#REF!+'SEMANA DEL 14 AL 21 '!#REF!+'SEMANA DEL 21AL 28-3'!#REF!+#REF! -> #REF!
A37: =+'SEMANA DEL 2 AL 7-3-26'!A36 -> ROSALBA MATAGIRA | B37: =+'SEMANA DEL 2 AL 7-3-26'!B36 -> 0 | C37: =+'SEMANA DEL 2 AL 7-3-26'!C36 -> 0 | D37: =+'SEMANA DEL 2 AL 7-3-26'!D36 -> 0 | E37: =+'SEMANA DEL 2 AL 7-3-26'!E36 -> 0 | F37: =+'SEMANA DEL 2 AL 7-3-26'!F36 -> 0 | G37: =+'SEMANA DEL 2 AL 7-3-26'!G36 -> 0 | H37: =+'SEMANA DEL 2 AL 7-3-26'!H36 -> 0 | ... Q37: =+'SEMANA DEL 2 AL 7-3-26'!Q36 -> 0 | R37: =+'SEMANA DEL 2 AL 7-3-26'!#REF!+'SEMANA DEL 7 AL 14'!#REF!+'SEMANA DEL 14 AL 21 '!#REF!+'SEMANA DEL 21AL 28-3'!#REF!+#REF! -> #REF! | S37: =+'SEMANA DEL 2 AL 7-3-26'!#REF!+'SEMANA DEL 7 AL 14'!#REF!+'SEMANA DEL 14 AL 21 '!#REF!+'SEMANA DEL 21AL 28-3'!#REF!+#REF! -> #REF! | T37: =+'SEMANA DEL 2 AL 7-3-26'!#REF!+'SEMANA DEL 7 AL 14'!#REF!+'SEMANA DEL 14 AL 21 '!#REF!+'SEMANA DEL 21AL 28-3'!#REF!+#REF! -> #REF! | U37: =+'SEMANA DEL 2 AL 7-3-26'!#REF!+'SEMANA DEL 7 AL 14'!#REF!+'SEMANA DEL 14 AL 21 '!#REF!+'SEMANA DEL 21AL 28-3'!#REF!+#REF! -> #REF! | V37: =+'SEMANA DEL 2 AL 7-3-26'!#REF!+'SEMANA DEL 7 AL 14'!#REF!+'SEMANA DEL 14 AL 21 '!#REF!+'SEMANA DEL 21AL 28-3'!#REF!+#REF! -> #REF! | W37: =+'SEMANA DEL 2 AL 7-3-26'!#REF!+'SEMANA DEL 7 AL 14'!#REF!+'SEMANA DEL 14 AL 21 '!#REF!+'SEMANA DEL 21AL 28-3'!#REF!+#REF! -> #REF! | X37: =+'SEMANA DEL 2 AL 7-3-26'!#REF!+'SEMANA DEL 7 AL 14'!#REF!+'SEMANA DEL 14 AL 21 '!#REF!+'SEMANA DEL 21AL 28-3'!#REF!+#REF! -> #REF! | Y37: =+'SEMANA DEL 2 AL 7-3-26'!#REF!+'SEMANA DEL 7 AL 14'!#REF!+'SEMANA DEL 14 AL 21 '!#REF!+'SEMANA DEL 21AL 28-3'!#REF!+#REF! -> #REF! | ... AW37: =+'SEMANA DEL 2 AL 7-3-26'!#REF!+'SEMANA DEL 7 AL 14'!#REF!+'SEMANA DEL 14 AL 21 '!#REF!+'SEMANA DEL 21AL 28-3'!#REF!+#REF! -> #REF! | AX37: =+B37+R37-AH37 -> #REF! | AY37: =+C37+S37-AI37 -> #REF! | AZ37: =+D37+T37-AJ37 -> #REF! | BA37: =+E37+U37-AK37 -> #REF! | BB37: =+F37+V37-AL37 -> #REF! | BC37: =+G37+W37-AM37 -> #REF! | BD37: =+H37+X37-AN37 -> #REF! | BE37: =+I37+Y37-AO37 -> #REF! | ... BM37: =+Q37+AG37-AW37 -> #REF! | BN37: =+'SEMANA DEL 2 AL 7-3-26'!#REF!+'SEMANA DEL 7 AL 14'!#REF!+'SEMANA DEL 14 AL 21 '!#REF!+'SEMANA DEL 21AL 28-3'!#REF!+#REF! -> #REF! | BO37: =+'SEMANA DEL 2 AL 7-3-26'!#REF!+'SEMANA DEL 7 AL 14'!#REF!+'SEMANA DEL 14 AL 21 '!#REF!+'SEMANA DEL 21AL 28-3'!#REF!+#REF! -> #REF! | BP37: =+'SEMANA DEL 2 AL 7-3-26'!#REF!+'SEMANA DEL 7 AL 14'!#REF!+'SEMANA DEL 14 AL 21 '!#REF!+'SEMANA DEL 21AL 28-3'!#REF!+#REF! -> #REF! | BQ37: =+'SEMANA DEL 2 AL 7-3-26'!#REF!+'SEMANA DEL 7 AL 14'!#REF!+'SEMANA DEL 14 AL 21 '!#REF!+'SEMANA DEL 21AL 28-3'!#REF!+#REF! -> #REF! | BR37: =+'SEMANA DEL 2 AL 7-3-26'!#REF!+'SEMANA DEL 7 AL 14'!#REF!+'SEMANA DEL 14 AL 21 '!#REF!+'SEMANA DEL 21AL 28-3'!#REF!+#REF! -> #REF! | BS37: =+'SEMANA DEL 2 AL 7-3-26'!#REF!+'SEMANA DEL 7 AL 14'!#REF!+'SEMANA DEL 14 AL 21 '!#REF!+'SEMANA DEL 21AL 28-3'!#REF!+#REF! -> #REF! | BT37: =+'SEMANA DEL 2 AL 7-3-26'!#REF!+'SEMANA DEL 7 AL 14'!#REF!+'SEMANA DEL 14 AL 21 '!#REF!+'SEMANA DEL 21AL 28-3'!#REF!+#REF! -> #REF! | BU37: =+'SEMANA DEL 2 AL 7-3-26'!#REF!+'SEMANA DEL 7 AL 14'!#REF!+'SEMANA DEL 14 AL 21 '!#REF!+'SEMANA DEL 21AL 28-3'!#REF!+#REF! -> #REF! | ... CI37: =+'SEMANA DEL 2 AL 7-3-26'!#REF!+'SEMANA DEL 7 AL 14'!#REF!+'SEMANA DEL 14 AL 21 '!#REF!+'SEMANA DEL 21AL 28-3'!#REF!+#REF! -> #REF!
A38: =+'SEMANA DEL 2 AL 7-3-26'!#REF! -> #REF! | B38: =+'SEMANA DEL 2 AL 7-3-26'!#REF! -> #REF! | C38: =+'SEMANA DEL 2 AL 7-3-26'!#REF! -> #REF! | D38: =+'SEMANA DEL 2 AL 7-3-26'!#REF! -> #REF! | E38: =+'SEMANA DEL 2 AL 7-3-26'!#REF! -> #REF! | F38: =+'SEMANA DEL 2 AL 7-3-26'!#REF! -> #REF! | G38: =+'SEMANA DEL 2 AL 7-3-26'!#REF! -> #REF! | H38: =+'SEMANA DEL 2 AL 7-3-26'!#REF! -> #REF! | ... Q38: =+'SEMANA DEL 2 AL 7-3-26'!#REF! -> #REF! | R38: =+'SEMANA DEL 2 AL 7-3-26'!#REF!+'SEMANA DEL 7 AL 14'!#REF!+'SEMANA DEL 14 AL 21 '!#REF!+'SEMANA DEL 21AL 28-3'!#REF!+#REF! -> #REF! | S38: =+'SEMANA DEL 2 AL 7-3-26'!#REF!+'SEMANA DEL 7 AL 14'!#REF!+'SEMANA DEL 14 AL 21 '!#REF!+'SEMANA DEL 21AL 28-3'!#REF!+#REF! -> #REF! | T38: =+'SEMANA DEL 2 AL 7-3-26'!#REF!+'SEMANA DEL 7 AL 14'!#REF!+'SEMANA DEL 14 AL 21 '!#REF!+'SEMANA DEL 21AL 28-3'!#REF!+#REF! -> #REF! | U38: =+'SEMANA DEL 2 AL 7-3-26'!#REF!+'SEMANA DEL 7 AL 14'!#REF!+'SEMANA DEL 14 AL 21 '!#REF!+'SEMANA DEL 21AL 28-3'!#REF!+#REF! -> #REF! | V38: =+'SEMANA DEL 2 AL 7-3-26'!#REF!+'SEMANA DEL 7 AL 14'!#REF!+'SEMANA DEL 14 AL 21 '!#REF!+'SEMANA DEL 21AL 28-3'!#REF!+#REF! -> #REF! | W38: =+'SEMANA DEL 2 AL 7-3-26'!#REF!+'SEMANA DEL 7 AL 14'!#REF!+'SEMANA DEL 14 AL 21 '!#REF!+'SEMANA DEL 21AL 28-3'!#REF!+#REF! -> #REF! | X38: =+'SEMANA DEL 2 AL 7-3-26'!#REF!+'SEMANA DEL 7 AL 14'!#REF!+'SEMANA DEL 14 AL 21 '!#REF!+'SEMANA DEL 21AL 28-3'!#REF!+#REF! -> #REF! | Y38: =+'SEMANA DEL 2 AL 7-3-26'!#REF!+'SEMANA DEL 7 AL 14'!#REF!+'SEMANA DEL 14 AL 21 '!#REF!+'SEMANA DEL 21AL 28-3'!#REF!+#REF! -> #REF! | ... AW38: =+'SEMANA DEL 2 AL 7-3-26'!#REF!+'SEMANA DEL 7 AL 14'!#REF!+'SEMANA DEL 14 AL 21 '!#REF!+'SEMANA DEL 21AL 28-3'!#REF!+#REF! -> #REF! | AX38: =+B38+R38-AH38 -> #REF! | AY38: =+C38+S38-AI38 -> #REF! | AZ38: =+D38+T38-AJ38 -> #REF! | BA38: =+E38+U38-AK38 -> #REF! | BB38: =+F38+V38-AL38 -> #REF! | BC38: =+G38+W38-AM38 -> #REF! | BD38: =+H38+X38-AN38 -> #REF! | BE38: =+I38+Y38-AO38 -> #REF! | ... BM38: =+Q38+AG38-AW38 -> #REF! | BN38: =+'SEMANA DEL 2 AL 7-3-26'!#REF!+'SEMANA DEL 7 AL 14'!#REF!+'SEMANA DEL 14 AL 21 '!#REF!+'SEMANA DEL 21AL 28-3'!#REF!+#REF! -> #REF! | BO38: =+'SEMANA DEL 2 AL 7-3-26'!#REF!+'SEMANA DEL 7 AL 14'!#REF!+'SEMANA DEL 14 AL 21 '!#REF!+'SEMANA DEL 21AL 28-3'!#REF!+#REF! -> #REF! | BP38: =+'SEMANA DEL 2 AL 7-3-26'!#REF!+'SEMANA DEL 7 AL 14'!#REF!+'SEMANA DEL 14 AL 21 '!#REF!+'SEMANA DEL 21AL 28-3'!#REF!+#REF! -> #REF! | BQ38: =+'SEMANA DEL 2 AL 7-3-26'!#REF!+'SEMANA DEL 7 AL 14'!#REF!+'SEMANA DEL 14 AL 21 '!#REF!+'SEMANA DEL 21AL 28-3'!#REF!+#REF! -> #REF! | BR38: =+'SEMANA DEL 2 AL 7-3-26'!#REF!+'SEMANA DEL 7 AL 14'!#REF!+'SEMANA DEL 14 AL 21 '!#REF!+'SEMANA DEL 21AL 28-3'!#REF!+#REF! -> #REF! | BS38: =+'SEMANA DEL 2 AL 7-3-26'!#REF!+'SEMANA DEL 7 AL 14'!#REF!+'SEMANA DEL 14 AL 21 '!#REF!+'SEMANA DEL 21AL 28-3'!#REF!+#REF! -> #REF! | BT38: =+'SEMANA DEL 2 AL 7-3-26'!#REF!+'SEMANA DEL 7 AL 14'!#REF!+'SEMANA DEL 14 AL 21 '!#REF!+'SEMANA DEL 21AL 28-3'!#REF!+#REF! -> #REF! | BU38: =+'SEMANA DEL 2 AL 7-3-26'!#REF!+'SEMANA DEL 7 AL 14'!#REF!+'SEMANA DEL 14 AL 21 '!#REF!+'SEMANA DEL 21AL 28-3'!#REF!+#REF! -> #REF! | ... CI38: =+'SEMANA DEL 2 AL 7-3-26'!#REF!+'SEMANA DEL 7 AL 14'!#REF!+'SEMANA DEL 14 AL 21 '!#REF!+'SEMANA DEL 21AL 28-3'!#REF!+#REF! -> #REF!
A39: =+'SEMANA DEL 2 AL 7-3-26'!A37 -> STELLA SILVA | B39: =+'SEMANA DEL 2 AL 7-3-26'!B37 -> 0 | C39: =+'SEMANA DEL 2 AL 7-3-26'!C37 -> 0 | D39: =+'SEMANA DEL 2 AL 7-3-26'!D37 -> 0 | E39: =+'SEMANA DEL 2 AL 7-3-26'!E37 -> 0 | F39: =+'SEMANA DEL 2 AL 7-3-26'!F37 -> 0 | G39: =+'SEMANA DEL 2 AL 7-3-26'!G37 -> 0 | H39: =+'SEMANA DEL 2 AL 7-3-26'!H37 -> 0 | ... Q39: =+'SEMANA DEL 2 AL 7-3-26'!Q37 -> 0 | R39: =SUM(R4:R38) -> #REF! | S39: =SUM(S4:S38) -> #REF! | T39: =SUM(T4:T38) -> #REF! | U39: =SUM(U4:U38) -> #REF! | V39: =SUM(V4:V38) -> #REF! | W39: =SUM(W4:W38) -> #REF! | X39: =SUM(X4:X38) -> #REF! | Y39: =SUM(Y4:Y38) -> #REF! | ... CI39: =SUM(CI4:CI38) -> #REF!
A40: =+'SEMANA DEL 2 AL 7-3-26'!#REF! -> #REF! | B40: =+'SEMANA DEL 2 AL 7-3-26'!#REF! -> #REF! | C40: =+'SEMANA DEL 2 AL 7-3-26'!#REF! -> #REF! | D40: =+'SEMANA DEL 2 AL 7-3-26'!#REF! -> #REF! | E40: =+'SEMANA DEL 2 AL 7-3-26'!#REF! -> #REF! | F40: =+'SEMANA DEL 2 AL 7-3-26'!#REF! -> #REF! | G40: =+'SEMANA DEL 2 AL 7-3-26'!#REF! -> #REF! | H40: =+'SEMANA DEL 2 AL 7-3-26'!#REF! -> #REF! | ... Q40: =+'SEMANA DEL 2 AL 7-3-26'!#REF! -> #REF! | R40: =SUM(R5:R39) -> #REF! | S40: =SUM(S5:S39) -> #REF! | T40: =SUM(T5:T39) -> #REF! | U40: =SUM(U5:U39) -> #REF! | V40: =SUM(V5:V39) -> #REF! | W40: =SUM(W5:W39) -> #REF! | X40: =SUM(X5:X39) -> #REF! | Y40: =SUM(Y5:Y39) -> #REF! | ... CI40: =SUM(CI5:CI39) -> #REF!
A41: =+'SEMANA DEL 2 AL 7-3-26'!#REF! -> #REF! | B41: =+'SEMANA DEL 2 AL 7-3-26'!#REF! -> #REF! | C41: =+'SEMANA DEL 2 AL 7-3-26'!#REF! -> #REF! | D41: =+'SEMANA DEL 2 AL 7-3-26'!#REF! -> #REF! | E41: =+'SEMANA DEL 2 AL 7-3-26'!#REF! -> #REF! | F41: =+'SEMANA DEL 2 AL 7-3-26'!#REF! -> #REF! | G41: =+'SEMANA DEL 2 AL 7-3-26'!#REF! -> #REF! | H41: =+'SEMANA DEL 2 AL 7-3-26'!#REF! -> #REF! | ... Q41: =+'SEMANA DEL 2 AL 7-3-26'!#REF! -> #REF! | R41: =SUM(R6:R40) -> #REF! | S41: =SUM(S6:S40) -> #REF! | T41: =SUM(T6:T40) -> #REF! | U41: =SUM(U6:U40) -> #REF! | V41: =SUM(V6:V40) -> #REF! | W41: =SUM(W6:W40) -> #REF! | X41: =SUM(X6:X40) -> #REF! | Y41: =SUM(Y6:Y40) -> #REF! | ... CI41: =SUM(CI6:CI40) -> #REF!
A42: =+'SEMANA DEL 2 AL 7-3-26'!A42 -> YARIRETH ROA | B42: =+'SEMANA DEL 2 AL 7-3-26'!B42 -> 0.4 | C42: =+'SEMANA DEL 2 AL 7-3-26'!C42 -> 0.725 | D42: =+'SEMANA DEL 2 AL 7-3-26'!D42 -> 2.8 | E42: =+'SEMANA DEL 2 AL 7-3-26'!E42 -> 0 | F42: =+'SEMANA DEL 2 AL 7-3-26'!F42 -> 0 | G42: =+'SEMANA DEL 2 AL 7-3-26'!G42 -> 0 | H42: =+'SEMANA DEL 2 AL 7-3-26'!H42 -> 0 | ... Q42: =+'SEMANA DEL 2 AL 7-3-26'!Q42 -> 0 | R42: =SUM(R7:R41) -> #REF! | S42: =SUM(S7:S41) -> #REF! | T42: =SUM(T7:T41) -> #REF! | U42: =SUM(U7:U41) -> #REF! | V42: =SUM(V7:V41) -> #REF! | W42: =SUM(W7:W41) -> #REF! | X42: =SUM(X7:X41) -> #REF! | Y42: =SUM(Y7:Y41) -> #REF! | ... CI42: =SUM(CI7:CI41) -> #REF!
A43: =+'SEMANA DEL 2 AL 7-3-26'!A43 -> YOLI BECERRA | B43: =+'SEMANA DEL 2 AL 7-3-26'!B43 -> 0 | C43: =+'SEMANA DEL 2 AL 7-3-26'!C43 -> 0 | D43: =+'SEMANA DEL 2 AL 7-3-26'!D43 -> 3.4 | E43: =+'SEMANA DEL 2 AL 7-3-26'!E43 -> 0 | F43: =+'SEMANA DEL 2 AL 7-3-26'!F43 -> 0 | G43: =+'SEMANA DEL 2 AL 7-3-26'!G43 -> 0 | H43: =+'SEMANA DEL 2 AL 7-3-26'!H43 -> 0 | ... Q43: =+'SEMANA DEL 2 AL 7-3-26'!Q43 -> 0 | R43: =SUM(R8:R42) -> #REF! | S43: =SUM(S8:S42) -> #REF! | T43: =SUM(T8:T42) -> #REF! | U43: =SUM(U8:U42) -> #REF! | V43: =SUM(V8:V42) -> #REF! | W43: =SUM(W8:W42) -> #REF! | X43: =SUM(X8:X42) -> #REF! | Y43: =SUM(Y8:Y42) -> #REF! | ... CI43: =SUM(CI8:CI42) -> #REF!
A44: =+'SEMANA DEL 2 AL 7-3-26'!A45 -> 0 | B44: =SUM(B4:B43) -> #REF! | C44: =SUM(C4:C43) -> #REF! | D44: =SUM(D4:D43) -> #REF! | E44: =SUM(E4:E43) -> #REF! | F44: =SUM(F4:F43) -> #REF! | G44: =SUM(G4:G43) -> #REF! | H44: =SUM(H4:H43) -> #REF! | I44: =SUM(I4:I43) -> #REF! | ... CI44: =SUM(CI4:CI43) -> #REF!

Sheet SEMANA DEL 2 AL 7-3-26
A1: SEMANA # 9 DEL 2 AL 7 DE MARZO DEL 2026 | CH1: =4.55*65 -> 295.75 | CK1: =+A1 -> SEMANA # 9 DEL 2 AL 7 DE MARZO DEL 2026 | CS1: =+A1 -> SEMANA # 9 DEL 2 AL 7 DE MARZO DEL 2026
A2: FABRIQUINES SEMANA # 9 | CK2: =+A2 -> FABRIQUINES SEMANA # 9 | CS2: =+A2 -> FABRIQUINES SEMANA # 9
A3: PRODUCCION # 6 | AX3: SALDOS | BW3: SUMINISTROS | CB3: DESCUENTOS | CH3: OTRAS | CK3: =+A3 -> PRODUCCION # 6 | CS3: =+A3 -> PRODUCCION # 6
A4: NOMBRE | B4: CAPA | C4: CAPOTE | D4: PIC | E4: CESTA | F4: SACAS | G4: GOMA | H4: MAR | I4: PAPEL | J4: REST | K4: TABL | L4: MAQ | M4: TRAP | N4: SILLA | O4: PRENS | P4: PACORA | Q4: REZAGOS | R4: CAPA | S4: CAPOTE | T4: PIC | U4: CESTA | V4: SACAS | W4: GOMA | X4: MAR | Y4: PAPEL | Z4: REST | AA4: TABL | AB4: MAQ | AC4: TRAP | AD4: SILLA | AE4: PRENS | AF4: PACORAS | AG4: REZAGOS | AH4: CAPA | AI4: CAPOTE | AJ4: PIC | AK4: CESTA | AL4: SACAS | AM4: GOMA | AN4: MAR | AO4: PAPEL | AP4: REST | AQ4: TABL | AR4: MAQ | AS4: TRAP | AT4: PACORA | AU4: PRENS | AV4: PACORAS | AW4: REZAGOS | AX4: CAPA | AY4: CAPOTE | AZ4: PIC | BA4: CESTA | BB4: SACAS | BC4: GOMA | BD4: MAR | BE4: PAPPEL | BF4: RESIST | BG4: MAQUINA | BH4: TRAPOS | BI4: PACORAS | BJ4: PRENSA | BK4: PRENS | BL4: PACORAS | BM4: REZAGOS | BN4: TAB.ENTREG. | BO4: SACAS | BP4: GOMA | BQ4: MAR | BR4: PAPEL | BS4: REST | BT4: PACORA | BU4: MAQ | BV4: TRAP | BW4: SILLA | BX4: PRENS | BY4: PACORA | BZ4: REZAGOS | CA4: PRESTAMOS | CB4: AHORROS | CC4: PRECIO CAPA | CD4: PRECIO CAPOTE | CE4: PRECIO PICADURA | CF4: TOTAL MATERIAL | CG4: PRECIO TAB. | CH4: DEDUCCIONES | CI4: TOTAL A PAGAR $ | CK4: TABACOS RECIBIDOS | CM4: =+#REF! -> #REF! | CR4: NOMBRES APELLIDOS | CS4: CEDULA | CT4: TABACOS | CU4: REZAGOS | CV4: COMPRAS | CW4: PRECIO | CX4: RECORTE | CY4: VENA | CZ4: TOTAL BS | DA4: FIRMA | DB4: TOTAL | DC4: BS TABACOS | DD4: TOTAL A PAGAR PESOS
A5: =+'[1]SEMANA DEL 13 AL 20 '!A5 -> ALCIDES CORREA | B5: 0 | C5: 0 | D5: 0 | E5: 0 | F5: 0 | G5: 0 | H5: 0 | I5: 0 | J5: 0 | K5: 0 | L5: 0 | M5: 0 | N5: 0 | O5: 0 | P5: 0 | Q5: 0 | R5: 10 | S5: 18 | T5: 70 | U5: 8 | AH5: 10 | AI5: 18 | AJ5: 70 | AK5: 8 | AX5: =B5+R5-AH5 -> 0 | AY5: =C5+S5-AI5 -> 0 | AZ5: =D5+T5-AJ5 -> 0 | BA5: =E5+U5-AK5 -> 0 | BB5: =F5+V5-AL5 -> 0 | BC5: =G5+W5-AM5 -> 0 | BD5: =H5+X5-AN5 -> 0 | BE5: =I5+Y5-AO5 -> 0 | ... BH5: =L5+AB5-AR5 -> 0 | BI5: =+P5+AF5-AV5 -> 0 | BJ5: =N5+AD5-AT5 -> 0 | BK5: =O5+AE5-AU5 -> 0 | BL5: =P5+AF5-AV5 -> 0 | BM5: =Q5+AG5-AW5 -> 0 | BN5: 10000 | BO5: =+AL5*2500 -> 0 | BP5: =+AM5*60000 -> 0 | BQ5: =+AN5*3000 -> 0 | BR5: =+AO5*6000 -> 0 | BS5: =+AP5*8000 -> 0 | BT5: =+AQ5*8000 -> 0 | BU5: =+AR5*150000 -> 0 | BV5: =+AS5*3000 -> 0 | BW5: =+AT5*25000 -> 0 | BX5: =+AU5*200000 -> 0 | BY5: =+AV5*8000 -> 0 | BZ5: =+AW5*1.5 -> 0 | CC5: =+AH5*16 -> 160 | CD5: =+AI5*12+24 -> 240 | CE5: =+AJ5*3 -> 210 | CF5: =+CC5+CD5+CE5 -> 610 | CG5: =+BN5*75061/1000 -> 750610 | CH5: =+BO5+BP5+BQ5+BR5+BS5+BT5+BU5+BV5+BW5+BX5+BY5+CA5+CB5 -> 0 | CI5: =+CG5-CF5-CH5 -> 750000 | CR5: =+A5 -> ALCIDES CORREA | CS5: CC-88.193.514 | CT5: =+BN5 -> 10000 | CU5: =+AW5 -> 0 | CW5: =+CV5*230 -> 0 | CX5: 3.6 | CY5: 6.7 | CZ5: =+CX5*6500+CY5*3500 -> 46850 | DB5: =+CT5*75 -> 750000 | DC5: =+CI5 -> 750000 | DD5: =+CI5+CZ5+CW5 -> 796850
A6: ALBA SANABRIA | B6: 0.25 | C6: 0.45 | D6: 12.25 | E6: 0 | F6: 0 | G6: 0 | H6: 0 | I6: 0 | J6: 0 | K6: 0 | L6: 0 | M6: 0 | N6: 0 | O6: 0 | P6: 0 | Q6: 0 | R6: 5 | S6: 9 | T6: 35 | U6: 4 | AH6: 5 | AI6: 9 | AJ6: 35 | AK6: 4 | AX6: =B6+R6-AH6 -> 0.25 | AY6: =C6+S6-AI6 -> 0.45 | AZ6: =D6+T6-AJ6 -> 12.25 | BA6: =E6+U6-AK6 -> 0 | BB6: =F6+V6-AL6 -> 0 | BC6: =G6+W6-AM6 -> 0 | BD6: =H6+X6-AN6 -> 0 | BE6: =I6+Y6-AO6 -> 0 | ... BH6: =L6+AB6-AR6 -> 0 | BI6: =+P6+AF6-AV6 -> 0 | BJ6: =N6+AD6-AT6 -> 0 | BK6: =O6+AE6-AU6 -> 0 | BL6: =P6+AF6-AV6 -> 0 | BM6: =Q6+AG6-AW6 -> 0 | BN6: 5000 | BO6: =+AL6*2500 -> 0 | BP6: =+AM6*60000 -> 0 | BQ6: =+AN6*3000 -> 0 | BR6: =+AO6*6000 -> 0 | BS6: =+AP6*8000 -> 0 | BT6: =+AQ6*8000 -> 0 | BU6: =+AR6*150000 -> 0 | BV6: =+AS6*3000 -> 0 | BW6: =+AT6*25000 -> 0 | BX6: =+AU6*200000 -> 0 | BY6: =+AV6*8000 -> 0 | BZ6: =+AW6*1.5 -> 0 | CC6: =+AH6*16 -> 80 | CD6: =+AI6*12+12 -> 120 | CE6: =+AJ6*3 -> 105 | CF6: =+CC6+CD6+CE6 -> 305 | CG6: =+BN6*75061/1000 -> 375305 | CH6: =+BO6+BP6+BQ6+BR6+BS6+BT6+BU6+BV6+BW6+BX6+BY6+CA6+CB6 -> 0 | CI6: =+CG6-CF6-CH6 -> 375000 | CR6: =+A6 -> ALBA SANABRIA | CS6: V-20.427.079 | CT6: =+BN6 -> 5000 | CU6: =+AW6 -> 0 | CV6: 300 | CW6: =+CV6*230 -> 69000 | CX6: 4.5 | CY6: 2.7 | CZ6: =+CX6*6500+CY6*3500 -> 38700 | DB6: =+CT6*75 -> 375000 | DC6: =+CI6 -> 375000 | DD6: =+CI6+CZ6+CW6 -> 482700
A7: =+'[1]SEMANA DEL 13 AL 20 '!A6 -> BLANCA ALVARADO | B7: 0 | C7: 0 | D7: 0 | E7: 0 | F7: 0 | G7: 0 | H7: 0 | I7: 0 | J7: 0 | K7: 0 | L7: 0 | M7: 0 | N7: 0 | O7: 0 | P7: 0 | Q7: 0 | R7: 0 | S7: 0 | T7: 0 | U7: 0 | AH7: 0 | AI7: 0 | AJ7: 0 | AK7: 0 | AX7: =B7+R7-AH7 -> 0 | AY7: =C7+S7-AI7 -> 0 | AZ7: =D7+T7-AJ7 -> 0 | BA7: =E7+U7-AK7 -> 0 | BB7: =F7+V7-AL7 -> 0 | BC7: =G7+W7-AM7 -> 0 | BD7: =H7+X7-AN7 -> 0 | BE7: =I7+Y7-AO7 -> 0 | ... BH7: =L7+AB7-AR7 -> 0 | BI7: =+P7+AF7-AV7 -> 0 | BJ7: =N7+AD7-AT7 -> 0 | BK7: =O7+AE7-AU7 -> 0 | BL7: =P7+AF7-AV7 -> 0 | BM7: =Q7+AG7-AW7 -> 0 | BN7: 0 | BO7: =+AL7*2500 -> 0 | BP7: =+AM7*60000 -> 0 | BQ7: =+AN7*3000 -> 0 | BR7: =+AO7*6000 -> 0 | BS7: =+AP7*8000 -> 0 | BT7: =+AQ7*8000 -> 0 | BU7: =+AR7*150000 -> 0 | BV7: =+AS7*3000 -> 0 | BW7: =+AT7*25000 -> 0 | BX7: =+AU7*200000 -> 0 | BY7: =+AV7*8000 -> 0 | BZ7: =+AW7*1.5 -> 0 | CC7: =+AH7*16 -> 0 | CD7: =+AI7*12 -> 0 | CE7: =+AJ7*3 -> 0 | CF7: =+CC7+CD7+CE7 -> 0 | CG7: =+BN7*75061/1000 -> 0 | CH7: =+BO7+BP7+BQ7+BR7+BS7+BT7+BU7+BV7+BW7+BX7+BY7+CA7+CB7 -> 0 | CI7: =+CG7-CF7-CH7 -> 0 | CK7: CAPOTE | CL7: =+#REF! -> #REF! | CM7: =+#REF! -> #REF! | CN7: =+CL7+CM7 -> #REF! | CO7: =+#REF! -> #REF! | CP7: =CN7-CO7 -> #REF! | CR7: =+A7 -> BLANCA ALVARADO | CS7: CC.60.402,510 | CT7: =+BN7 -> 0 | CU7: =+AW7 -> 0 | CW7: =+CV7*230 -> 0 | CX7: 0 | CY7: 0 | CZ7: =+CX7*6500+CY7*3500 -> 0 | DB7: =+CT7*75 -> 0 | DC7: =+CI7 -> 0 | DD7: =+CI7+CZ7+CW7 -> 0
A8: =+'[1]SEMANA DEL 13 AL 20 '!A7 -> ESPERANZA REY | B8: 0 | C8: 0 | D8: 0 | E8: 0 | F8: 0 | G8: 0 | H8: 0 | I8: 0 | J8: 0 | K8: 0 | L8: 0 | M8: 0 | N8: 0 | O8: 0 | P8: 0 | Q8: 0 | R8: 3 | S8: 5.4 | T8: 21 | U8: 3 | AH8: 0 | AI8: 0 | AJ8: 0 | AK8: 0 | AX8: =B8+R8-AH8 -> 3 | AY8: =C8+S8-AI8 -> 5.4 | AZ8: =D8+T8-AJ8 -> 21 | BA8: =E8+U8-AK8 -> 3 | BB8: =F8+V8-AL8 -> 0 | BC8: =G8+W8-AM8 -> 0 | BD8: =H8+X8-AN8 -> 0 | BE8: =I8+Y8-AO8 -> 0 | ... BH8: =L8+AB8-AR8 -> 0 | BI8: =+P8+AF8-AV8 -> 0 | BJ8: =N8+AD8-AT8 -> 0 | BK8: =O8+AE8-AU8 -> 0 | BL8: =P8+AF8-AV8 -> 0 | BM8: =Q8+AG8-AW8 -> 0 | BN8: 0 | BO8: =+AL8*2500 -> 0 | BP8: =+AM8*60000 -> 0 | BQ8: =+AN8*3000 -> 0 | BR8: =+AO8*6000 -> 0 | BS8: =+AP8*8000 -> 0 | BT8: =+AQ8*8000 -> 0 | BU8: =+AR8*150000 -> 0 | BV8: =+AS8*3000 -> 0 | BW8: =+AT8*25000 -> 0 | BX8: =+AU8*200000 -> 0 | BY8: =+AV8*8000 -> 0 | BZ8: =+AW8*1.5 -> 0 | CC8: =+AH8*16 -> 0 | CD8: =+AI8*12 -> 0 | CE8: =+AJ8*3 -> 0 | CF8: =+CC8+CD8+CE8 -> 0 | CG8: =+BN8*75061/1000 -> 0 | CH8: =+BO8+BP8+BQ8+BR8+BS8+BT8+BU8+BV8+BW8+BX8+BY8+CA8+CB8 -> 0 | CI8: =+CG8-CF8-CH8 -> 0 | CR8: =+A8 -> ESPERANZA REY | CS8: V-22.633.248 | CT8: =+BN8 -> 0 | CU8: =+AW8 -> 0 | CW8: =+CV8*230 -> 0 | CX8: 0 | CY8: 0 | CZ8: =+CX8*6500+CY8*3500 -> 0 | DB8: =+CT8*75 -> 0 | DC8: =+CI8 -> 0 | DD8: =+CI8+CZ8+CW8 -> 0
A9: =+'[1]SEMANA DEL 13 AL 20 '!A8 -> ELIZABETH REYES SERRANO | B9: 0 | C9: 0 | D9: 0 | E9: 0 | F9: 0 | G9: 0 | H9: 0 | I9: 0 | J9: 0 | K9: 0 | L9: 0 | M9: 0 | N9: 0 | O9: 0 | P9: 0 | Q9: 0 | R9: 7 | S9: 12.6 | T9: 49 | U9: 6 | AH9: 7 | AI9: 12.6 | AJ9: 49 | AK9: 6 | AX9: =B9+R9-AH9 -> 0 | AY9: =C9+S9-AI9 -> 0 | AZ9: =D9+T9-AJ9 -> 0 | BA9: =E9+U9-AK9 -> 0 | BB9: =F9+V9-AL9 -> 0 | BC9: =G9+W9-AM9 -> 0 | BD9: =H9+X9-AN9 -> 0 | BE9: =I9+Y9-AO9 -> 0 | ... BH9: =L9+AB9-AR9 -> 0 | BI9: =+P9+AF9-AV9 -> 0 | BJ9: =N9+AD9-AT9 -> 0 | BK9: =O9+AE9-AU9 -> 0 | BL9: =P9+AF9-AV9 -> 0 | BM9: =Q9+AG9-AW9 -> 0 | BN9: 7000 | BO9: =+AL9*2500 -> 0 | BP9: =+AM9*60000 -> 0 | BQ9: =+AN9*3000 -> 0 | BR9: =+AO9*6000 -> 0 | BS9: =+AP9*8000 -> 0 | BT9: =+AQ9*8000 -> 0 | BU9: =+AR9*150000 -> 0 | BV9: =+AS9*3000 -> 0 | BW9: =+AT9*25000 -> 0 | BX9: =+AU9*200000 -> 0 | BY9: =+AV9*8000 -> 0 | BZ9: =+AW9*1.5 -> 0 | CA9: 50000 | CC9: =+AH9*16 -> 112 | CD9: =+AI9*12+16.8 -> 168 | CE9: =+AJ9*3 -> 147 | CF9: =+CC9+CD9+CE9 -> 427 | CG9: =+BN9*75061/1000 -> 525427 | CH9: =+BO9+BP9+BQ9+BR9+BS9+BT9+BU9+BV9+BW9+BX9+BY9+CA9+CB9 -> 50000 | CI9: =+CG9-CF9-CH9 -> 475000 | CR9: =+A9 -> ELIZABETH REYES SERRANO | CS9: V-15.956.387 | CT9: =+BN9 -> 7000 | CU9: =+AW9 -> 0 | CW9: =+CV9*230 -> 0 | CX9: 3 | CY9: 6.2 | CZ9: =+CX9*6500+CY9*3500 -> 41200 | DB9: =+CT9*75 -> 525000 | DC9: =+CI9 -> 475000 | DD9: =+CI9+CZ9+CW9 -> 516200
A10: =+'[1]SEMANA DEL 13 AL 20 '!A9 -> ELVIRA LOPEZ | B10: 0 | C10: 0 | D10: 0 | E10: 0 | F10: 0 | G10: 0 | H10: 0 | I10: 0 | J10: 0 | K10: 0 | L10: 0 | M10: 0 | N10: 0 | O10: 0 | P10: 0 | Q10: 0 | R10: 12 | S10: 21.6 | T10: 84 | U10: 10 | AH10: 12 | AI10: 21.6 | AJ10: 84 | AK10: 10 | AX10: =B10+R10-AH10 -> 0 | AY10: =C10+S10-AI10 -> 0 | AZ10: =D10+T10-AJ10 -> 0 | BA10: =E10+U10-AK10 -> 0 | BB10: =F10+V10-AL10 -> 0 | BC10: =G10+W10-AM10 -> 0 | BD10: =H10+X10-AN10 -> 0 | BE10: =I10+Y10-AO10 -> 0 | ... BH10: =L10+AB10-AR10 -> 0 | BI10: =+P10+AF10-AV10 -> 0 | BJ10: =N10+AD10-AT10 -> 0 | BK10: =O10+AE10-AU10 -> 0 | BL10: =P10+AF10-AV10 -> 0 | BM10: =Q10+AG10-AW10 -> 0 | BN10: 12000 | BO10: =+AL10*2500 -> 0 | BP10: =+AM10*60000 -> 0 | BQ10: =+AN10*3000 -> 0 | BR10: =+AO10*6000 -> 0 | BS10: =+AP10*8000 -> 0 | BT10: =+AQ10*8000 -> 0 | BU10: =+AR10*150000 -> 0 | BV10: =+AS10*3000 -> 0 | BW10: =+AT10*25000 -> 0 | BX10: =+AU10*200000 -> 0 | BY10: =+AV10*8000 -> 0 | BZ10: =+AW10*1.5 -> 0 | CC10: =+AH10*16 -> 192 | CD10: =+AI10*12+28.8 -> 288 | CE10: =+AJ10*3 -> 252 | CF10: =+CC10+CD10+CE10 -> 732 | CG10: =+BN10*75061/1000 -> 900732 | CH10: =+BO10+BP10+BQ10+BR10+BS10+BT10+BU10+BV10+BW10+BX10+BY10+CA10+CB10 -> 0 | CI10: =+CG10-CF10-CH10 -> 900000 | CR10: =+A10 -> ELVIRA LOPEZ | CS10: V-29,664.726 | CT10: =+BN10 -> 12000 | CU10: =+AW10 -> 0 | CV10: 750 | CW10: =+CV10*230 -> 172500 | CX10: 4.3 | CY10: 9.8 | CZ10: =+CX10*6500+CY10*3500 -> 62250 | DB10: =+CT10*75 -> 900000 | DC10: =+CI10 -> 900000 | DD10: =+CI10+CZ10+CW10 -> 1134750
A11: =+'[1]SEMANA DEL 13 AL 20 '!A10 -> ERNESTO REYES | B11: 0.2 | C11: 0.36 | D11: 1.4 | E11: 0 | F11: 0 | G11: 0 | H11: 0 | I11: 0 | J11: 0 | K11: 0 | L11: 0 | M11: 0 | N11: 0 | O11: 0 | P11: 0 | Q11: 0 | R11: 3 | S11: 5.4 | T11: 21 | U11: 3 | AH11: 3 | AI11: 5.4 | AJ11: 21 | AK11: 3 | AX11: =B11+R11-AH11 -> 0.2 | AY11: =C11+S11-AI11 -> 0.36 | AZ11: =D11+T11-AJ11 -> 1.4 | BA11: =E11+U11-AK11 -> 0 | BB11: =F11+V11-AL11 -> 0 | BC11: =G11+W11-AM11 -> 0 | BD11: =H11+X11-AN11 -> 0 | BE11: =I11+Y11-AO11 -> 0 | ... BH11: =L11+AB11-AR11 -> 0 | BI11: =+P11+AF11-AV11 -> 0 | BJ11: =N11+AD11-AT11 -> 0 | BK11: =O11+AE11-AU11 -> 0 | BL11: =P11+AF11-AV11 -> 0 | BM11: =Q11+AG11-AW11 -> 0 | BN11: 3000 | BO11: =+AL11*2500 -> 0 | BP11: =+AM11*60000 -> 0 | BQ11: =+AN11*3000 -> 0 | BR11: =+AO11*6000 -> 0 | BS11: =+AP11*8000 -> 0 | BT11: =+AQ11*8000 -> 0 | BU11: =+AR11*150000 -> 0 | BV11: =+AS11*3000 -> 0 | BW11: =+AT11*25000 -> 0 | BX11: =+AU11*200000 -> 0 | BY11: =+AV11*8000 -> 0 | BZ11: =+AW11*1.5 -> 0 | CC11: =+AH11*16 -> 48 | CD11: =+AI11*12+7.2 -> 72 | CE11: =+AJ11*3 -> 63 | CF11: =+CC11+CD11+CE11 -> 183 | CG11: =+BN11*75061/1000 -> 225183 | CH11: =+BO11+BP11+BQ11+BR11+BS11+BT11+BU11+BV11+BW11+BX11+BY11+CA11+CB11 -> 0 | CI11: =+CG11-CF11-CH11 -> 225000 | CR11: =+A11 -> ERNESTO REYES | CS11: CC-5.535.335 | CT11: =+BN11 -> 3000 | CU11: =+AW11 -> 0 | CW11: =+CV11*230 -> 0 | CX11: 2.3 | CY11: 2.9 | CZ11: =+CX11*6500+CY11*3500 -> 25100 | DB11: =+CT11*75 -> 225000 | DC11: =+CI11 -> 225000 | DD11: =+CI11+CZ11+CW11 -> 250100
A12: =+'[1]SEMANA DEL 13 AL 20 '!A11 -> GUILLERMO ZAMBRANO | B12: 0.35 | C12: 1.63 | D12: 4.45 | E12: 0 | F12: 0 | G12: 0 | H12: 0 | I12: 0 | J12: 0 | K12: 0 | L12: 0 | M12: 0 | N12: 0 | O12: 0 | P12: 0 | Q12: 0 | R12: 0 | S12: 0 | T12: 0 | U12: 0 | AH12: 0 | AI12: 0 | AJ12: 0 | AK12: 0 | AX12: =B12+R12-AH12 -> 0.35 | AY12: =C12+S12-AI12 -> 1.63 | AZ12: =D12+T12-AJ12 -> 4.45 | BA12: =E12+U12-AK12 -> 0 | BB12: =F12+V12-AL12 -> 0 | BC12: =G12+W12-AM12 -> 0 | BD12: =H12+X12-AN12 -> 0 | BE12: =I12+Y12-AO12 -> 0 | ... BH12: =L12+AB12-AR12 -> 0 | BI12: =+P12+AF12-AV12 -> 0 | BJ12: =N12+AD12-AT12 -> 0 | BK12: =O12+AE12-AU12 -> 0 | BL12: =P12+AF12-AV12 -> 0 | BM12: =Q12+AG12-AW12 -> 0 | BN12: 0 | BO12: =+AL12*2500 -> 0 | BP12: =+AM12*60000 -> 0 | BQ12: =+AN12*3000 -> 0 | BR12: =+AO12*6000 -> 0 | BS12: =+AP12*8000 -> 0 | BT12: =+AQ12*8000 -> 0 | BU12: =+AR12*150000 -> 0 | BV12: =+AS12*3000 -> 0 | BW12: =+AT12*25000 -> 0 | BX12: =+AU12*200000 -> 0 | BY12: =+AV12*8000 -> 0 | BZ12: =+AW12*1.5 -> 0 | CC12: =+AH12*16 -> 0 | CD12: =+AI12*12 -> 0 | CE12: =+AJ12*3 -> 0 | CF12: =+CC12+CD12+CE12 -> 0 | CG12: =+BN12*75061/1000 -> 0 | CH12: =+BO12+BP12+BQ12+BR12+BS12+BT12+BU12+BV12+BW12+BX12+BY12+CA12+CB12 -> 0 | CI12: =+CG12-CF12-CH12 -> 0 | CR12: =+A12 -> GUILLERMO ZAMBRANO | CS12: V-5.642.663 | CT12: =+BN12 -> 0 | CU12: =+AW12 -> 0 | CW12: =+CV12*230 -> 0 | CX12: 0 | CY12: 0 | CZ12: =+CX12*6500+CY12*3500 -> 0 | DB12: =+CT12*75 -> 0 | DC12: =+CI12 -> 0 | DD12: =+CI12+CZ12+CW12 -> 0
A13: =+'[1]SEMANA DEL 13 AL 20 '!A13 -> HUGO ALMEIDA | B13: 0 | C13: 0 | D13: 0 | E13: 0 | F13: 0 | G13: 0 | H13: 0 | I13: 0 | J13: 0 | K13: 0 | L13: 0 | M13: 0 | N13: 0 | O13: 0 | P13: 0 | Q13: 0 | R13: 5 | S13: 9 | T13: 35 | U13: 4 | AH13: 5 | AI13: 9 | AJ13: 35 | AK13: 4 | AX13: =B13+R13-AH13 -> 0 | AY13: =C13+S13-AI13 -> 0 | AZ13: =D13+T13-AJ13 -> 0 | BA13: =E13+U13-AK13 -> 0 | BB13: =F13+V13-AL13 -> 0 | BC13: =G13+W13-AM13 -> 0 | BD13: =H13+X13-AN13 -> 0 | BE13: =I13+Y13-AO13 -> 0 | ... BH13: =L13+AB13-AR13 -> 0 | BI13: =+P13+AF13-AV13 -> 0 | BJ13: =N13+AD13-AT13 -> 0 | BK13: =O13+AE13-AU13 -> 0 | BL13: =P13+AF13-AV13 -> 0 | BM13: =Q13+AG13-AW13 -> 0 | BN13: 5000 | BO13: =+AL13*2500 -> 0 | BP13: =+AM13*60000 -> 0 | BQ13: =+AN13*3000 -> 0 | BR13: =+AO13*6000 -> 0 | BS13: =+AP13*8000 -> 0 | BT13: =+AQ13*8000 -> 0 | BU13: =+AR13*150000 -> 0 | BV13: =+AS13*3000 -> 0 | BW13: =+AT13*25000 -> 0 | BX13: =+AU13*200000 -> 0 | BY13: =+AV13*8000 -> 0 | BZ13: =+AW13*1.5 -> 0 | CC13: =+AH13*16 -> 80 | CD13: =+AI13*12+12 -> 120 | CE13: =+AJ13*3 -> 105 | CF13: =+CC13+CD13+CE13 -> 305 | CG13: =+BN13*75061/1000 -> 375305 | CH13: =+BO13+BP13+BQ13+BR13+BS13+BT13+BU13+BV13+BW13+BX13+BY13+CA13+CB13 -> 0 | CI13: =+CG13-CF13-CH13 -> 375000 | CR13: =+A13 -> HUGO ALMEIDA | CS13: V-8,988,550 | CT13: =+BN13 -> 5000 | CU13: =+AW13 -> 0 | CW13: =+CV13*230 -> 0 | CX13: 4 | CY13: 3.1 | CZ13: =+CX13*6500+CY13*3500 -> 36850 | DB13: =+CT13*75 -> 375000 | DC13: =+CI13 -> 375000 | DD13: =+CI13+CZ13+CW13 -> 411850
A14: =+'[1]SEMANA DEL 13 AL 20 '!A14 -> HILDA SERRANO | B14: 1 | C14: 1.8 | D14: 7 | E14: 0 | F14: 0 | G14: 0 | H14: 0 | I14: 0 | J14: 0 | K14: 0 | L14: 0 | M14: 0 | N14: 0 | O14: 0 | P14: 0 | Q14: 0 | R14: 7 | S14: 12.6 | T14: 49 | U14: 7 | AH14: 7 | AI14: 12.6 | AJ14: 49 | AK14: 6 | AX14: =B14+R14-AH14 -> 1 | AY14: =C14+S14-AI14 -> 1.8 | AZ14: =D14+T14-AJ14 -> 7 | BA14: =E14+U14-AK14 -> 1 | BB14: =F14+V14-AL14 -> 0 | BC14: =G14+W14-AM14 -> 0 | BD14: =H14+X14-AN14 -> 0 | BE14: =I14+Y14-AO14 -> 0 | ... BH14: =L14+AB14-AR14 -> 0 | BI14: =+P14+AF14-AV14 -> 0 | BJ14: =N14+AD14-AT14 -> 0 | BK14: =O14+AE14-AU14 -> 0 | BL14: =P14+AF14-AV14 -> 0 | BM14: =Q14+AG14-AW14 -> 0 | BN14: 7000 | BO14: =+AL14*2500 -> 0 | BP14: =+AM14*60000 -> 0 | BQ14: =+AN14*3000 -> 0 | BR14: =+AO14*6000 -> 0 | BS14: =+AP14*8000 -> 0 | BT14: =+AQ14*8000 -> 0 | BU14: =+AR14*150000 -> 0 | BV14: =+AS14*3000 -> 0 | BW14: =+AT14*25000 -> 0 | BX14: =+AU14*200000 -> 0 | BY14: =+AV14*8000 -> 0 | BZ14: =+AW14*1.5 -> 0 | CA14: 20000 | CC14: =+AH14*16 -> 112 | CD14: =+AI14*12+16.8 -> 168 | CE14: =+AJ14*3 -> 147 | CF14: =+CC14+CD14+CE14 -> 427 | CG14: =+BN14*75061/1000 -> 525427 | CH14: =+BO14+BP14+BQ14+BR14+BS14+BT14+BU14+BV14+BW14+BX14+BY14+CA14+CB14 -> 20000 | CI14: =+CG14-CF14-CH14 -> 505000 | CR14: =+A14 -> HILDA SERRANO | CS14: CC-60.413.802 | CT14: =+BN14 -> 7000 | CU14: =+AW14 -> 0 | CW14: =+CV14*230 -> 0 | CX14: 4.9 | CY14: 4.3 | CZ14: =+CX14*6500+CY14*3500 -> 46900 | DB14: =+CT14*75 -> 525000 | DC14: =+CI14 -> 505000 | DD14: =+CI14+CZ14+CW14 -> 551900
A15: =+'[1]SEMANA DEL 13 AL 20 '!A15 -> HUMBERTO LUNA | B15: 0 | C15: 0 | D15: 0 | E15: 0 | F15: 0 | G15: 0 | H15: 0 | I15: 0 | J15: 0 | K15: 0 | L15: 0 | M15: 0 | N15: 0 | O15: 0 | P15: 0 | Q15: 0 | R15: 10 | S15: 18 | T15: 70 | U15: 8 | AH15: 10 | AI15: 18 | AJ15: 70 | AK15: 8 | AX15: =B15+R15-AH15 -> 0 | AY15: =C15+S15-AI15 -> 0 | AZ15: =D15+T15-AJ15 -> 0 | BA15: =E15+U15-AK15 -> 0 | BB15: =F15+V15-AL15 -> 0 | BC15: =G15+W15-AM15 -> 0 | BD15: =H15+X15-AN15 -> 0 | BE15: =I15+Y15-AO15 -> 0 | ... BH15: =L15+AB15-AR15 -> 0 | BI15: =+P15+AF15-AV15 -> 0 | BJ15: =N15+AD15-AT15 -> 0 | BK15: =O15+AE15-AU15 -> 0 | BL15: =P15+AF15-AV15 -> 0 | BM15: =Q15+AG15-AW15 -> 0 | BN15: 10000 | BO15: =+AL15*2500 -> 0 | BP15: =+AM15*60000 -> 0 | BQ15: =+AN15*3000 -> 0 | BR15: =+AO15*6000 -> 0 | BS15: =+AP15*8000 -> 0 | BT15: =+AQ15*8000 -> 0 | BU15: =+AR15*150000 -> 0 | BV15: =+AS15*3000 -> 0 | BW15: =+AT15*25000 -> 0 | BX15: =+AU15*200000 -> 0 | BY15: =+AV15*8000 -> 0 | BZ15: =+AW15*1.5 -> 0 | CC15: =+AH15*16 -> 160 | CD15: =+AI15*12+24 -> 240 | CE15: =+AJ15*3 -> 210 | CF15: =+CC15+CD15+CE15 -> 610 | CG15: =+BN15*75061/1000 -> 750610 | CH15: =+BO15+BP15+BQ15+BR15+BS15+BT15+BU15+BV15+BW15+BX15+BY15+CA15+CB15 -> 0 | CI15: =+CG15-CF15-CH15 -> 750000 | CR15: =+A15 -> HUMBERTO LUNA | CS15: V-25.344.223 | CT15: =+BN15 -> 10000 | CU15: =+AW15 -> 0 | CV15: 600 | CW15: =+CV15*230 -> 138000 | CX15: 3.8 | CY15: 7.8 | CZ15: =+CX15*6500+CY15*3500 -> 52000 | DB15: =+CT15*75 -> 750000 | DC15: =+CI15 -> 750000 | DD15: =+CI15+CZ15+CW15 -> 940000
A16: =+'[1]SEMANA DEL 13 AL 20 '!A16 -> JOSE EBLAN GIRON | B16: 0.2 | C16: 0.36 | D16: 1.4 | E16: 1 | F16: 0 | G16: 0 | H16: 0 | I16: 1 | J16: 0 | K16: 0 | L16: 0 | M16: 0 | N16: 0 | O16: 0 | P16: 0 | Q16: 0 | R16: 5 | S16: 9 | T16: 35 | U16: 4 | AH16: 4 | AI16: 7.2 | AJ16: 28 | AK16: 3 | AX16: =B16+R16-AH16 -> 1.2 | AY16: =C16+S16-AI16 -> 2.16 | AZ16: =D16+T16-AJ16 -> 8.4 | BA16: =E16+U16-AK16 -> 2 | BB16: =F16+V16-AL16 -> 0 | BC16: =G16+W16-AM16 -> 0 | BD16: =H16+X16-AN16 -> 0 | BE16: =I16+Y16-AO16 -> 1 | ... BH16: =L16+AB16-AR16 -> 0 | BI16: =+P16+AF16-AV16 -> 0 | BJ16: =N16+AD16-AT16 -> 0 | BK16: =O16+AE16-AU16 -> 0 | BL16: =P16+AF16-AV16 -> 0 | BM16: =Q16+AG16-AW16 -> 0 | BN16: 4000 | BO16: =+AL16*2500 -> 0 | BP16: =+AM16*60000 -> 0 | BQ16: =+AN16*3000 -> 0 | BR16: =+AO16*6000 -> 0 | BS16: =+AP16*8000 -> 0 | BT16: =+AQ16*8000 -> 0 | BU16: =+AR16*150000 -> 0 | BV16: =+AS16*3000 -> 0 | BW16: =+AT16*25000 -> 0 | BX16: =+AU16*200000 -> 0 | BY16: =+AV16*8000 -> 0 | BZ16: =+AW16*1.5 -> 0 | CC16: =+AH16*16 -> 64 | CD16: =+AI16*12+9.6 -> 96 | CE16: =+AJ16*3 -> 84 | CF16: =+CC16+CD16+CE16 -> 244 | CG16: =+BN16*75061/1000 -> 300244 | CH16: =+BO16+BP16+BQ16+BR16+BS16+BT16+BU16+BV16+BW16+BX16+BY16+CA16+CB16 -> 0 | CI16: =+CG16-CF16-CH16 -> 300000 | CK16: GOMA | CL16: =+#REF! -> #REF! | CM16: =+#REF! -> #REF! | CN16: =+CL16+CM16 -> #REF! | CO16: =+#REF! -> #REF! | CP16: =CN16-CO16 -> #REF! | CR16: =+A16 -> JOSE EBLAN GIRON | CS16: V-9.130.173 | CT16: =+BN16 -> 4000 | CU16: =+AW16 -> 0 | CW16: =+CV16*230 -> 0 | CX16: 2.9 | CY16: 3.4 | CZ16: =+CX16*6500+CY16*3500 -> 30750 | DB16: =+CT16*75 -> 300000 | DC16: =+CI16 -> 300000 | DD16: =+CI16+CZ16+CW16 -> 330750
A17: =+'[1]SEMANA DEL 13 AL 20 '!A17 -> JOSE JURADO | B17: 0 | C17: 0 | D17: 0 | E17: 0 | F17: 0 | G17: 0 | H17: 0 | I17: 0 | J17: 0 | K17: 0 | L17: 0 | M17: 0 | N17: 0 | O17: 0 | P17: 0 | Q17: 0 | R17: 5 | S17: 9 | T17: 35 | U17: 4 | W17: 0.25 | AH17: 5 | AI17: 9 | AJ17: 35 | AK17: 4 | AM17: 0.25 | AX17: =B17+R17-AH17 -> 0 | AY17: =C17+S17-AI17 -> 0 | AZ17: =D17+T17-AJ17 -> 0 | BA17: =E17+U17-AK17 -> 0 | BB17: =F17+V17-AL17 -> 0 | BC17: =G17+W17-AM17 -> 0 | BD17: =H17+X17-AN17 -> 0 | BE17: =I17+Y17-AO17 -> 0 | ... BH17: =L17+AB17-AR17 -> 0 | BI17: =+P17+AF17-AV17 -> 0 | BJ17: =N17+AD17-AT17 -> 0 | BK17: =O17+AE17-AU17 -> 0 | BL17: =P17+AF17-AV17 -> 0 | BM17: =Q17+AG17-AW17 -> 0 | BN17: 5000 | BO17: =+AL17*2500 -> 0 | BP17: =+AM17*60000 -> 15000 | BQ17: =+AN17*3000 -> 0 | BR17: =+AO17*6000 -> 0 | BS17: =+AP17*8000 -> 0 | BT17: =+AQ17*8000 -> 0 | BU17: =+AR17*150000 -> 0 | BV17: =+AS17*3000 -> 0 | BW17: =+AT17*25000 -> 0 | BX17: =+AU17*200000 -> 0 | BY17: =+AV17*8000 -> 0 | BZ17: =+AW17*1.5 -> 0 | CC17: =+AH17*16 -> 80 | CD17: =+AI17*12+12 -> 120 | CE17: =+AJ17*3 -> 105 | CF17: =+CC17+CD17+CE17 -> 305 | CG17: =+BN17*75061/1000 -> 375305 | CH17: =+BO17+BP17+BQ17+BR17+BS17+BT17+BU17+BV17+BW17+BX17+BY17+CA17+CB17 -> 15000 | CI17: =+CG17-CF17-CH17 -> 360000 | CR17: =+A17 -> JOSE JURADO | CS17: V-8.986.394 | CT17: =+BN17 -> 5000 | CU17: =+AW17 -> 0 | CW17: =+CV17*230 -> 0 | CX17: 2.1 | CY17: 4.3 | CZ17: =+CX17*6500+CY17*3500 -> 28700 | DB17: =+CT17*75 -> 375000 | DC17: =+CI17 -> 360000 | DD17: =+CI17+CZ17+CW17 -> 388700
A18: =+'[1]SEMANA DEL 13 AL 20 '!A18 -> KARINA SILVA | B18: 0.35 | C18: 0.63 | D18: 9.8 | E18: 0 | F18: 0 | G18: 0 | H18: 0 | I18: 0 | J18: 0 | K18: 0 | L18: 0 | M18: 0 | N18: 0 | O18: 0 | P18: 0 | Q18: 0 | R18: 5 | S18: 9 | T18: 35 | U18: 4 | AH18: 5.05 | AI18: 9.09 | AJ18: 35.35 | AK18: 4 | AX18: =B18+R18-AH18 -> 0.3 | AY18: =C18+S18-AI18 -> 0.54 | AZ18: =D18+T18-AJ18 -> 9.45 | BA18: =E18+U18-AK18 -> 0 | BB18: =F18+V18-AL18 -> 0 | BC18: =G18+W18-AM18 -> 0 | BD18: =H18+X18-AN18 -> 0 | BE18: =I18+Y18-AO18 -> 0 | ... BH18: =L18+AB18-AR18 -> 0 | BI18: =+P18+AF18-AV18 -> 0 | BJ18: =N18+AD18-AT18 -> 0 | BK18: =O18+AE18-AU18 -> 0 | BL18: =P18+AF18-AV18 -> 0 | BM18: =Q18+AG18-AW18 -> 0 | BN18: 5050 | BO18: =+AL18*2500 -> 0 | BP18: =+AM18*60000 -> 0 | BQ18: =+AN18*3000 -> 0 | BR18: =+AO18*6000 -> 0 | BS18: =+AP18*8000 -> 0 | BT18: =+AQ18*8000 -> 0 | BU18: =+AR18*150000 -> 0 | BV18: =+AS18*3000 -> 0 | BW18: =+AT18*25000 -> 0 | BX18: =+AU18*200000 -> 0 | BY18: =+AV18*8000 -> 0 | BZ18: =+AW18*1.5 -> 0 | CC18: =+AH18*16 -> 80.8 | CD18: =+AI18*12+12.12 -> 121.2 | CE18: =+AJ18*3 -> 106.05 | CF18: =+CC18+CD18+CE18 -> 308.05 | CG18: =+BN18*75061/1000 -> 379058.05 | CH18: =+BO18+BP18+BQ18+BR18+BS18+BT18+BU18+BV18+BW18+BX18+BY18+CA18+CB18 -> 0 | CI18: =+CG18-CF18-CH18 -> 378750 | CR18: =+A18 -> KARINA SILVA | CS18: V-17.465.799 | CT18: =+BN18 -> 5050 | CU18: =+AW18 -> 0 | CW18: =+CV18*230 -> 0 | CX18: 5.7 | CY18: 4.8 | CZ18: =+CX18*6500+CY18*3500 -> 53850 | DB18: =+CT18*75 -> 378750 | DC18: =+CI18 -> 378750 | DD18: =+CI18+CZ18+CW18 -> 432600
A19: =+'[1]SEMANA DEL 13 AL 20 '!A19 -> LUZ MERY ABAUNZA | B19: 0 | C19: 0 | D19: 0 | E19: 0 | F19: 0 | G19: 0 | H19: 0 | I19: 0 | J19: 0 | K19: 0 | L19: 0 | M19: 0 | N19: 0 | O19: 0 | P19: 0 | Q19: 0 | R19: 5 | S19: 9 | T19: 35 | U19: 4 | AH19: 5 | AI19: 9 | AJ19: 35 | AK19: 4 | AX19: =B19+R19-AH19 -> 0 | AY19: =C19+S19-AI19 -> 0 | AZ19: =D19+T19-AJ19 -> 0 | BA19: =E19+U19-AK19 -> 0 | BB19: =F19+V19-AL19 -> 0 | BC19: =G19+W19-AM19 -> 0 | BD19: =H19+X19-AN19 -> 0 | BE19: =I19+Y19-AO19 -> 0 | ... BH19: =L19+AB19-AR19 -> 0 | BI19: =+P19+AF19-AV19 -> 0 | BJ19: =N19+AD19-AT19 -> 0 | BK19: =O19+AE19-AU19 -> 0 | BL19: =P19+AF19-AV19 -> 0 | BM19: =Q19+AG19-AW19 -> 0 | BN19: 5000 | BO19: =+AL19*2500 -> 0 | BP19: =+AM19*60000 -> 0 | BQ19: =+AN19*3000 -> 0 | BR19: =+AO19*6000 -> 0 | BS19: =+AP19*8000 -> 0 | BT19: =+AQ19*8000 -> 0 | BU19: =+AR19*150000 -> 0 | BV19: =+AS19*3000 -> 0 | BW19: =+AT19*25000 -> 0 | BX19: =+AU19*200000 -> 0 | BY19: =+AV19*8000 -> 0 | BZ19: =+AW19*1.5 -> 0 | CA19: 50000 | CC19: =+AH19*16 -> 80 | CD19: =+AI19*12+12 -> 120 | CE19: =+AJ19*3 -> 105 | CF19: =+CC19+CD19+CE19 -> 305 | CG19: =+BN19*75061/1000 -> 375305 | CH19: =+BO19+BP19+BQ19+BR19+BS19+BT19+BU19+BV19+BW19+BX19+BY19+CA19+CB19 -> 50000 | CI19: =+CG19-CF19-CH19 -> 325000 | CR19: =+A19 -> LUZ MERY ABAUNZA | CS19: CC-60.407.054 | CT19: =+BN19 -> 5000 | CU19: =+AW19 -> 0 | CW19: =+CV19*230 -> 0 | CX19: 0 | CY19: 4.1 | CZ19: =+CX19*6500+CY19*3500 -> 14350 | DB19: =+CT19*75 -> 375000 | DC19: =+CI19 -> 325000 | DD19: =+CI19+CZ19+CW19 -> 339350
A20: =+'[1]SEMANA DEL 13 AL 20 '!A20 -> LUIS ROJAS | B20: 0 | C20: 0 | D20: 0 | E20: 0 | F20: 0 | G20: 0 | H20: 0 | I20: 0 | J20: 0 | K20: 0 | L20: 0 | M20: 0 | N20: 0 | O20: 0 | P20: 0 | Q20: 0 | R20: 0 | S20: 0 | T20: 0 | U20: 0 | AH20: 0 | AI20: 0 | AJ20: 0 | AK20: 0 | AX20: =B20+R20-AH20 -> 0 | AY20: =C20+S20-AI20 -> 0 | AZ20: =D20+T20-AJ20 -> 0 | BA20: =E20+U20-AK20 -> 0 | BB20: =F20+V20-AL20 -> 0 | BC20: =G20+W20-AM20 -> 0 | BD20: =H20+X20-AN20 -> 0 | BE20: =I20+Y20-AO20 -> 0 | ... BH20: =L20+AB20-AR20 -> 0 | BI20: =+P20+AF20-AV20 -> 0 | BJ20: =N20+AD20-AT20 -> 0 | BK20: =O20+AE20-AU20 -> 0 | BL20: =P20+AF20-AV20 -> 0 | BM20: =Q20+AG20-AW20 -> 0 | BN20: 0 | BO20: =+AL20*2500 -> 0 | BP20: =+AM20*60000 -> 0 | BQ20: =+AN20*3000 -> 0 | BR20: =+AO20*6000 -> 0 | BS20: =+AP20*8000 -> 0 | BT20: =+AQ20*8000 -> 0 | BU20: =+AR20*150000 -> 0 | BV20: =+AS20*3000 -> 0 | BW20: =+AT20*25000 -> 0 | BX20: =+AU20*200000 -> 0 | BY20: =+AV20*8000 -> 0 | BZ20: =+AW20*1.5 -> 0 | CC20: =+AH20*16 -> 0 | CD20: =+AI20*12 -> 0 | CE20: =+AJ20*3 -> 0 | CF20: =+CC20+CD20+CE20 -> 0 | CG20: =+BN20*75061/1000 -> 0 | CH20: =+BO20+BP20+BQ20+BR20+BS20+BT20+BU20+BV20+BW20+BX20+BY20+CA20+CB20 -> 0 | CI20: =+CG20-CF20-CH20 -> 0 | CK20: PAPEL | CL20: =+#REF! -> #REF! | CM20: =+#REF! -> #REF! | CN20: =+CL20+CM20 -> #REF! | CO20: =+#REF! -> #REF! | CP20: =CN20-CO20 -> #REF! | CR20: =+A20 -> LUIS ROJAS | CS20: CC.79.336.610 | CT20: =+BN20 -> 0 | CU20: =+AW20 -> 0 | CW20: =+CV20*230 -> 0 | CZ20: =+CX20*6500+CY20*3500 -> 0 | DB20: =+CT20*75 -> 0 | DC20: =+CI20 -> 0 | DD20: =+CI20+CZ20+CW20 -> 0
A21: =+'[1]SEMANA DEL 13 AL 20 '!A21 -> LUIS VALDERRAMA | B21: 0 | C21: 0 | D21: 0 | E21: 0 | F21: 0 | G21: 0 | H21: 0 | I21: 0 | J21: 0 | K21: 0 | L21: 0 | M21: 0 | N21: 0 | O21: 0 | P21: 0 | Q21: 0 | R21: 15 | S21: 27 | T21: 105 | U21: 12 | AH21: 15 | AI21: 27 | AJ21: 105 | AK21: 12 | AX21: =B21+R21-AH21 -> 0 | AY21: =C21+S21-AI21 -> 0 | AZ21: =D21+T21-AJ21 -> 0 | BA21: =E21+U21-AK21 -> 0 | BB21: =F21+V21-AL21 -> 0 | BC21: =G21+W21-AM21 -> 0 | BD21: =H21+X21-AN21 -> 0 | BE21: =I21+Y21-AO21 -> 0 | ... BH21: =L21+AB21-AR21 -> 0 | BI21: =+P21+AF21-AV21 -> 0 | BJ21: =N21+AD21-AT21 -> 0 | BK21: =O21+AE21-AU21 -> 0 | BL21: =P21+AF21-AV21 -> 0 | BM21: =Q21+AG21-AW21 -> 0 | BN21: 15000 | BO21: =+AL21*2500 -> 0 | BP21: =+AM21*60000 -> 0 | BQ21: =+AN21*3000 -> 0 | BR21: =+AO21*6000 -> 0 | BS21: =+AP21*8000 -> 0 | BT21: =+AQ21*8000 -> 0 | BU21: =+AR21*150000 -> 0 | BV21: =+AS21*3000 -> 0 | BW21: =+AT21*25000 -> 0 | BX21: =+AU21*200000 -> 0 | BY21: =+AV21*8000 -> 0 | BZ21: =+AW21*1.5 -> 0 | CC21: =+AH21*16 -> 240 | CD21: =+AI21*12+36 -> 360 | CE21: =+AJ21*3 -> 315 | CF21: =+CC21+CD21+CE21 -> 915 | CG21: =+BN21*75061/1000 -> 1125915 | CH21: =+BO21+BP21+BQ21+BR21+BS21+BT21+BU21+BV21+BW21+BX21+BY21+CA21+CB21 -> 0 | CI21: =+CG21-CF21-CH21 -> 1125000 | CK21: RESORTES | CL21: =+#REF! -> #REF! | CM21: =+#REF! -> #REF! | CN21: =+CL21+CM21 -> #REF! | CO21: =+#REF! -> #REF! | CP21: =CN21-CO21 -> #REF! | CR21: =+A21 -> LUIS VALDERRAMA | CS21: V-23.095.433 | CT21: =+BN21 -> 15000 | CU21: =+AW21 -> 0 | CV21: 1000 | CW21: =+CV21*230 -> 230000 | CX21: 7 | CY21: 9.5 | CZ21: =+CX21*6500+CY21*3500 -> 78750 | DB21: =+CT21*75 -> 1125000 | DC21: =+CI21 -> 1125000 | DD21: =+CI21+CZ21+CW21 -> 1433750
A22: =+'[1]SEMANA DEL 13 AL 20 '!A22 -> LILIANA VEGA | B22: 0 | C22: 0 | D22: 0 | E22: 1 | F22: 0 | G22: 0 | H22: 0 | I22: 1 | J22: 0 | K22: 0 | L22: 0 | M22: 0 | N22: 0 | O22: 0 | P22: 0 | Q22: 0 | R22: 8 | S22: 14.4 | T22: 56 | U22: 6 | AH22: 8 | AI22: 14.4 | AJ22: 56 | AK22: 7 | AO22: 1 | AX22: =B22+R22-AH22 -> 0 | AY22: =C22+S22-AI22 -> 0 | AZ22: =D22+T22-AJ22 -> 0 | BA22: =E22+U22-AK22 -> 0 | BB22: =F22+V22-AL22 -> 0 | BC22: =G22+W22-AM22 -> 0 | BD22: =H22+X22-AN22 -> 0 | BE22: =I22+Y22-AO22 -> 0 | ... BH22: =L22+AB22-AR22 -> 0 | BI22: =+P22+AF22-AV22 -> 0 | BJ22: =N22+AD22-AT22 -> 0 | BK22: =O22+AE22-AU22 -> 0 | BL22: =P22+AF22-AV22 -> 0 | BM22: =Q22+AG22-AW22 -> 0 | BN22: 8000 | BO22: =+AL22*2500 -> 0 | BP22: =+AM22*60000 -> 0 | BQ22: =+AN22*3000 -> 0 | BR22: =+AO22*6000 -> 6000 | BS22: =+AP22*8000 -> 0 | BT22: =+AQ22*8000 -> 0 | BU22: =+AR22*150000 -> 0 | BV22: =+AS22*3000 -> 0 | BW22: =+AT22*25000 -> 0 | BX22: =+AU22*200000 -> 0 | BY22: =+AV22*8000 -> 0 | BZ22: =+AW22*1.5 -> 0 | CC22: =+AH22*16 -> 128 | CD22: =+AI22*12+19.2 -> 192 | CE22: =+AJ22*3 -> 168 | CF22: =+CC22+CD22+CE22 -> 488 | CG22: =+BN22*75061/1000 -> 600488 | CH22: =+BO22+BP22+BQ22+BR22+BS22+BT22+BU22+BV22+BW22+BX22+BY22+CA22+CB22 -> 6000 | CI22: =+CG22-CF22-CH22 -> 594000 | CR22: =+A22 -> LILIANA VEGA | CS22: V-11.021.605 | CT22: =+BN22 -> 8000 | CU22: =+AW22 -> 0 | CW22: =+CV22*230 -> 0 | CX22: 6.6 | CY22: 6.4 | CZ22: =+CX22*6500+CY22*3500 -> 65300 | DB22: =+CT22*75 -> 600000 | DC22: =+CI22 -> 594000 | DD22: =+CI22+CZ22+CW22 -> 659300
A23: =+'[1]SEMANA DEL 13 AL 20 '!A23 -> LUIS ERNESTO ALMEIDA | B23: 0 | C23: 0 | D23: 0 | E23: 0 | F23: 0 | G23: 0 | H23: 0 | I23: 0 | J23: 0 | K23: 0 | L23: 0 | M23: 0 | N23: 0 | O23: 0 | P23: 0 | Q23: 0 | R23: 8 | S23: 14.4 | T23: 56 | U23: 7 | AH23: 8 | AI23: 14.4 | AJ23: 56 | AK23: 7 | AX23: =B23+R23-AH23 -> 0 | AY23: =C23+S23-AI23 -> 0 | AZ23: =D23+T23-AJ23 -> 0 | BA23: =E23+U23-AK23 -> 0 | BB23: =F23+V23-AL23 -> 0 | BC23: =G23+W23-AM23 -> 0 | BD23: =H23+X23-AN23 -> 0 | BE23: =I23+Y23-AO23 -> 0 | ... BH23: =L23+AB23-AR23 -> 0 | BI23: =+P23+AF23-AV23 -> 0 | BJ23: =N23+AD23-AT23 -> 0 | BK23: =O23+AE23-AU23 -> 0 | BL23: =P23+AF23-AV23 -> 0 | BM23: =Q23+AG23-AW23 -> 0 | BN23: 8000 | BO23: =+AL23*2500 -> 0 | BP23: =+AM23*60000 -> 0 | BQ23: =+AN23*3000 -> 0 | BR23: =+AO23*6000 -> 0 | BS23: =+AP23*8000 -> 0 | BT23: =+AQ23*8000 -> 0 | BU23: =+AR23*150000 -> 0 | BV23: =+AS23*3000 -> 0 | BW23: =+AT23*25000 -> 0 | BX23: =+AU23*200000 -> 0 | BY23: =+AV23*8000 -> 0 | BZ23: =+AW23*1.5 -> 0 | CA23: 25000 | CC23: =+AH23*16 -> 128 | CD23: =+AI23*12+19.2 -> 192 | CE23: =+AJ23*3 -> 168 | CF23: =+CC23+CD23+CE23 -> 488 | CG23: =+BN23*75061/1000 -> 600488 | CH23: =+BO23+BP23+BQ23+BR23+BS23+BT23+BU23+BV23+BW23+BX23+BY23+CA23+CB23 -> 25000 | CI23: =+CG23-CF23-CH23 -> 575000 | CR23: =+A23 -> LUIS ERNESTO ALMEIDA | CS23: V-13.365.579 | CT23: =+BN23 -> 8000 | CU23: =+AW23 -> 0 | CW23: =+CV23*230 -> 0 | CX23: 6.5 | CY23: 2.9 | CZ23: =+CX23*6500+CY23*3500 -> 52400 | DB23: =+CT23*75 -> 600000 | DC23: =+CI23 -> 575000 | DD23: =+CI23+CZ23+CW23 -> 627400
A24: =+'[1]SEMANA DEL 13 AL 20 '!A24 -> LEIDY SERRANO | B24: 0 | C24: 0 | D24: 0 | E24: 0 | F24: 0 | G24: 0 | H24: 0 | I24: 0 | J24: 0 | K24: 0 | L24: 0 | M24: 0 | N24: 0 | O24: 0 | P24: 0 | Q24: 0 | R24: 5 | S24: 9 | T24: 35 | U24: 4 | AH24: 5 | AI24: 9 | AJ24: 35 | AK24: 4 | AX24: =B24+R24-AH24 -> 0 | AY24: =C24+S24-AI24 -> 0 | AZ24: =D24+T24-AJ24 -> 0 | BA24: =E24+U24-AK24 -> 0 | BB24: =F24+V24-AL24 -> 0 | BC24: =G24+W24-AM24 -> 0 | BD24: =H24+X24-AN24 -> 0 | BE24: =I24+Y24-AO24 -> 0 | ... BH24: =L24+AB24-AR24 -> 0 | BI24: =+P24+AF24-AV24 -> 0 | BJ24: =N24+AD24-AT24 -> 0 | BK24: =O24+AE24-AU24 -> 0 | BL24: =P24+AF24-AV24 -> 0 | BM24: =Q24+AG24-AW24 -> 0 | BN24: 5000 | BO24: =+AL24*2500 -> 0 | BP24: =+AM24*60000 -> 0 | BQ24: =+AN24*3000 -> 0 | BR24: =+AO24*6000 -> 0 | BS24: =+AP24*8000 -> 0 | BT24: =+AQ24*8000 -> 0 | BU24: =+AR24*150000 -> 0 | BV24: =+AS24*3000 -> 0 | BW24: =+AT24*25000 -> 0 | BX24: =+AU24*200000 -> 0 | BY24: =+AV24*8000 -> 0 | BZ24: =+AW24*1.5 -> 0 | CC24: =+AH24*16 -> 80 | CD24: =+AI24*12+12 -> 120 | CE24: =+AJ24*3 -> 105 | CF24: =+CC24+CD24+CE24 -> 305 | CG24: =+BN24*75061/1000 -> 375305 | CH24: =+BO24+BP24+BQ24+BR24+BS24+BT24+BU24+BV24+BW24+BX24+BY24+CA24+CB24 -> 0 | CI24: =+CG24-CF24-CH24 -> 375000 | CR24: =+A24 -> LEIDY SERRANO | CS24: V-15.958.666 | CT24: =+BN24 -> 5000 | CU24: =+AW24 -> 0 | CV24: 750 | CW24: =+CV24*230 -> 172500 | CX24: 5.4 | CY24: 4.6 | CZ24: =+CX24*6500+CY24*3500 -> 51200 | DB24: =+CT24*75 -> 375000 | DC24: =+CI24 -> 375000 | DD24: =+CI24+CZ24+CW24 -> 598700
A25: =+'[1]SEMANA DEL 13 AL 20 '!A25 -> MAYERLIN BOLIVAR | B25: 0.3 | C25: 1.34 | D25: 2.1 | E25: 0 | F25: 0 | G25: 0 | H25: 0 | I25: 0 | J25: 0 | K25: 0 | L25: 0 | M25: 0 | N25: 0 | O25: 0 | P25: 0 | Q25: 0 | R25: 15 | S25: 27 | T25: 105 | U25: 12 | AH25: 15 | AI25: 27 | AJ25: 105 | AK25: 12 | AX25: =B25+R25-AH25 -> 0.3 | AY25: =C25+S25-AI25 -> 1.34 | AZ25: =D25+T25-AJ25 -> 2.1 | BA25: =E25+U25-AK25 -> 0 | BB25: =F25+V25-AL25 -> 0 | BC25: =G25+W25-AM25 -> 0 | BD25: =H25+X25-AN25 -> 0 | BE25: =I25+Y25-AO25 -> 0 | ... BH25: =L25+AB25-AR25 -> 0 | BI25: =+P25+AF25-AV25 -> 0 | BJ25: =N25+AD25-AT25 -> 0 | BK25: =O25+AE25-AU25 -> 0 | BL25: =P25+AF25-AV25 -> 0 | BM25: =Q25+AG25-AW25 -> 0 | BN25: 15000 | BO25: =+AL25*2500 -> 0 | BP25: =+AM25*60000 -> 0 | BQ25: =+AN25*3000 -> 0 | BR25: =+AO25*6000 -> 0 | BS25: =+AP25*8000 -> 0 | BT25: =+AQ25*8000 -> 0 | BU25: =+AR25*150000 -> 0 | BV25: =+AS25*3000 -> 0 | BW25: =+AT25*25000 -> 0 | BX25: =+AU25*200000 -> 0 | BY25: =+AV25*8000 -> 0 | BZ25: =+AW25*1.5 -> 0 | CC25: =+AH25*16 -> 240 | CD25: =+AI25*12+36 -> 360 | CE25: =+AJ25*3 -> 315 | CF25: =+CC25+CD25+CE25 -> 915 | CG25: =+BN25*75061/1000 -> 1125915 | CH25: =+BO25+BP25+BQ25+BR25+BS25+BT25+BU25+BV25+BW25+BX25+BY25+CA25+CB25 -> 0 | CI25: =+CG25-CF25-CH25 -> 1125000 | CR25: =+A25 -> MAYERLIN BOLIVAR | CS25: V-15,774,803 | CT25: =+BN25 -> 15000 | CU25: =+AW25 -> 0 | CW25: =+CV25*230 -> 0 | CX25: 3.5 | CY25: 8.4 | CZ25: =+CX25*6500+CY25*3500 -> 52150 | DB25: =+CT25*75 -> 1125000 | DC25: =+CI25 -> 1125000 | DD25: =+CI25+CZ25+CW25 -> 1177150
A26: =+'[1]SEMANA DEL 13 AL 20 '!A26 -> MARTHA SILVA | B26: 0.1 | C26: 0.18 | D26: 12 | E26: 0 | F26: 0 | G26: 0 | H26: 0 | I26: 0 | J26: 0 | K26: 0 | L26: 0 | M26: 0 | N26: 0 | O26: 0 | P26: 0 | Q26: 0 | R26: 0 | S26: 0 | T26: 0 | U26: 0 | AH26: 0 | AI26: 0 | AJ26: 0 | AK26: 0 | AX26: =B26+R26-AH26 -> 0.1 | AY26: =C26+S26-AI26 -> 0.18 | AZ26: =D26+T26-AJ26 -> 12 | BA26: =E26+U26-AK26 -> 0 | BB26: =F26+V26-AL26 -> 0 | BC26: =G26+W26-AM26 -> 0 | BD26: =H26+X26-AN26 -> 0 | BE26: =I26+Y26-AO26 -> 0 | ... BH26: =L26+AB26-AR26 -> 0 | BI26: =+P26+AF26-AV26 -> 0 | BJ26: =N26+AD26-AT26 -> 0 | BK26: =O26+AE26-AU26 -> 0 | BL26: =P26+AF26-AV26 -> 0 | BM26: =Q26+AG26-AW26 -> 0 | BN26: 0 | BO26: =+AL26*2500 -> 0 | BP26: =+AM26*60000 -> 0 | BQ26: =+AN26*3000 -> 0 | BR26: =+AO26*6000 -> 0 | BS26: =+AP26*8000 -> 0 | BT26: =+AQ26*8000 -> 0 | BU26: =+AR26*150000 -> 0 | BV26: =+AS26*3000 -> 0 | BW26: =+AT26*25000 -> 0 | BX26: =+AU26*200000 -> 0 | BY26: =+AV26*8000 -> 0 | BZ26: =+AW26*1.5 -> 0 | CC26: =+AH26*16 -> 0 | CD26: =+AI26*12 -> 0 | CE26: =+AJ26*3 -> 0 | CF26: =+CC26+CD26+CE26 -> 0 | CG26: =+BN26*75061/1000 -> 0 | CH26: =+BO26+BP26+BQ26+BR26+BS26+BT26+BU26+BV26+BW26+BX26+BY26+CA26+CB26 -> 0 | CI26: =+CG26-CF26-CH26 -> 0 | CK26: SILLAS | CL26: =+#REF! -> #REF! | CM26: =+#REF! -> #REF! | CN26: =+CL26+CM26 -> #REF! | CO26: =+#REF! -> #REF! | CP26: =CN26-CO26 -> #REF! | CR26: =+A26 -> MARTHA SILVA | CS26: V-28,636.032 | CT26: =+BN26 -> 0 | CU26: =+AW26 -> 0 | CW26: =+CV26*230 -> 0 | CX26: 0 | CY26: 0 | CZ26: =+CX26*6500+CY26*3500 -> 0 | DB26: =+CT26*75 -> 0 | DC26: =+CI26 -> 0 | DD26: =+CI26+CZ26+CW26 -> 0
A27: MARIELA MARTINEZ | B27: 0 | C27: -0.004 | D27: 0 | E27: 0 | F27: 0 | G27: 0 | H27: 0 | I27: 0 | J27: 0 | K27: 0 | L27: 0 | M27: 0 | N27: 0 | O27: 0 | P27: 0 | Q27: 0 | AX27: =B27+R27-AH27 -> 0 | AY27: =C27+S27-AI27 -> -0.004 | AZ27: =D27+T27-AJ27 -> 0 | BA27: =E27+U27-AK27 -> 0 | BB27: =F27+V27-AL27 -> 0 | BC27: =G27+W27-AM27 -> 0 | BD27: =H27+X27-AN27 -> 0 | BE27: =I27+Y27-AO27 -> 0 | ... BH27: =L27+AB27-AR27 -> 0 | BI27: =+P27+AF27-AV27 -> 0 | BJ27: =N27+AD27-AT27 -> 0 | BK27: =O27+AE27-AU27 -> 0 | BL27: =P27+AF27-AV27 -> 0 | BM27: =Q27+AG27-AW27 -> 0
A28: MANUEL CONTRERAS | B28: 0 | C28: -0.004 | D28: 0 | E28: 0 | F28: 0 | G28: 0 | H28: 0 | I28: 0 | J28: 0 | K28: 0 | L28: 0 | M28: 0 | N28: 0 | O28: 0 | P28: 0 | Q28: 0 | AX28: =B28+R28-AH28 -> 0 | AY28: =C28+S28-AI28 -> -0.004 | AZ28: =D28+T28-AJ28 -> 0 | BA28: =E28+U28-AK28 -> 0 | BB28: =F28+V28-AL28 -> 0 | BC28: =G28+W28-AM28 -> 0 | BD28: =H28+X28-AN28 -> 0 | BE28: =I28+Y28-AO28 -> 0 | ... BH28: =L28+AB28-AR28 -> 0 | BI28: =+P28+AF28-AV28 -> 0 | BJ28: =N28+AD28-AT28 -> 0 | BK28: =O28+AE28-AU28 -> 0 | BL28: =P28+AF28-AV28 -> 0 | BM28: =Q28+AG28-AW28 -> 0
A29: =+'[1]SEMANA DEL 13 AL 20 '!A27 -> MARIA MEDINA | B29: 0 | C29: -0.004 | D29: 0 | E29: 0 | F29: 0 | G29: 0 | H29: 0 | I29: 0 | J29: 0 | K29: 0 | L29: 0 | M29: 0 | N29: 0 | O29: 0 | P29: 0 | Q29: 0 | R29: 5 | S29: 9 | T29: 35 | U29: 4 | AH29: 5 | AI29: 9 | AJ29: 35 | AK29: 4 | AX29: =B29+R29-AH29 -> 0 | AY29: =C29+S29-AI29 -> -0.004 | AZ29: =D29+T29-AJ29 -> 0 | BA29: =E29+U29-AK29 -> 0 | BB29: =F29+V29-AL29 -> 0 | BC29: =G29+W29-AM29 -> 0 | BD29: =H29+X29-AN29 -> 0 | BE29: =I29+Y29-AO29 -> 0 | ... BH29: =L29+AB29-AR29 -> 0 | BI29: =+P29+AF29-AV29 -> 0 | BJ29: =N29+AD29-AT29 -> 0 | BK29: =O29+AE29-AU29 -> 0 | BL29: =P29+AF29-AV29 -> 0 | BM29: =Q29+AG29-AW29 -> 0 | BN29: 5000 | BO29: =+AL29*2500 -> 0 | BP29: =+AM29*60000 -> 0 | BQ29: =+AN29*3000 -> 0 | BR29: =+AO29*6000 -> 0 | BS29: =+AP29*8000 -> 0 | BT29: =+AQ29*8000 -> 0 | BU29: =+AR29*150000 -> 0 | BV29: =+AS29*3000 -> 0 | BW29: =+AT29*25000 -> 0 | BX29: =+AU29*200000 -> 0 | BY29: =+AV29*8000 -> 0 | BZ29: =+AW29*1.5 -> 0 | CC29: =+AH29*16 -> 80 | CD29: =+AI29*12+12 -> 120 | CE29: =+AJ29*3 -> 105 | CF29: =+CC29+CD29+CE29 -> 305 | CG29: =+BN29*75061/1000 -> 375305 | CH29: =+BO29+BP29+BQ29+BR29+BS29+BT29+BU29+BV29+BW29+BX29+BY29+CA29+CB29 -> 0 | CI29: =+CG29-CF29-CH29 -> 375000 | CR29: =+A29 -> MARIA MEDINA | CS29: V-22.680.548 | CT29: =+BN29 -> 5000 | CU29: =+AW29 -> 0 | CV29: 507 | CW29: =+CV29*230 -> 116610 | CX29: 1.2 | CY29: 1.7 | CZ29: =+CX29*6500+CY29*3500 -> 13750 | DB29: =+CT29*75 -> 375000 | DC29: =+CI29 -> 375000 | DD29: =+CI29+CZ29+CW29 -> 505360
A30: =+'[1]SEMANA DEL 13 AL 20 '!A30 -> PETTER BENAVIDES | B30: 0 | C30: 0 | D30: 0 | E30: 0 | F30: 0 | G30: 0 | H30: 0 | I30: 2 | J30: 0 | K30: 0 | L30: 0 | M30: 0 | N30: 0 | O30: 0 | P30: 0 | Q30: 0 | R30: 10 | S30: 18 | T30: 70 | U30: 8 | AH30: 10 | AI30: 18 | AJ30: 70 | AK30: 8 | AX30: =B30+R30-AH30 -> 0 | AY30: =C30+S30-AI30 -> 0 | AZ30: =D30+T30-AJ30 -> 0 | BA30: =E30+U30-AK30 -> 0 | BB30: =F30+V30-AL30 -> 0 | BC30: =G30+W30-AM30 -> 0 | BD30: =H30+X30-AN30 -> 0 | BE30: =I30+Y30-AO30 -> 2 | ... BH30: =L30+AB30-AR30 -> 0 | BI30: =+P30+AF30-AV30 -> 0 | BJ30: =N30+AD30-AT30 -> 0 | BK30: =O30+AE30-AU30 -> 0 | BL30: =P30+AF30-AV30 -> 0 | BM30: =Q30+AG30-AW30 -> 0 | BN30: 10000 | BO30: =+AL30*2500 -> 0 | BP30: =+AM30*60000 -> 0 | BQ30: =+AN30*3000 -> 0 | BR30: =+AO30*6000 -> 0 | BS30: =+AP30*8000 -> 0 | BT30: =+AQ30*8000 -> 0 | BU30: =+AR30*150000 -> 0 | BV30: =+AS30*3000 -> 0 | BW30: =+AT30*25000 -> 0 | BX30: =+AU30*200000 -> 0 | BY30: =+AV30*8000 -> 0 | BZ30: =+AW30*1.5 -> 0 | CC30: =+AH30*16 -> 160 | CD30: =+AI30*12+24 -> 240 | CE30: =+AJ30*3 -> 210 | CF30: =+CC30+CD30+CE30 -> 610 | CG30: =+BN30*75061/1000 -> 750610 | CH30: =+BO30+BP30+BQ30+BR30+BS30+BT30+BU30+BV30+BW30+BX30+BY30+CA30+CB30 -> 0 | CI30: =+CG30-CF30-CH30 -> 750000 | CR30: =+A30 -> PETTER BENAVIDES | CS30: V-8991.028 | CT30: =+BN30 -> 10000 | CU30: =+AW30 -> 0 | CW30: =+CV30*230 -> 0 | CX30: 8 | CY30: 5.9 | CZ30: =+CX30*6500+CY30*3500 -> 72650 | DB30: =+CT30*75 -> 750000 | DC30: =+CI30 -> 750000 | DD30: =+CI30+CZ30+CW30 -> 822650
A31: =+'[1]SEMANA DEL 13 AL 20 '!A31 -> RAMON PARRA | B31: 0 | C31: 0 | D31: 0 | E31: 0 | F31: 0 | G31: 0 | H31: 0 | I31: 0 | J31: 0 | K31: 0 | L31: 0 | M31: 0 | N31: 0 | O31: 0 | P31: 0 | Q31: 0 | R31: 5 | S31: 9 | T31: 35 | U31: 4 | AH31: 5 | AI31: 9 | AJ31: 35 | AK31: 4 | AX31: =B31+R31-AH31 -> 0 | AY31: =C31+S31-AI31 -> 0 | AZ31: =D31+T31-AJ31 -> 0 | BA31: =E31+U31-AK31 -> 0 | BB31: =F31+V31-AL31 -> 0 | BC31: =G31+W31-AM31 -> 0 | BD31: =H31+X31-AN31 -> 0 | BE31: =I31+Y31-AO31 -> 0 | ... BH31: =L31+AB31-AR31 -> 0 | BI31: =+P31+AF31-AV31 -> 0 | BJ31: =N31+AD31-AT31 -> 0 | BK31: =O31+AE31-AU31 -> 0 | BL31: =P31+AF31-AV31 -> 0 | BM31: =Q31+AG31-AW31 -> 0 | BN31: 5000 | BO31: =+AL31*2500 -> 0 | BP31: =+AM31*60000 -> 0 | BQ31: =+AN31*3000 -> 0 | BR31: =+AO31*6000 -> 0 | BS31: =+AP31*8000 -> 0 | BT31: =+AQ31*8000 -> 0 | BU31: =+AR31*150000 -> 0 | BV31: =+AS31*3000 -> 0 | BW31: =+AT31*25000 -> 0 | BX31: =+AU31*200000 -> 0 | BY31: =+AV31*8000 -> 0 | BZ31: =+AW31*1.5 -> 0 | CC31: =+AH31*16 -> 80 | CD31: =+AI31*12+12 -> 120 | CE31: =+AJ31*3 -> 105 | CF31: =+CC31+CD31+CE31 -> 305 | CG31: =+BN31*75061/1000 -> 375305 | CH31: =+BO31+BP31+BQ31+BR31+BS31+BT31+BU31+BV31+BW31+BX31+BY31+CA31+CB31 -> 0 | CI31: =+CG31-CF31-CH31 -> 375000 | CR31: =+A31 -> RAMON PARRA | CS31: V-5.327.891 | CT31: =+BN31 -> 5000 | CU31: =+AW31 -> 0 | CW31: =+CV31*230 -> 0 | CX31: 1.9 | CY31: 4.2 | CZ31: =+CX31*6500+CY31*3500 -> 27050 | DB31: =+CT31*75 -> 375000 | DC31: =+CI31 -> 375000 | DD31: =+CI31+CZ31+CW31 -> 402050
A32: =+'[1]SEMANA DEL 13 AL 20 '!A32 -> SULAY ALMEIDA | B32: 1 | C32: 1.81 | D32: 6.95 | E32: 0 | F32: 0 | G32: 0 | H32: 0 | I32: 0 | J32: 0 | K32: 0 | L32: 0 | M32: 0 | N32: 0 | O32: 0 | P32: 0 | Q32: 0 | R32: 0 | S32: 0 | T32: 0 | U32: 0 | AH32: 0 | AI32: 0 | AJ32: 0 | AK32: 0 | AX32: =B32+R32-AH32 -> 1 | AY32: =C32+S32-AI32 -> 1.81 | AZ32: =D32+T32-AJ32 -> 6.95 | BA32: =E32+U32-AK32 -> 0 | BB32: =F32+V32-AL32 -> 0 | BC32: =G32+W32-AM32 -> 0 | BD32: =H32+X32-AN32 -> 0 | BE32: =I32+Y32-AO32 -> 0 | ... BH32: =L32+AB32-AR32 -> 0 | BI32: =+P32+AF32-AV32 -> 0 | BJ32: =N32+AD32-AT32 -> 0 | BK32: =O32+AE32-AU32 -> 0 | BL32: =P32+AF32-AV32 -> 0 | BM32: =Q32+AG32-AW32 -> 0 | BN32: 0 | BO32: =+AL32*2500 -> 0 | BP32: =+AM32*60000 -> 0 | BQ32: =+AN32*3000 -> 0 | BR32: =+AO32*6000 -> 0 | BS32: =+AP32*8000 -> 0 | BT32: =+AQ32*8000 -> 0 | BU32: =+AR32*150000 -> 0 | BV32: =+AS32*3000 -> 0 | BW32: =+AT32*25000 -> 0 | BX32: =+AU32*200000 -> 0 | BY32: =+AV32*8000 -> 0 | BZ32: =+AW32*1.5 -> 0 | CC32: =+AH32*16 -> 0 | CD32: =+AI32*12 -> 0 | CE32: =+AJ32*3 -> 0 | CF32: =+CC32+CD32+CE32 -> 0 | CG32: =+BN32*75061/1000 -> 0 | CH32: =+BO32+BP32+BQ32+BR32+BS32+BT32+BU32+BV32+BW32+BX32+BY32+CA32+CB32 -> 0 | CI32: =+CG32-CF32-CH32 -> 0 | CR32: =+A32 -> SULAY ALMEIDA | CS32: V-18.718.244 | CT32: =+BN32 -> 0 | CU32: =+AW32 -> 0 | CW32: =+CV32*230 -> 0 | CX32: 0 | CY32: 0 | CZ32: =+CX32*6500+CY32*3500 -> 0 | DB32: =+CT32*75 -> 0 | DC32: =+CI32 -> 0 | DD32: =+CI32+CZ32+CW32 -> 0
A33: =+'[1]SEMANA DEL 13 AL 20 '!A34 -> RENE ALMEIDA | B33: 1.35 | C33: 1.43 | D33: 12.75 | E33: 0 | F33: 0 | G33: 0 | H33: 0 | I33: 0 | J33: 0 | K33: 0 | L33: 0 | M33: 0 | N33: 0 | O33: 0 | P33: 0 | Q33: 0 | R33: 2.5 | S33: 3.5 | T33: 15 | U33: 2 | AH33: 2.45 | AI33: 4.41 | AJ33: 17.15 | AK33: 2 | AX33: =B33+R33-AH33 -> 1.4 | AY33: =C33+S33-AI33 -> 0.52 | AZ33: =D33+T33-AJ33 -> 10.6 | BA33: =E33+U33-AK33 -> 0 | BB33: =F33+V33-AL33 -> 0 | BC33: =G33+W33-AM33 -> 0 | BD33: =H33+X33-AN33 -> 0 | BE33: =I33+Y33-AO33 -> 0 | ... BH33: =L33+AB33-AR33 -> 0 | BI33: =+P33+AF33-AV33 -> 0 | BJ33: =N33+AD33-AT33 -> 0 | BK33: =O33+AE33-AU33 -> 0 | BL33: =P33+AF33-AV33 -> 0 | BM33: =Q33+AG33-AW33 -> 0 | BN33: 2450 | BO33: =+AL33*2500 -> 0 | BP33: =+AM33*60000 -> 0 | BQ33: =+AN33*3000 -> 0 | BR33: =+AO33*6000 -> 0 | BS33: =+AP33*8000 -> 0 | BT33: =+AQ33*8000 -> 0 | BU33: =+AR33*150000 -> 0 | BV33: =+AS33*3000 -> 0 | BW33: =+AT33*25000 -> 0 | BX33: =+AU33*200000 -> 0 | BY33: =+AV33*8000 -> 0 | BZ33: =+AW33*1.5 -> 0 | CC33: =+AH33*16 -> 39.2 | CD33: =+AI33*12+5.88 -> 58.8 | CE33: =+AJ33*3 -> 51.45 | CF33: =+CC33+CD33+CE33 -> 149.45 | CG33: =+BN33*75061/1000 -> 183899.45 | CH33: =+BO33+BP33+BQ33+BR33+BS33+BT33+BU33+BV33+BW33+BX33+BY33+CA33+CB33 -> 0 | CI33: =+CG33-CF33-CH33 -> 183750 | CR33: =+A33 -> RENE ALMEIDA | CS33: V-21.033.815 | CT33: =+BN33 -> 2450 | CU33: =+AW33 -> 0 | CW33: =+CV33*230 -> 0 | CX33: 2.2 | CY33: 1.9 | CZ33: =+CX33*6500+CY33*3500 -> 20950 | DB33: =+CT33*75 -> 183750 | DC33: =+CI33 -> 183750 | DD33: =+CI33+CZ33+CW33 -> 204700
A34: =+'[1]SEMANA DEL 13 AL 20 '!A35 -> RUBIELA MARTINEZ | B34: 0 | C34: 1.56 | D34: -0.002 | E34: 0 | F34: 0 | G34: 0 | H34: 0 | I34: 0 | J34: 0 | K34: 0 | L34: 0 | M34: 0 | N34: 0 | O34: 0 | P34: 0 | Q34: 0 | R34: 10 | S34: 17.5 | T34: 70 | U34: 8 | AH34: 10 | AI34: 18 | AJ34: 70 | AK34: 8 | AX34: =B34+R34-AH34 -> 0 | AY34: =C34+S34-AI34 -> 1.06 | AZ34: =D34+T34-AJ34 -> -0.002 | BA34: =E34+U34-AK34 -> 0 | BB34: =F34+V34-AL34 -> 0 | BC34: =G34+W34-AM34 -> 0 | BD34: =H34+X34-AN34 -> 0 | BE34: =I34+Y34-AO34 -> 0 | ... BH34: =L34+AB34-AR34 -> 0 | BI34: =+P34+AF34-AV34 -> 0 | BJ34: =N34+AD34-AT34 -> 0 | BK34: =O34+AE34-AU34 -> 0 | BL34: =P34+AF34-AV34 -> 0 | BM34: =Q34+AG34-AW34 -> 0 | BN34: 10000 | BO34: =+AL34*2500 -> 0 | BP34: =+AM34*60000 -> 0 | BQ34: =+AN34*3000 -> 0 | BR34: =+AO34*6000 -> 0 | BS34: =+AP34*8000 -> 0 | BT34: =+AQ34*8000 -> 0 | BU34: =+AR34*150000 -> 0 | BV34: =+AS34*3000 -> 0 | BW34: =+AT34*25000 -> 0 | BX34: =+AU34*200000 -> 0 | BY34: =+AV34*8000 -> 0 | BZ34: =+AW34*1.5 -> 0 | CC34: =+AH34*16 -> 160 | CD34: =+AI34*12+24 -> 240 | CE34: =+AJ34*3 -> 210 | CF34: =+CC34+CD34+CE34 -> 610 | CG34: =+BN34*75061/1000 -> 750610 | CH34: =+BO34+BP34+BQ34+BR34+BS34+BT34+BU34+BV34+BW34+BX34+BY34+CA34+CB34 -> 0 | CI34: =+CG34-CF34-CH34 -> 750000 | CR34: =+A34 -> RUBIELA MARTINEZ | CS34: CC-60.412.324 | CT34: =+BN34 -> 10000 | CU34: =+AW34 -> 0 | CW34: =+CV34*230 -> 0 | CX34: 5 | CY34: 3.8 | CZ34: =+CX34*6500+CY34*3500 -> 45800 | DB34: =+CT34*75 -> 750000 | DC34: =+CI34 -> 750000 | DD34: =+CI34+CZ34+CW34 -> 795800
A35: =+'[1]SEMANA DEL 13 AL 20 '!A36 -> ROSMIRA DURAN | B35: 0.996 | C35: 0.9 | D35: 3.5 | E35: 1 | F35: 0 | G35: 0 | H35: 0 | I35: 0 | J35: 0 | K35: 0 | L35: 0 | M35: 0 | N35: 0 | O35: 0 | P35: 0 | Q35: 0 | R35: 2 | S35: 3 | T35: 14 | U35: 2 | AH35: 3 | AI35: 3.9 | AJ35: 17.5 | AK35: 2 | AX35: =B35+R35-AH35 -> -0.004 | AY35: =C35+S35-AI35 -> 0 | AZ35: =D35+T35-AJ35 -> 0 | BA35: =E35+U35-AK35 -> 1 | BB35: =F35+V35-AL35 -> 0 | BC35: =G35+W35-AM35 -> 0 | BD35: =H35+X35-AN35 -> 0 | BE35: =I35+Y35-AO35 -> 0 | ... BH35: =L35+AB35-AR35 -> 0 | BI35: =+P35+AF35-AV35 -> 0 | BJ35: =N35+AD35-AT35 -> 0 | BK35: =O35+AE35-AU35 -> 0 | BL35: =P35+AF35-AV35 -> 0 | BM35: =Q35+AG35-AW35 -> 0 | BN35: 2500 | BO35: =+AL35*2500 -> 0 | BP35: =+AM35*60000 -> 0 | BQ35: =+AN35*3000 -> 0 | BR35: =+AO35*6000 -> 0 | BS35: =+AP35*8000 -> 0 | BT35: =+AQ35*8000 -> 0 | BU35: =+AR35*150000 -> 0 | BV35: =+AS35*3000 -> 0 | BW35: =+AT35*25000 -> 0 | BX35: =+AU35*200000 -> 0 | BY35: =+AV35*8000 -> 0 | BZ35: =+AW35*1.5 -> 0 | CC35: =+AH35*16 -> 48 | CD35: =+AI35*12+5.2 -> 52 | CE35: =+AJ35*3 -> 52.5 | CF35: =+CC35+CD35+CE35 -> 152.5 | CG35: =+BN35*75061/1000 -> 187652.5 | CH35: =+BO35+BP35+BQ35+BR35+BS35+BT35+BU35+BV35+BW35+BX35+BY35+CA35+CB35 -> 0 | CI35: =+CG35-CF35-CH35 -> 187500 | CR35: =+A35 -> ROSMIRA DURAN | CS35: CC-37.543.611 | CT35: =+BN35 -> 2500 | CU35: =+AW35 -> 0 | CW35: =+CV35*230 -> 0 | CX35: 1.5 | CY35: 1.4 | CZ35: =+CX35*6500+CY35*3500 -> 14650 | DB35: =+CT35*75 -> 187500 | DC35: =+CI35 -> 187500 | DD35: =+CI35+CZ35+CW35 -> 202150
A36: =+'[1]SEMANA DEL 13 AL 20 '!A38 -> ROSALBA MATAGIRA | B36: 0 | C36: 0 | D36: 0 | E36: 0 | F36: 0 | G36: 0 | H36: 0 | I36: 0 | J36: 0 | K36: 0 | L36: 0 | M36: 0 | N36: 0 | O36: 0 | P36: 0 | Q36: 0 | R36: 11 | S36: 19.8 | T36: 77 | U36: 9 | AH36: 11 | AI36: 19.8 | AJ36: 77 | AK36: 9 | AX36: =B36+R36-AH36 -> 0 | AY36: =C36+S36-AI36 -> 0 | AZ36: =D36+T36-AJ36 -> 0 | BA36: =E36+U36-AK36 -> 0 | BB36: =F36+V36-AL36 -> 0 | BC36: =G36+W36-AM36 -> 0 | BD36: =H36+X36-AN36 -> 0 | BE36: =I36+Y36-AO36 -> 0 | ... BH36: =L36+AB36-AR36 -> 0 | BI36: =+P36+AF36-AV36 -> 0 | BJ36: =N36+AD36-AT36 -> 0 | BK36: =O36+AE36-AU36 -> 0 | BL36: =P36+AF36-AV36 -> 0 | BM36: =Q36+AG36-AW36 -> 0 | BN36: 11000 | BO36: =+AL36*2500 -> 0 | BP36: =+AM36*60000 -> 0 | BQ36: =+AN36*3000 -> 0 | BR36: =+AO36*6000 -> 0 | BS36: =+AP36*8000 -> 0 | BT36: =+AQ36*8000 -> 0 | BU36: =+AR36*150000 -> 0 | BV36: =+AS36*3000 -> 0 | BW36: =+AT36*25000 -> 0 | BX36: =+AU36*200000 -> 0 | BY36: =+AV36*8000 -> 0 | BZ36: =+AW36*1.5 -> 0 | CC36: =+AH36*16 -> 176 | CD36: =+AI36*12+26.4 -> 264 | CE36: =+AJ36*3 -> 231 | CF36: =+CC36+CD36+CE36 -> 671 | CG36: =+BN36*75061/1000 -> 825671 | CH36: =+BO36+BP36+BQ36+BR36+BS36+BT36+BU36+BV36+BW36+BX36+BY36+CA36+CB36 -> 0 | CI36: =+CG36-CF36-CH36 -> 825000 | CR36: =+A36 -> ROSALBA MATAGIRA | CS36: CC-37.221.293 | CT36: =+BN36 -> 11000 | CU36: =+AW36 -> 0 | CW36: =+CV36*230 -> 0 | CX36: 8 | CY36: 8.2 | CZ36: =+CX36*6500+CY36*3500 -> 80700 | DB36: =+CT36*75 -> 825000 | DC36: =+CI36 -> 825000 | DD36: =+CI36+CZ36+CW36 -> 905700
A37: =+'[1]SEMANA DEL 13 AL 20 '!A40 -> STELLA SILVA | B37: 0 | C37: 0 | D37: 0 | E37: 0 | F37: 0 | G37: 0 | H37: 0 | I37: 0 | J37: 0 | K37: 0 | L37: 0 | M37: 0 | N37: 0 | O37: 0 | P37: 0 | Q37: 0 | R37: 4 | S37: 7.2 | T37: 28 | U37: 3 | AH37: 4 | AI37: 7.2 | AJ37: 28 | AK37: 3 | AX37: =B37+R37-AH37 -> 0 | AY37: =C37+S37-AI37 -> 0 | AZ37: =D37+T37-AJ37 -> 0 | BA37: =E37+U37-AK37 -> 0 | BB37: =F37+V37-AL37 -> 0 | BC37: =G37+W37-AM37 -> 0 | BD37: =H37+X37-AN37 -> 0 | BE37: =I37+Y37-AO37 -> 0 | ... BH37: =L37+AB37-AR37 -> 0 | BI37: =+P37+AF37-AV37 -> 0 | BJ37: =N37+AD37-AT37 -> 0 | BK37: =O37+AE37-AU37 -> 0 | BL37: =P37+AF37-AV37 -> 0 | BM37: =Q37+AG37-AW37 -> 0 | BN37: 4000 | BO37: =+AL37*2500 -> 0 | BP37: =+AM37*60000 -> 0 | BQ37: =+AN37*3000 -> 0 | BR37: =+AO37*6000 -> 0 | BS37: =+AP37*8000 -> 0 | BT37: =+AQ37*8000 -> 0 | BU37: =+AR37*150000 -> 0 | BV37: =+AS37*3000 -> 0 | BW37: =+AT37*25000 -> 0 | BX37: =+AU37*200000 -> 0 | BY37: =+AV37*8000 -> 0 | BZ37: =+AW37*1.5 -> 0 | CA37: 30000 | CC37: =+AH37*16 -> 64 | CD37: =+AI37*12+9.6 -> 96 | CE37: =+AJ37*3 -> 84 | CF37: =+CC37+CD37+CE37 -> 244 | CG37: =+BN37*75061/1000 -> 300244 | CH37: =+BO37+BP37+BQ37+BR37+BS37+BT37+BU37+BV37+BW37+BX37+BY37+CA37+CB37 -> 30000 | CI37: =+CG37-CF37-CH37 -> 270000 | CR37: =+A37 -> STELLA SILVA | CS37: V-11.021.592 | CT37: =+BN37 -> 4000 | CU37: =+AW37 -> 0 | CW37: =+CV37*230 -> 0 | CX37: 3.1 | CY37: 2.7 | CZ37: =+CX37*6500+CY37*3500 -> 29600 | DB37: =+CT37*75 -> 300000 | DC37: =+CI37 -> 270000 | DD37: =+CI37+CZ37+CW37 -> 299600
A38: SANDRA MILENA ANTOLINES | B38: 0 | C38: 0 | D38: 0 | E38: 0 | F38: 0 | G38: 0 | H38: 0 | I38: 0 | J38: 0 | K38: 0 | L38: 0 | M38: 0 | N38: 0 | O38: 0 | P38: 0 | Q38: 0 | R38: 5 | S38: 9 | T38: 35 | U38: 4 | AH38: 5 | AI38: 9 | AJ38: 35 | AK38: 4 | AX38: =B38+R38-AH38 -> 0 | AY38: =C38+S38-AI38 -> 0 | AZ38: =D38+T38-AJ38 -> 0 | BA38: =E38+U38-AK38 -> 0 | BB38: =F38+V38-AL38 -> 0 | BC38: =G38+W38-AM38 -> 0 | BD38: =H38+X38-AN38 -> 0 | BE38: =I38+Y38-AO38 -> 0 | ... BH38: =L38+AB38-AR38 -> 0 | BI38: =+P38+AF38-AV38 -> 0 | BJ38: =N38+AD38-AT38 -> 0 | BK38: =O38+AE38-AU38 -> 0 | BL38: =P38+AF38-AV38 -> 0 | BM38: =Q38+AG38-AW38 -> 0 | BN38: 5000 | BO38: =+AL38*2500 -> 0 | BP38: =+AM38*60000 -> 0 | BQ38: =+AN38*3000 -> 0 | BR38: =+AO38*6000 -> 0 | BS38: =+AP38*8000 -> 0 | BT38: =+AQ38*8000 -> 0 | BU38: =+AR38*150000 -> 0 | BV38: =+AS38*3000 -> 0 | BW38: =+AT38*25000 -> 0 | BX38: =+AU38*200000 -> 0 | BY38: =+AV38*8000 -> 0 | BZ38: =+AW38*1.5 -> 0 | CC38: =+AH38*16 -> 80 | CD38: =+AI38*12+12 -> 120 | CE38: =+AJ38*3 -> 105 | CF38: =+CC38+CD38+CE38 -> 305 | CG38: =+BN38*75061/1000 -> 375305 | CH38: =+BO38+BP38+BQ38+BR38+BS38+BT38+BU38+BV38+BW38+BX38+BY38+CA38+CB38 -> 0 | CI38: =+CG38-CF38-CH38 -> 375000 | CR38: =+A38 -> SANDRA MILENA ANTOLINES | CS38: CC-1.102.348.573 | CT38: =+BN38 -> 5000 | CU38: =+AW38 -> 0 | CW38: =+CV38*230 -> 0 | CX38: 3.2 | CY38: 2.6 | CZ38: =+CX38*6500+CY38*3500 -> 29900 | DB38: =+CT38*75 -> 375000 | DC38: =+CI38 -> 375000 | DD38: =+CI38+CZ38+CW38 -> 404900
A39: SANDRA MORENO | B39: 0.95 | C39: 0.81 | D39: 3.15 | E39: 0 | F39: 0 | G39: 0 | H39: 0 | I39: 0 | J39: 0 | K39: 0 | L39: 0 | M39: 0 | N39: 0 | O39: 0 | P39: 0 | Q39: 0 | R39: 5 | S39: 9 | T39: 35 | U39: 4 | AH39: 5.2 | AI39: 9.36 | AJ39: 36.4 | AK39: 4 | AX39: =B39+R39-AH39 -> 0.75 | AY39: =C39+S39-AI39 -> 0.45 | AZ39: =D39+T39-AJ39 -> 1.75 | BA39: =E39+U39-AK39 -> 0 | BB39: =F39+V39-AL39 -> 0 | BC39: =G39+W39-AM39 -> 0 | BD39: =H39+X39-AN39 -> 0 | BE39: =I39+Y39-AO39 -> 0 | ... BH39: =L39+AB39-AR39 -> 0 | BI39: =+P39+AF39-AV39 -> 0 | BJ39: =N39+AD39-AT39 -> 0 | BK39: =O39+AE39-AU39 -> 0 | BL39: =P39+AF39-AV39 -> 0 | BM39: =Q39+AG39-AW39 -> 0 | BN39: 5200 | BO39: =+AL39*2500 -> 0 | BP39: =+AM39*60000 -> 0 | BQ39: =+AN39*3000 -> 0 | BR39: =+AO39*6000 -> 0 | BS39: =+AP39*8000 -> 0 | BT39: =+AQ39*8000 -> 0 | BU39: =+AR39*150000 -> 0 | BV39: =+AS39*3000 -> 0 | BW39: =+AT39*25000 -> 0 | BX39: =+AU39*200000 -> 0 | BY39: =+AV39*8000 -> 0 | BZ39: =+AW39*1.5 -> 0 | CC39: =+AH39*16 -> 83.2 | CD39: =+AI39*12+12.48 -> 124.8 | CE39: =+AJ39*3 -> 109.2 | CF39: =+CC39+CD39+CE39 -> 317.2 | CG39: =+BN39*75061/1000 -> 390317.2 | CH39: =+BO39+BP39+BQ39+BR39+BS39+BT39+BU39+BV39+BW39+BX39+BY39+CA39+CB39 -> 0 | CI39: =+CG39-CF39-CH39 -> 390000 | CR39: =+A39 -> SANDRA MORENO | CS39: V-18.355.048 | CT39: =+BN39 -> 5200 | CU39: =+AW39 -> 0 | CW39: =+CV39*230 -> 0 | CX39: 2.6 | CY39: 4.1 | CZ39: =+CX39*6500+CY39*3500 -> 31250 | DB39: =+CT39*75 -> 390000 | DC39: =+CI39 -> 390000 | DD39: =+CI39+CZ39+CW39 -> 421250
A40: =+'[1]SEMANA DEL 13 AL 20 '!A43 -> YENDER PADILLA | B40: 0 | C40: 0 | D40: 0 | E40: 0 | F40: 0 | G40: 0 | H40: 0 | I40: 0 | J40: 0 | K40: 0 | L40: 0 | M40: 0 | N40: 0 | O40: 0 | P40: 0 | Q40: 0 | R40: 5 | S40: 9 | T40: 35 | U40: 4 | AH40: 5 | AI40: 9 | AJ40: 35 | AK40: 4 | AX40: =B40+R40-AH40 -> 0 | AY40: =C40+S40-AI40 -> 0 | AZ40: =D40+T40-AJ40 -> 0 | BA40: =E40+U40-AK40 -> 0 | BB40: =F40+V40-AL40 -> 0 | BC40: =G40+W40-AM40 -> 0 | BD40: =H40+X40-AN40 -> 0 | BE40: =I40+Y40-AO40 -> 0 | ... BH40: =L40+AB40-AR40 -> 0 | BI40: =+P40+AF40-AV40 -> 0 | BJ40: =N40+AD40-AT40 -> 0 | BK40: =O40+AE40-AU40 -> 0 | BL40: =P40+AF40-AV40 -> 0 | BM40: =Q40+AG40-AW40 -> 0 | BN40: 5000 | BO40: =+AL40*2500 -> 0 | BP40: =+AM40*60000 -> 0 | BQ40: =+AN40*3000 -> 0 | BR40: =+AO40*6000 -> 0 | BS40: =+AP40*8000 -> 0 | BT40: =+AQ40*8000 -> 0 | BU40: =+AR40*150000 -> 0 | BV40: =+AS40*3000 -> 0 | BW40: =+AT40*25000 -> 0 | BX40: =+AU40*200000 -> 0 | BY40: =+AV40*8000 -> 0 | BZ40: =+AW40*1.5 -> 0 | CC40: =+AH40*16 -> 80 | CD40: =+AI40*12+12 -> 120 | CE40: =+AJ40*3 -> 105 | CF40: =+CC40+CD40+CE40 -> 305 | CG40: =+BN40*75061/1000 -> 375305 | CH40: =+BO40+BP40+BQ40+BR40+BS40+BT40+BU40+BV40+BW40+BX40+BY40+CA40+CB40 -> 0 | CI40: =+CG40-CF40-CH40 -> 375000 | CR40: =+A40 -> YENDER PADILLA | CS40: CC-1.092.340.667 | CT40: =+BN40 -> 5000 | CU40: =+AW40 -> 0 | CW40: =+CV40*230 -> 0 | CX40: 3.8 | CY40: 5.7 | CZ40: =+CX40*6500+CY40*3500 -> 44650 | DB40: =+CT40*75 -> 375000 | DC40: =+CI40 -> 375000 | DD40: =+CI40+CZ40+CW40 -> 419650
A41: YEFERSON CONTRERAS | E41: 0 | F41: 0 | G41: 0 | H41: 0 | I41: 0 | J41: 0 | K41: 0 | L41: 0 | M41: 0 | N41: 0 | O41: 0 | P41: 0 | Q41: 0 | AX41: =B41+R41-AH41 -> 0 | AY41: =C41+S41-AI41 -> 0 | AZ41: =D41+T41-AJ41 -> 0 | BA41: =E41+U41-AK41 -> 0 | BB41: =F41+V41-AL41 -> 0 | BC41: =G41+W41-AM41 -> 0 | BD41: =H41+X41-AN41 -> 0 | BE41: =I41+Y41-AO41 -> 0 | ... BH41: =L41+AB41-AR41 -> 0 | BI41: =+P41+AF41-AV41 -> 0 | BJ41: =N41+AD41-AT41 -> 0 | BK41: =O41+AE41-AU41 -> 0 | BL41: =P41+AF41-AV41 -> 0 | BM41: =Q41+AG41-AW41 -> 0
A42: =+'[1]SEMANA DEL 13 AL 20 '!A44 -> YARIRETH ROA | B42: 0.4 | C42: 0.725 | D42: 2.8 | E42: 0 | F42: 0 | G42: 0 | H42: 0 | I42: 0 | J42: 0 | K42: 0 | L42: 0 | M42: 0 | N42: 0 | O42: 0 | P42: 0 | Q42: 0 | R42: 12 | S42: 21.6 | T42: 84 | U42: 10 | Z42: 2 | AH42: 11.25 | AI42: 20.25 | AJ42: 78.75 | AK42: 9 | AP42: 2 | AX42: =B42+R42-AH42 -> 1.15 | AY42: =C42+S42-AI42 -> 2.075 | AZ42: =D42+T42-AJ42 -> 8.05 | BA42: =E42+U42-AK42 -> 1 | BB42: =F42+V42-AL42 -> 0 | BC42: =G42+W42-AM42 -> 0 | BD42: =H42+X42-AN42 -> 0 | BE42: =I42+Y42-AO42 -> 0 | ... BH42: =L42+AB42-AR42 -> 0 | BI42: =+P42+AF42-AV42 -> 0 | BJ42: =N42+AD42-AT42 -> 0 | BK42: =O42+AE42-AU42 -> 0 | BL42: =P42+AF42-AV42 -> 0 | BM42: =Q42+AG42-AW42 -> 0 | BN42: 11250 | BO42: =+AL42*2500 -> 0 | BP42: =+AM42*60000 -> 0 | BQ42: =+AN42*3000 -> 0 | BR42: =+AO42*6000 -> 0 | BS42: =+AP42*8000 -> 16000 | BT42: =+AQ42*8000 -> 0 | BU42: =+AR42*150000 -> 0 | BV42: =+AS42*3000 -> 0 | BW42: =+AT42*25000 -> 0 | BX42: =+AU42*200000 -> 0 | BY42: =+AV42*8000 -> 0 | BZ42: =+AW42*1.5 -> 0 | CC42: =+AH42*16 -> 180 | CD42: =+AI42*12+27 -> 270 | CE42: =+AJ42*3 -> 236.25 | CF42: =+CC42+CD42+CE42 -> 686.25 | CG42: =+BN42*75061/1000 -> 844436.25 | CH42: =+BO42+BP42+BQ42+BR42+BS42+BT42+BU42+BV42+BW42+BX42+BY42+CA42+CB42 -> 16000 | CI42: =+CG42-CF42-CH42 -> 827750 | CR42: =+A42 -> YARIRETH ROA | CS42: V-14,975,665 | CT42: =+BN42 -> 11250 | CU42: =+AW42 -> 0 | CW42: =+CV42*230 -> 0 | CX42: 2.8 | CY42: 5.5 | CZ42: =+CX42*6500+CY42*3500 -> 37450 | DB42: =+CT42*75 -> 843750 | DC42: =+CI42 -> 827750 | DD42: =+CI42+CZ42+CW42 -> 865200
A43: =+'[1]SEMANA DEL 13 AL 20 '!A45 -> YOLI BECERRA | B43: 0 | C43: 0 | D43: 3.4 | E43: 0 | F43: 0 | G43: 0 | H43: 0 | I43: 0 | J43: 0 | K43: 0 | L43: 0 | M43: 0 | N43: 0 | O43: 0 | P43: 0 | Q43: 0 | R43: 3 | S43: 5.4 | T43: 17.6 | U43: 3 | AX43: =B43+R43-AH43 -> 3 | AY43: =C43+S43-AI43 -> 5.4 | AZ43: =D43+T43-AJ43 -> 21 | BA43: =E43+U43-AK43 -> 3 | BB43: =F43+V43-AL43 -> 0 | BC43: =G43+W43-AM43 -> 0 | BD43: =H43+X43-AN43 -> 0 | BE43: =I43+Y43-AO43 -> 0 | ... BH43: =L43+AB43-AR43 -> 0 | BI43: =+P43+AF43-AV43 -> 0 | BJ43: =N43+AD43-AT43 -> 0 | BK43: =O43+AE43-AU43 -> 0 | BL43: =P43+AF43-AV43 -> 0 | BM43: =Q43+AG43-AW43 -> 0 | BO43: =+AL43*2500 -> 0 | BP43: =+AM43*60000 -> 0 | BQ43: =+AN43*3000 -> 0 | BR43: =+AO43*6000 -> 0 | BS43: =+AP43*8000 -> 0 | BT43: =+AQ43*8000 -> 0 | BU43: =+AR43*150000 -> 0 | BV43: =+AS43*3000 -> 0 | BW43: =+AT43*25000 -> 0 | BX43: =+AU43*200000 -> 0 | BY43: =+AV43*8000 -> 0 | BZ43: =+AW43*1.5 -> 0 | CC43: =+AH43*16 -> 0 | CD43: =+AI43*12 -> 0 | CE43: =+AJ43*3 -> 0 | CF43: =+CC43+CD43+CE43 -> 0 | CG43: =+BN43*75061/1000 -> 0 | CH43: =+BO43+BP43+BQ43+BR43+BS43+BT43+BU43+BV43+BW43+BX43+BY43+CA43+CB43 -> 0 | CI43: =+CG43-CF43-CH43 -> 0 | CR43: =+A43 -> YOLI BECERRA | CS43: V-11.017.442 | CT43: =+BN43 -> 0 | CU43: =+AW43 -> 0 | CW43: =+CV43*230 -> 0 | CZ43: =+CX43*6500+CY43*3500 -> 0 | DB43: =+CT43*75 -> 0 | DC43: =+CI43 -> 0 | DD43: =+CI43+CZ43+CW43 -> 0
A44: =+'[1]SEMANA DEL 13 AL 20 '!A46 -> MUESTRAS SRA MARIA | B44: 0 | C44: 0 | D44: 0 | E44: 0 | F44: 0 | G44: 0 | H44: 0 | I44: 0 | J44: 0 | K44: 0 | L44: 0 | M44: 0 | N44: 0 | O44: 0 | P44: 0 | Q44: 0 | R44: 0 | S44: 0 | T44: 0 | U44: 0 | AX44: =B44+R44-AH44 -> 0 | AY44: =C44+S44-AI44 -> 0 | AZ44: =D44+T44-AJ44 -> 0 | BA44: =E44+U44-AK44 -> 0 | BB44: =F44+V44-AL44 -> 0 | BC44: =G44+W44-AM44 -> 0 | BD44: =H44+X44-AN44 -> 0 | BE44: =I44+Y44-AO44 -> 0 | ... BH44: =L44+AB44-AR44 -> 0 | BI44: =+P44+AF44-AV44 -> 0 | BJ44: =N44+AD44-AT44 -> 0 | BK44: =O44+AE44-AU44 -> 0 | BL44: =P44+AF44-AV44 -> 0 | BM44: =Q44+AG44-AW44 -> 0 | BO44: =+AL44*2500 -> 0 | BP44: =+AM44*60000 -> 0 | BQ44: =+AN44*3000 -> 0 | BR44: =+AO44*6000 -> 0 | BS44: =+AP44*8000 -> 0 | BT44: =+AQ44*8000 -> 0 | BU44: =+AR44*150000 -> 0 | BV44: =+AS44*3000 -> 0 | BW44: =+AT44*25000 -> 0 | BX44: =+AU44*200000 -> 0 | BY44: =+AV44*8000 -> 0 | BZ44: =+AW44*1.5 -> 0 | CC44: =+AH44*16 -> 0 | CD44: =+AI44*12 -> 0 | CE44: =+AJ44*3 -> 0 | CF44: =+CC44+CD44+CE44 -> 0 | CG44: =+BN44*75061/1000 -> 0 | CH44: =+BO44+BP44+BQ44+BR44+BS44+BT44+BU44+BV44+BW44+BX44+BY44+CA44+CB44 -> 0 | CI44: =+CG44-CF44-CH44 -> 0 | CR44: =+A44 -> MUESTRAS SRA MARIA | CU44: =+AW44 -> 0 | CW44: =+CV44*230 -> 0 | CZ44: =+CX44*6500+CY44*3500 -> 0 | DB44: =+CT44*75 -> 0 | DC44: =+CI44 -> 0 | DD44: =+CI44+CZ44+CW44 -> 0
A45: =+'[1]SEMANA DEL 13 AL 20 '!A47 -> 0 | B45: =SUM(B5:B44) -> 7.446 | C45: =SUM(C5:C44) -> 13.973 | D45: =SUM(D5:D44) -> 82.948 | E45: =SUM(E5:E44) -> 3 | F45: =SUM(F5:F44) -> 0 | G45: =SUM(G5:G44) -> 0 | H45: =SUM(H5:H44) -> 0 | I45: =SUM(I5:I44) -> 4 | ... CI45: =SUM(CI5:CI44) -> 15196750 | CR45: =+A45 -> 0 | CT45: =SUM(CT5:CT43) -> 205450 | CU45: =SUM(CU5:CU43) -> 0 | CV45: =SUM(CV5:CV43) -> 3907 | CW45: =SUM(CW5:CW43) -> 898610 | CX45: =SUM(CX5:CX44) -> 113.4 | CY45: =SUM(CY5:CY44) -> 139.6 | CZ45: =SUM(CZ5:CZ43) -> 1225700 | DA45: =SUM(DA5:DA43) -> 0 | DB45: =SUM(DB5:DB43) -> 15408750 | DC45: =SUM(DC5:DC43) -> 15196750 | DD45: =SUM(DD5:DD43) -> 17321060
CI46: =+CI45+CH45 -> 15408750 | CR46: =+A46 -> 0
CS47: TOTAL TABACOS | CU47: =+CT45+CU45+CV45 -> 209357

Sheet SEMANA DEL 7 AL 14
A1: SEMANA 10 DEL 7 AL 14 DE MARZO 2026 | CL1: =+A1 -> SEMANA 10 DEL 7 AL 14 DE MARZO 2026 | CS1: =+A1 -> SEMANA 10 DEL 7 AL 14 DE MARZO 2026
A2: FABRIQUINES SEMANA # 10 | CL2: =+A2 -> FABRIQUINES SEMANA # 10 | CS2: =+CL2 -> FABRIQUINES SEMANA # 10
A3: PRODUCCION # 7 | B3: S A L D O S I N I C I A L E S | R3: L L E V A N | AH3: P A G A N | AX3: SALDOS | BW3: SUMINISTROS | CH3: OTRAS | CI3: PESOS | CL3: =+A3 -> PRODUCCION # 7 | CS3: =+A3 -> PRODUCCION # 7
A4: NOMBRE | B4: CAPA | C4: CAPOTE | D4: PIC | E4: CESTA | F4: SACAS | G4: GOMA | H4: MAR | I4: PAPEL | J4: REST | K4: TABL | L4: MAQ | M4: TRAP | N4: SILLA | O4: PRENS | P4: CORT | Q4: REZAGOS | R4: CAPA | S4: CAPOTE | T4: PIC | U4: CESTA | V4: SACAS | W4: GOMA | X4: MAR | Y4: PAPEL | Z4: REST | AA4: TABL | AB4: MAQ | AC4: TRAP | AD4: PACORA | AE4: PRENS | AF4: CUCHILLAS | AG4: REZAGOS | AH4: CAPA | AI4: CAPOTE | AJ4: PIC | AK4: CESTA | AL4: SACAS | AM4: GOMA | AN4: MAR | AO4: PAPEL | AP4: REST | AQ4: TABL | AR4: MAQ | AS4: TRAP | AT4: PACORA | AU4: PRENS | AV4: CORT | AW4: REZAGOS | AX4: CAPA | AY4: CAPOTE | AZ4: PIC | BA4: CESTA | BB4: SACAS | BC4: GOMA | BD4: MAR | BE4: PAPPEL | BF4: RESIST | BG4: MAQUINA | BH4: TRAPOS | BI4: PACORAS | BJ4: PRENSA | BK4: PRENS | BL4: CORT | BM4: REZAGOS | BN4: TAB.ENTREG. | BO4: SACAS | BP4: GOMA | BQ4: MAR | BR4: PAPEL | BS4: REST | BT4: TABL | BU4: MAQ | BV4: TRAP | BW4: PACORA | BX4: PRENS | BY4: PACORA | BZ4: REZAGOS | CA4: PRESTAMOS | CB4: AHORROS | CC4: PRECIO CAPA | CD4: PRECIO CAPOTE | CE4: PRECIO PICADURA | CF4: TOTAL MATERIAL | CG4: PRECIO TAB. | CH4: DEDUCCIONES | CI4: TOTAL A PAGAR $ | CL4: TABACOS RECIBIDOS | CN4: =+#REF!+#REF!+#REF! -> #REF! | CR4: NOMBRE Y APELLIDOS | CS4: CEDULA | CT4: TABACOS | CU4: REZAGOS | CW4: PRECIO | CX4: RECORTE | CY4: VENA | CZ4: TOTAL BS | DA4: TOTAL | DB4: BS TABACOS | DC4: TOTAL PAGAR
A5: =+'SEMANA DEL 2 AL 7-3-26'!A5 -> ALCIDES CORREA | B5: =+'SEMANA DEL 2 AL 7-3-26'!AX5 -> 0 | C5: =+'SEMANA DEL 2 AL 7-3-26'!AY5 -> 0 | D5: =+'SEMANA DEL 2 AL 7-3-26'!AZ5 -> 0 | E5: =+'SEMANA DEL 2 AL 7-3-26'!BA5 -> 0 | F5: =+'SEMANA DEL 2 AL 7-3-26'!BB5 -> 0 | G5: =+'SEMANA DEL 2 AL 7-3-26'!BC5 -> 0 | H5: =+'SEMANA DEL 2 AL 7-3-26'!BD5 -> 0 | I5: =+'SEMANA DEL 2 AL 7-3-26'!BE5 -> 0 | ... Q5: =+'SEMANA DEL 2 AL 7-3-26'!BM5 -> 0 | R5: 10 | S5: 18 | T5: 70 | U5: 8 | W5: 0.25 | AX5: =+B5+R5-AH5 -> 10 | AY5: =+C5+S5-AI5 -> 18 | AZ5: =+D5+T5-AJ5 -> 70 | BA5: =+E5+U5-AK5 -> 8 | BB5: =+F5+V5-AL5 -> 0 | BC5: =+G5+W5-AM5 -> 0.25 | BD5: =+H5+X5-AN5 -> 0 | BE5: =+I5+Y5-AO5 -> 0 | ... BM5: =+Q5+AG5-AW5 -> 0 | BO5: =+AL5*2500 -> 0 | BP5: =+AM5*60000 -> 0 | BQ5: =+AN5*3000 -> 0 | BR5: =+AO5*6000 -> 0 | BS5: =+AP5*8000 -> 0 | BT5: =+AQ5*8000 -> 0 | BU5: =+AR5*150000 -> 0 | BV5: =+AS5*3000 -> 0 | BW5: =+AT5*8000 -> 0 | BX5: =+AU5*200000 -> 0 | BY5: =+AV5*8000 -> 0 | BZ5: =+AW5*1.5 -> 0 | CC5: =+AH5*16 -> 0 | CD5: =+AI5*12 -> 0 | CE5: =+AJ5*3 -> 0 | CF5: =+CC5+CD5+CE5 -> 0 | CG5: =+BN5*85061/1000 -> 0 | CH5: =+BO5+BP5+BQ5+BR5+BS5+BT5+BU5+BV5+BW5+BX5+BY5+CA5+CB5 -> 0 | CI5: =+CG5-CF5-CH5 -> 0 | CR5: =+A5 -> ALCIDES CORREA | CS5: =+'SEMANA DEL 2 AL 7-3-26'!CS5 -> CC-88.193.514 | CT5: =+BN5 -> 0 | CU5: =+AW5 -> 0 | CW5: =+CV5*230 -> 0 | CZ5: =+CX5*6500+CY5*3500 -> 0 | DA5: =+CT5*75 -> 0 | DB5: =+CI5 -> 0 | DC5: =+CI5+CW5+CZ5 -> 0
A6: =+'SEMANA DEL 2 AL 7-3-26'!A6 -> ALBA SANABRIA | B6: =+'SEMANA DEL 2 AL 7-3-26'!AX6 -> 0.25 | C6: =+'SEMANA DEL 2 AL 7-3-26'!AY6 -> 0.45 | D6: =+'SEMANA DEL 2 AL 7-3-26'!AZ6 -> 12.25 | E6: =+'SEMANA DEL 2 AL 7-3-26'!BA6 -> 0 | F6: =+'SEMANA DEL 2 AL 7-3-26'!BB6 -> 0 | G6: =+'SEMANA DEL 2 AL 7-3-26'!BC6 -> 0 | H6: =+'SEMANA DEL 2 AL 7-3-26'!BD6 -> 0 | I6: =+'SEMANA DEL 2 AL 7-3-26'!BE6 -> 0 | ... Q6: =+'SEMANA DEL 2 AL 7-3-26'!BM6 -> 0 | R6: 5 | S6: 9 | T6: 35 | U6: 4 | W6: 0.25 | AH6: 5 | AI6: 9 | AJ6: 35 | AK6: 4 | AM6: 0.25 | AX6: =+B6+R6-AH6 -> 0.25 | AY6: =+C6+S6-AI6 -> 0.45 | AZ6: =+D6+T6-AJ6 -> 12.25 | BA6: =+E6+U6-AK6 -> 0 | BB6: =+F6+V6-AL6 -> 0 | BC6: =+G6+W6-AM6 -> 0 | BD6: =+H6+X6-AN6 -> 0 | BE6: =+I6+Y6-AO6 -> 0 | ... BM6: =+Q6+AG6-AW6 -> 0 | BN6: 5000 | BO6: =+AL6*2500 -> 0 | BP6: =+AM6*60000 -> 15000 | BQ6: =+AN6*3000 -> 0 | BR6: =+AO6*6000 -> 0 | BS6: =+AP6*8000 -> 0 | BT6: =+AQ6*8000 -> 0 | BU6: =+AR6*150000 -> 0 | BV6: =+AS6*3000 -> 0 | BW6: =+AT6*8000 -> 0 | BX6: =+AU6*200000 -> 0 | BY6: =+AV6*8000 -> 0 | BZ6: =+AW6*1.5 -> 0 | CC6: =+AH6*16 -> 80 | CD6: =+AI6*12+12 -> 120 | CE6: =+AJ6*3 -> 105 | CF6: =+CC6+CD6+CE6 -> 305 | CG6: =+BN6*85061/1000 -> 425305 | CH6: =+BO6+BP6+BQ6+BR6+BS6+BT6+BU6+BV6+BW6+BX6+BY6+CA6+CB6 -> 15000 | CI6: =+CG6-CF6-CH6 -> 410000 | CR6: =+A6 -> ALBA SANABRIA | CS6: =+'SEMANA DEL 2 AL 7-3-26'!CS6 -> V-20.427.079 | CT6: =+BN6 -> 5000 | CU6: =+AW6 -> 0 | CW6: =+CV6*230 -> 0 | CX6: 3.1 | CY6: 3.1 | CZ6: =+CX6*6500+CY6*3500 -> 31000 | DA6: =+CT6*75 -> 375000 | DB6: =+CI6 -> 410000 | DC6: =+CI6+CW6+CZ6 -> 441000
A7: =+'SEMANA DEL 2 AL 7-3-26'!A7 -> BLANCA ALVARADO | B7: =+'SEMANA DEL 2 AL 7-3-26'!AX7 -> 0 | C7: =+'SEMANA DEL 2 AL 7-3-26'!AY7 -> 0 | D7: =+'SEMANA DEL 2 AL 7-3-26'!AZ7 -> 0 | E7: =+'SEMANA DEL 2 AL 7-3-26'!BA7 -> 0 | F7: =+'SEMANA DEL 2 AL 7-3-26'!BB7 -> 0 | G7: =+'SEMANA DEL 2 AL 7-3-26'!BC7 -> 0 | H7: =+'SEMANA DEL 2 AL 7-3-26'!BD7 -> 0 | I7: =+'SEMANA DEL 2 AL 7-3-26'!BE7 -> 0 | ... Q7: =+'SEMANA DEL 2 AL 7-3-26'!BM7 -> 0 | R7: 0 | S7: 0 | T7: 0 | U7: 0 | AX7: =+B7+R7-AH7 -> 0 | AY7: =+C7+S7-AI7 -> 0 | AZ7: =+D7+T7-AJ7 -> 0 | BA7: =+E7+U7-AK7 -> 0 | BB7: =+F7+V7-AL7 -> 0 | BC7: =+G7+W7-AM7 -> 0 | BD7: =+H7+X7-AN7 -> 0 | BE7: =+I7+Y7-AO7 -> 0 | ... BM7: =+Q7+AG7-AW7 -> 0 | BO7: =+AL7*2500 -> 0 | BP7: =+AM7*60000 -> 0 | BQ7: =+AN7*3000 -> 0 | BR7: =+AO7*6000 -> 0 | BS7: =+AP7*8000 -> 0 | BT7: =+AQ7*8000 -> 0 | BU7: =+AR7*150000 -> 0 | BV7: =+AS7*3000 -> 0 | BW7: =+AT7*8000 -> 0 | BX7: =+AU7*200000 -> 0 | BY7: =+AV7*8000 -> 0 | BZ7: =+AW7*1.5 -> 0 | CC7: =+AH7*16 -> 0 | CD7: =+AI7*12 -> 0 | CE7: =+AJ7*3 -> 0 | CF7: =+CC7+CD7+CE7 -> 0 | CG7: =+BN7*85061/1000 -> 0 | CH7: =+BO7+BP7+BQ7+BR7+BS7+BT7+BU7+BV7+BW7+BX7+BY7+CA7+CB7 -> 0 | CI7: =+CG7-CF7-CH7 -> 0 | CR7: =+A7 -> BLANCA ALVARADO | CS7: =+'SEMANA DEL 2 AL 7-3-26'!CS7 -> CC.60.402,510 | CT7: =+BN7 -> 0 | CU7: =+AW7 -> 0 | CW7: =+CV7*230 -> 0 | CZ7: =+CX7*6500+CY7*3500 -> 0 | DA7: =+CT7*75 -> 0 | DB7: =+CI7 -> 0 | DC7: =+CI7+CW7+CZ7 -> 0
A8: =+'SEMANA DEL 2 AL 7-3-26'!A8 -> ESPERANZA REY | B8: =+'SEMANA DEL 2 AL 7-3-26'!AX8 -> 3 | C8: =+'SEMANA DEL 2 AL 7-3-26'!AY8 -> 5.4 | D8: =+'SEMANA DEL 2 AL 7-3-26'!AZ8 -> 21 | E8: =+'SEMANA DEL 2 AL 7-3-26'!BA8 -> 3 | F8: =+'SEMANA DEL 2 AL 7-3-26'!BB8 -> 0 | G8: =+'SEMANA DEL 2 AL 7-3-26'!BC8 -> 0 | H8: =+'SEMANA DEL 2 AL 7-3-26'!BD8 -> 0 | I8: =+'SEMANA DEL 2 AL 7-3-26'!BE8 -> 0 | ... Q8: =+'SEMANA DEL 2 AL 7-3-26'!BM8 -> 0 | R8: 0 | S8: 0 | T8: 0 | U8: 0 | AX8: =+B8+R8-AH8 -> 3 | AY8: =+C8+S8-AI8 -> 5.4 | AZ8: =+D8+T8-AJ8 -> 21 | BA8: =+E8+U8-AK8 -> 3 | BB8: =+F8+V8-AL8 -> 0 | BC8: =+G8+W8-AM8 -> 0 | BD8: =+H8+X8-AN8 -> 0 | BE8: =+I8+Y8-AO8 -> 0 | ... BM8: =+Q8+AG8-AW8 -> 0 | BO8: =+AL8*2500 -> 0 | BP8: =+AM8*60000 -> 0 | BQ8: =+AN8*3000 -> 0 | BR8: =+AO8*6000 -> 0 | BS8: =+AP8*8000 -> 0 | BT8: =+AQ8*8000 -> 0 | BU8: =+AR8*150000 -> 0 | BV8: =+AS8*3000 -> 0 | BW8: =+AT8*8000 -> 0 | BX8: =+AU8*200000 -> 0 | BY8: =+AV8*8000 -> 0 | BZ8: =+AW8*1.5 -> 0 | CC8: =+AH8*16 -> 0 | CD8: =+AI8*12 -> 0 | CE8: =+AJ8*3 -> 0 | CF8: =+CC8+CD8+CE8 -> 0 | CG8: =+BN8*85061/1000 -> 0 | CH8: =+BO8+BP8+BQ8+BR8+BS8+BT8+BU8+BV8+BW8+BX8+BY8+CA8+CB8 -> 0 | CI8: =+CG8-CF8-CH8 -> 0 | CR8: =+A8 -> ESPERANZA REY | CS8: =+'SEMANA DEL 2 AL 7-3-26'!CS8 -> V-22.633.248 | CT8: =+BN8 -> 0 | CU8: =+AW8 -> 0 | CW8: =+CV8*230 -> 0 | CZ8: =+CX8*6500+CY8*3500 -> 0 | DA8: =+CT8*75 -> 0 | DB8: =+CI8 -> 0 | DC8: =+CI8+CW8+CZ8 -> 0
A9: =+'SEMANA DEL 2 AL 7-3-26'!A9 -> ELIZABETH REYES SERRANO | B9: =+'SEMANA DEL 2 AL 7-3-26'!AX9 -> 0 | C9: =+'SEMANA DEL 2 AL 7-3-26'!AY9 -> 0 | D9: =+'SEMANA DEL 2 AL 7-3-26'!AZ9 -> 0 | E9: =+'SEMANA DEL 2 AL 7-3-26'!BA9 -> 0 | F9: =+'SEMANA DEL 2 AL 7-3-26'!BB9 -> 0 | G9: =+'SEMANA DEL 2 AL 7-3-26'!BC9 -> 0 | H9: =+'SEMANA DEL 2 AL 7-3-26'!BD9 -> 0 | I9: =+'SEMANA DEL 2 AL 7-3-26'!BE9 -> 0 | ... Q9: =+'SEMANA DEL 2 AL 7-3-26'!BM9 -> 0 | R9: 7 | S9: 12.6 | T9: 49 | U9: 6 | AH9: 7 | AI9: 12.6 | AJ9: 49 | AK9: 6 | AX9: =+B9+R9-AH9 -> 0 | AY9: =+C9+S9-AI9 -> 0 | AZ9: =+D9+T9-AJ9 -> 0 | BA9: =+E9+U9-AK9 -> 0 | BB9: =+F9+V9-AL9 -> 0 | BC9: =+G9+W9-AM9 -> 0 | BD9: =+H9+X9-AN9 -> 0 | BE9: =+I9+Y9-AO9 -> 0 | ... BM9: =+Q9+AG9-AW9 -> 0 | BN9: 7000 | BO9: =+AL9*2500 -> 0 | BP9: =+AM9*60000 -> 0 | BQ9: =+AN9*3000 -> 0 | BR9: =+AO9*6000 -> 0 | BS9: =+AP9*8000 -> 0 | BT9: =+AQ9*8000 -> 0 | BU9: =+AR9*150000 -> 0 | BV9: =+AS9*3000 -> 0 | BW9: =+AT9*8000 -> 0 | BX9: =+AU9*200000 -> 0 | BY9: =+AV9*8000 -> 0 | BZ9: =+AW9*1.5 -> 0 | CA9: 50000 | CC9: =+AH9*16 -> 112 | CD9: =+AI9*12+16.8 -> 168 | CE9: =+AJ9*3 -> 147 | CF9: =+CC9+CD9+CE9 -> 427 | CG9: =+BN9*85061/1000 -> 595427 | CH9: =+BO9+BP9+BQ9+BR9+BS9+BT9+BU9+BV9+BW9+BX9+BY9+CA9+CB9 -> 50000 | CI9: =+CG9-CF9-CH9 -> 545000 | CR9: =+A9 -> ELIZABETH REYES SERRANO | CS9: =+'SEMANA DEL 2 AL 7-3-26'!CS9 -> V-15.956.387 | CT9: =+BN9 -> 7000 | CU9: =+AW9 -> 0 | CV9: 500 | CW9: =+CV9*230 -> 115000 | CX9: 5.1 | CY9: 7 | CZ9: =+CX9*6500+CY9*3500 -> 57650 | DA9: =+CT9*75 -> 525000 | DB9: =+CI9 -> 545000 | DC9: =+CI9+CW9+CZ9 -> 717650
